Workbook

Sheet Petunjuk
A1: LEMBAR KODING PERTAHANAN MCP (v1.1) - untuk Section 6 / Tabel 16
A2: Korpus: 186 record MCP-spesifik setelah dedup putaran kedua (file final_corpus_ids_186.csv).
A4: CARA MENGISI
A5: 1. Kolom KUNING = diisi manusia. Kolom ABU-ABU = informasi. Kolom BIRU = rumus otomatis (jangan diedit).
A6: 2. Urutan kerja: baris "kandidat_agent" dulu, lalu "kandidat_cek_recall" (agent melabeli none, tetapi judul/abstrak menunjukkan pertahanan), lalu "scan_cepat" (cukup pastikan peran bukan pertahanan).
A7: 3. Isi kolom "peran" untuk semua baris. Kolom mekanisme dan evaluasi hanya untuk peran defense_primary, defense_secondary, dan proposal_only.
A8: 4. Kode evaluasi dari bagian metode/eksperimen teks lengkap, bukan dari judul atau abstrak. Tanpa teks lengkap: isi peran, nama, paradigma, mekanisme; kosongkan kolom evaluasi (teks_lengkap_tersedia = tidak).
A9: 5. Kolom "kutipan_adaptif" wajib bila adaptif = ya (maks 25 kata, persis dari paper). Kolom "lokasi_bukti" wajib untuk setiap entri yang dievaluasi.
A10: 6. Maturitas dihitung otomatis: L3 = spec_normatif atau produksi_bukti_publik; L2 = ada evaluasi independen; L1 = dievaluasi penulis sendiri; L0 = tanpa evaluasi (isi jenis_evaluasi = none). Jangan diisi manual.
A11: 7. Kolom "cek_konsistensi" harus kosong pada baris yang sudah selesai. Bila berisi PERIKSA, perbaiki isian.
A12: 8. Sheet "Ringkasan" menghitung semua statistik langsung dari Koding (dengan penyebut). Jangan salin angka dari ingatan.
A13: 9. Satu paper dengan beberapa pertahanan terpisah: duplikasi barisnya (salin baris, ubah nama_pertahanan), jangan menggabungkan.
A15: CONTOH PENGISIAN (bukan data nyata; kolom sama dengan sheet Koding)
B16: peran | C16: paradigma | D16: llm_dlm_keputusan | E16: titik_penegakan | F16: crossings | G16: kelas_diklaim | H16: kelas_dievaluasi | I16: jenis_evaluasi | J16: asal_set_serangan | K16: adaptif | L16: kutipan_adaptif | M16: lokasi_bukti | N16: deployment | O16: maturitas (hasil rumus)
B17: defense_primary | C17: isolation_containment | D17: tidak | E17: S | F17: R5 | G17: C5 | H17: C5 | I17: author_run | J17: authors_own | K17: tidak | L17: (kosong) | M17: Section 5, Table 3 | N17: prototype_open_source | O17: L1
B18: Contoh: sandbox subprocess yang dievaluasi penulis pada 20 kasus path traversal dengan set serangan buatan sendiri; tidak ada serangan yang disesuaikan terhadap sandbox, jadi adaptif = tidak.

Sheet Koding
A1: record_id | B1: judul | C1: tahun | D1: tier | E1: triase | F1: agent_role (referensi) | G1: tautan | H1: teks_lengkap_tersedia | I1: peran | J1: nama_pertahanan | K1: paradigma | L1: ringkasan_mekanisme (kata sendiri, maks 2 kalimat) | M1: llm_dlm_keputusan | N1: titik_penegakan | O1: crossings (R1-R7, pisah ;) | P1: kelas_diklaim (A1-D3, pisah ;) | Q1: kelas_dievaluasi (hanya yang ada eksperimen) | R1: jenis_evaluasi | S1: evaluator_independen (record_id) | T1: asal_set_serangan | U1: adaptif | V1: kutipan_adaptif (maks 25 kata) | W1: lokasi_bukti (bagian/tabel/hal.) | X1: deployment | Y1: biaya_utilitas | Z1: catatan | AA1: maturitas (otomatis) | AB1: cek_konsistensi (otomatis) | AC1: korpus_v5 | AD1: kode_eksklusi_v5 | AE1: catatan_audit_v5
A2: aditi-2025-model-context-protocol-vision-systems | B2: Model Context Protocol for Vision Systems: Audit, Security, and Protocol Extensions | C2: 2025 | D2: E2 | E2: kandidat_agent | F2: primary | G2: https://arxiv.org/abs/2509.22814 | H2: ya | I2: proposal_only | J2: unnamed:vision-protocol-extensions | K2: protocol_provision | L2: Usulan ekstensi skema semantik MCP dan validator prototipe untuk membatasi aksi visi di testbed terkontrol. | M2: tidak | N2: registry | O2: R2;R5 | P2: A3;B3;C5 | R2: none | T2: none | U2: n/a_tanpa_evaluasi | X2: none | Y2: not_reported | Z2: Proposal ekstensi protokol MCP dengan skema semantik dan validator prototipe tanpa evaluasi terhadap serangan. Catatan deployment: prototipe internal/eksperimental (belum dirilis secara publik). | AA2: =IF(I2="","",IF(OR(I2="attack",I2="survey_review",I2="benchmark_measurement",I2="position_other",I2="not_defense"),"n/a",IF(OR(X2="spec_normatif",X2="produksi_bukti_publik"),"L3",IF(ISNUMBER(SEARCH("independent",R2)),"L2",IF(R2="author_run","L1",IF(R2="none","L0","")))))) | AB2: =IF(I2="","",IF(AND(K2="deterministic_policy",M2="ya"),"PERIKSA: deterministic_policy tetapi LLM/ML ada dalam keputusan. ","")&IF(AND(U2="ya",V2=""),"PERIKSA: adaptif=ya wajib ada kutipan. ","")&IF(AND(R2="none",U2<>"n/a_tanpa_evaluasi",U2<>""),"PERIKSA: tanpa evaluasi, adaptif harus n/a. ","")&IF(AND(OR(R2="author_run",R2="author_run+independent",R2="independent_only"),Q2=""),"PERIKSA: isi kelas_dievaluasi. ","")&IF(AND(OR(R2="author_run",R2="author_run+independent",R2="independent_only"),W2=""),"PERIKSA: isi lokasi_bukti. ","")&IF(AND(H2="tidak",R2<>""),"PERIKSA: tanpa teks lengkap, kosongkan kolom evaluasi. ","")) | AC2: include
A3: alexander-2026-task-conditioned-least-privilege-learning | B3: Task-Conditioned Least-Privilege Learning for Executable Terminal and MCP Agents | C3: 2026 | D3: E2 | E3: kandidat_agent | F3: primary | G3: https://arxiv.org/abs/2608.18351 | H3: tidak | I3: not_defense | Z3: [AUDIT_v5_EXCLUDE: EC2] Dikeluarkan dari korpus MCP-spesifik oleh audit reviewer kedua v5. Pembelajaran least-privilege terminal/agen umum dengan MCP hanya alat pengganti insidental. | AA3: =IF(I3="","",IF(OR(I3="attack",I3="survey_review",I3="benchmark_measurement",I3="position_other",I3="not_defense"),"n/a",IF(OR(X3="spec_normatif",X3="produksi_bukti_publik"),"L3",IF(ISNUMBER(SEARCH("independent",R3)),"L2",IF(R3="author_run","L1",IF(R3="none","L0","")))))) | AB3: =IF(I3="","",IF(AND(K3="deterministic_policy",M3="ya"),"PERIKSA: deterministic_policy tetapi LLM/ML ada dalam keputusan. ","")&IF(AND(U3="ya",V3=""),"PERIKSA: adaptif=ya wajib ada kutipan. ","")&IF(AND(R3="none",U3<>"n/a_tanpa_evaluasi",U3<>""),"PERIKSA: tanpa evaluasi, adaptif harus n/a. ","")&IF(AND(OR(R3="author_run",R3="author_run+independent",R3="independent_only"),Q3=""),"PERIKSA: isi kelas_dievaluasi. ","")&IF(AND(OR(R3="author_run",R3="author_run+independent",R3="independent_only"),W3=""),"PERIKSA: isi lokasi_bukti. ","")&IF(AND(H3="tidak",R3<>""),"PERIKSA: tanpa teks lengkap, kosongkan kolom evaluasi. ","")) | AC3: exclude | AD3: EC2 | AE3: audit lanjutan; diterima koordinator
A4: alfonso-2026-mcp-seclint-open-source-static | B4: MCP-SecLint: An Open-Source Static Analyzer for Detecting Vulnerabilities in LLM Tool Integrations | C4: 2026 | D4: E1 | E4: kandidat_agent | F4: primary | G4: https://doi.org/10.1145/3806007.3810961 | H4: ya | I4: defense_primary | J4: MCP-SecLint | K4: content_inspection_static | L4: Penganalisis statis offline kode server MCP untuk mendeteksi eksekusi perintah berbahaya, token passthrough, dan endpoint tanpa autentikasi. | M4: tidak | N4: offline_analysis | O4: R4;R5 | P4: C5;C3 | Q4: C5;C3 | R4: author_run | T4: third_party_public | U4: tidak | W4: Abstract / hal. 1 | X4: none | Y4: not_reported | Z4: Penganalisis statis MCP-SecLint untuk mendeteksi dangerous sinks (C5) dan unauthenticated endpoints (C3) pada implementasi server MCP. Klaim C1 dicabut karena analisis statis kode server tidak menangani confused deputy planner. Catatan deployment: prototipe internal/eksperimental (belum dirilis secara publik). | AA4: =IF(I4="","",IF(OR(I4="attack",I4="survey_review",I4="benchmark_measurement",I4="position_other",I4="not_defense"),"n/a",IF(OR(X4="spec_normatif",X4="produksi_bukti_publik"),"L3",IF(ISNUMBER(SEARCH("independent",R4)),"L2",IF(R4="author_run","L1",IF(R4="none","L0","")))))) | AB4: =IF(I4="","",IF(AND(K4="deterministic_policy",M4="ya"),"PERIKSA: deterministic_policy tetapi LLM/ML ada dalam keputusan. ","")&IF(AND(U4="ya",V4=""),"PERIKSA: adaptif=ya wajib ada kutipan. ","")&IF(AND(R4="none",U4<>"n/a_tanpa_evaluasi",U4<>""),"PERIKSA: tanpa evaluasi, adaptif harus n/a. ","")&IF(AND(OR(R4="author_run",R4="author_run+independent",R4="independent_only"),Q4=""),"PERIKSA: isi kelas_dievaluasi. ","")&IF(AND(OR(R4="author_run",R4="author_run+independent",R4="independent_only"),W4=""),"PERIKSA: isi lokasi_bukti. ","")&IF(AND(H4="tidak",R4<>""),"PERIKSA: tanpa teks lengkap, kosongkan kolom evaluasi. ","")) | AC4: include
A5: alfredo-2026-attested-tool-server-admission-security | B5: Attested Tool-Server Admission: A Security Extension to the Model Context Protocol | C5: 2026 | D5: E2 | E5: kandidat_agent | F5: primary | G5: https://arxiv.org/abs/2605.24248 | H5: ya | I5: defense_primary | J5: mcp-attested | K5: integrity_provenance | L5: Mekanisme admisi server teratestasi kriptografis Ed25519 dengan validasi clearance assertion terhadap root trust pinned dan allowlist deny-by-default. | M5: tidak | N5: registry | O5: R7 | P5: B1;B2 | Q5: B1;B2 | R5: author_run | T5: authors_own | U5: tidak | W5: Sec 7.1; Sec 7.2; Tabel hal. 12 | X5: none | Y5: not_reported | Z5: Mekanisme admisi server teratestasi Ed25519 mcp-attested dengan allowlist deny-by-default, diuji pada 48 kasus tes hermetik & adversarial. Catatan deployment: prototipe internal/eksperimental (belum dirilis secara publik). | AA5: =IF(I5="","",IF(OR(I5="attack",I5="survey_review",I5="benchmark_measurement",I5="position_other",I5="not_defense"),"n/a",IF(OR(X5="spec_normatif",X5="produksi_bukti_publik"),"L3",IF(ISNUMBER(SEARCH("independent",R5)),"L2",IF(R5="author_run","L1",IF(R5="none","L0","")))))) | AB5: =IF(I5="","",IF(AND(K5="deterministic_policy",M5="ya"),"PERIKSA: deterministic_policy tetapi LLM/ML ada dalam keputusan. ","")&IF(AND(U5="ya",V5=""),"PERIKSA: adaptif=ya wajib ada kutipan. ","")&IF(AND(R5="none",U5<>"n/a_tanpa_evaluasi",U5<>""),"PERIKSA: tanpa evaluasi, adaptif harus n/a. ","")&IF(AND(OR(R5="author_run",R5="author_run+independent",R5="independent_only"),Q5=""),"PERIKSA: isi kelas_dievaluasi. ","")&IF(AND(OR(R5="author_run",R5="author_run+independent",R5="independent_only"),W5=""),"PERIKSA: isi lokasi_bukti. ","")&IF(AND(H5="tidak",R5<>""),"PERIKSA: tanpa teks lengkap, kosongkan kolom evaluasi. ","")) | AC5: include
A6: alfredo-2026-enclawed-configurable-sector-neutral-hardening | B6: enclawed: A Configurable, Sector-Neutral Hardening Framework for Single-User AI Assistant Gateways | C6: 2026 | D6: E2 | E6: kandidat_agent | F6: primary | G6: https://arxiv.org/abs/2604.16838 | H6: tidak | I6: not_defense | Z6: [AUDIT_v5_EXCLUDE: EC2] Dikeluarkan dari korpus MCP-spesifik oleh audit reviewer kedua v5. Hardening gateway asisten OpenClaw berbasis Bell-LaPadula; MCP insidental. | AA6: =IF(I6="","",IF(OR(I6="attack",I6="survey_review",I6="benchmark_measurement",I6="position_other",I6="not_defense"),"n/a",IF(OR(X6="spec_normatif",X6="produksi_bukti_publik"),"L3",IF(ISNUMBER(SEARCH("independent",R6)),"L2",IF(R6="author_run","L1",IF(R6="none","L0","")))))) | AB6: =IF(I6="","",IF(AND(K6="deterministic_policy",M6="ya"),"PERIKSA: deterministic_policy tetapi LLM/ML ada dalam keputusan. ","")&IF(AND(U6="ya",V6=""),"PERIKSA: adaptif=ya wajib ada kutipan. ","")&IF(AND(R6="none",U6<>"n/a_tanpa_evaluasi",U6<>""),"PERIKSA: tanpa evaluasi, adaptif harus n/a. ","")&IF(AND(OR(R6="author_run",R6="author_run+independent",R6="independent_only"),Q6=""),"PERIKSA: isi kelas_dievaluasi. ","")&IF(AND(OR(R6="author_run",R6="author_run+independent",R6="independent_only"),W6=""),"PERIKSA: isi lokasi_bukti. ","")&IF(AND(H6="tidak",R6<>""),"PERIKSA: tanpa teks lengkap, kosongkan kolom evaluasi. ","")) | AC6: exclude | AD6: EC2 | AE6: audit lanjutan; diterima koordinator
A7: anthropic-2024-model-context-protocol-specification-architecture | B7: Model Context Protocol Specification (Architecture & Security) | C7: 2024 | D7: E3 | E7: kandidat_agent | F7: primary | H7: ya | I7: position_other | Z7: Spesifikasi arsitektural protokol MCP resmi Anthropic (revisi 2024-11-05). Ketentuan normatif dilaporkan di Section 5 (Tabel 14-15), bukan sebagai L3 pertahanan literatur. | AA7: =IF(I7="","",IF(OR(I7="attack",I7="survey_review",I7="benchmark_measurement",I7="position_other",I7="not_defense"),"n/a",IF(OR(X7="spec_normatif",X7="produksi_bukti_publik"),"L3",IF(ISNUMBER(SEARCH("independent",R7)),"L2",IF(R7="author_run","L1",IF(R7="none","L0","")))))) | AB7: =IF(I7="","",IF(AND(K7="deterministic_policy",M7="ya"),"PERIKSA: deterministic_policy tetapi LLM/ML ada dalam keputusan. ","")&IF(AND(U7="ya",V7=""),"PERIKSA: adaptif=ya wajib ada kutipan. ","")&IF(AND(R7="none",U7<>"n/a_tanpa_evaluasi",U7<>""),"PERIKSA: tanpa evaluasi, adaptif harus n/a. ","")&IF(AND(OR(R7="author_run",R7="author_run+independent",R7="independent_only"),Q7=""),"PERIKSA: isi kelas_dievaluasi. ","")&IF(AND(OR(R7="author_run",R7="author_run+independent",R7="independent_only"),W7=""),"PERIKSA: isi lokasi_bukti. ","")&IF(AND(H7="tidak",R7<>""),"PERIKSA: tanpa teks lengkap, kosongkan kolom evaluasi. ","")) | AC7: include
A8: baichao-2026-flowguard-signals-evidence-mcp-security | B8: FlowGuard: From Signals to Evidence for MCP Security Detection | C8: 2026 | D8: E2 | E8: kandidat_agent | F8: primary | G8: https://arxiv.org/abs/2607.14754 | H8: ya | I8: defense_primary | J8: FlowGuard | K8: content_inspection_runtime | L8: Sistem pemindai keamanan MCP aktif berbasis probing bertahap (recon & strike) yang memverifikasi bukti runtime pada pemanggilan tool dan menganalisis risiko semantik metadata menggunakan LLM bounded. | M8: ya | N8: H | O8: R2;R4;R5 | P8: A1;A2;C3;C5 | Q8: A1;A2;C3;C5 | R8: author_run | T8: authors_own | U8: tidak | W8: Sec V; Table II; Table IV; hal. 7-10 | X8: none | Y8: latensi dilaporkan (reduksi 2.23x, Tabel IV) | Z8: Pemindai keamanan MCP dua fase (reconnaissance & targeted strike) dengan adjudikasi bukti berbasis Qwen3-235B. Diuji pada 1.880 kasus benchmark buatan penulis dan 8.000 server MCPZoo; ancaman adaptif eksplisit di luar cakupan. Catatan deployment: prototipe internal/eksperimental (belum dirilis secara publik). | AA8: =IF(I8="","",IF(OR(I8="attack",I8="survey_review",I8="benchmark_measurement",I8="position_other",I8="not_defense"),"n/a",IF(OR(X8="spec_normatif",X8="produksi_bukti_publik"),"L3",IF(ISNUMBER(SEARCH("independent",R8)),"L2",IF(R8="author_run","L1",IF(R8="none","L0","")))))) | AB8: =IF(I8="","",IF(AND(K8="deterministic_policy",M8="ya"),"PERIKSA: deterministic_policy tetapi LLM/ML ada dalam keputusan. ","")&IF(AND(U8="ya",V8=""),"PERIKSA: adaptif=ya wajib ada kutipan. ","")&IF(AND(R8="none",U8<>"n/a_tanpa_evaluasi",U8<>""),"PERIKSA: tanpa evaluasi, adaptif harus n/a. ","")&IF(AND(OR(R8="author_run",R8="author_run+independent",R8="independent_only"),Q8=""),"PERIKSA: isi kelas_dievaluasi. ","")&IF(AND(OR(R8="author_run",R8="author_run+independent",R8="independent_only"),W8=""),"PERIKSA: isi lokasi_bukti. ","")&IF(AND(H8="tidak",R8<>""),"PERIKSA: tanpa teks lengkap, kosongkan kolom evaluasi. ","")) | AC8: include
A9: bin-2025-mcpguard-automatically-detecting-vulnerabilities-mcp | B9: MCPGuard : Automatically Detecting Vulnerabilities in MCP Servers | C9: 2025 | D9: E2 | E9: kandidat_agent | F9: primary | G9: https://arxiv.org/abs/2510.23673 | H9: ya | I9: survey_review | Z9: Makalah survei/lanskap keamanan MCP dan tinjauan taksonomis komprehensif atas pertahanan yang ada (server-side scanning & runtime monitoring) tanpa evaluasi atau implementasi mekanisme baru oleh penulis. KODER 1 keliru menganggap judul 'MCPGuard' sebagai defense_primary. | AA9: =IF(I9="","",IF(OR(I9="attack",I9="survey_review",I9="benchmark_measurement",I9="position_other",I9="not_defense"),"n/a",IF(OR(X9="spec_normatif",X9="produksi_bukti_publik"),"L3",IF(ISNUMBER(SEARCH("independent",R9)),"L2",IF(R9="author_run","L1",IF(R9="none","L0","")))))) | AB9: =IF(I9="","",IF(AND(K9="deterministic_policy",M9="ya"),"PERIKSA: deterministic_policy tetapi LLM/ML ada dalam keputusan. ","")&IF(AND(U9="ya",V9=""),"PERIKSA: adaptif=ya wajib ada kutipan. ","")&IF(AND(R9="none",U9<>"n/a_tanpa_evaluasi",U9<>""),"PERIKSA: tanpa evaluasi, adaptif harus n/a. ","")&IF(AND(OR(R9="author_run",R9="author_run+independent",R9="independent_only"),Q9=""),"PERIKSA: isi kelas_dievaluasi. ","")&IF(AND(OR(R9="author_run",R9="author_run+independent",R9="independent_only"),W9=""),"PERIKSA: isi lokasi_bukti. ","")&IF(AND(H9="tidak",R9<>""),"PERIKSA: tanpa teks lengkap, kosongkan kolom evaluasi. ","")) | AC9: include
A10: chenkai-2026-when-agentic-executions-fail-detecting | B10: When Agentic Executions Fail: Detecting and Localizing Runtime Faults from Telemetry | C10: 2026 | D10: E2 | E10: kandidat_agent | F10: primary | G10: https://arxiv.org/abs/2608.14680 | H10: ya | I10: benchmark_measurement | Z10: Makalah kontribusi utamanya adalah benchmark injeksi kesalahan runtime (AgentChaosBench) berisi 275 jejak telemetri Langfuse pada 5 aplikasi multi-agen (MCP & A2A) dengan evaluasi baseline LLM diagnostik (zero-shot LLM baselines); tidak mengusulkan mekanisme pertahanan baru. KODER 1 keliru menetapkannya sebagai defense_primary. | AA10: =IF(I10="","",IF(OR(I10="attack",I10="survey_review",I10="benchmark_measurement",I10="position_other",I10="not_defense"),"n/a",IF(OR(X10="spec_normatif",X10="produksi_bukti_publik"),"L3",IF(ISNUMBER(SEARCH("independent",R10)),"L2",IF(R10="author_run","L1",IF(R10="none","L0","")))))) | AB10: =IF(I10="","",IF(AND(K10="deterministic_policy",M10="ya"),"PERIKSA: deterministic_policy tetapi LLM/ML ada dalam keputusan. ","")&IF(AND(U10="ya",V10=""),"PERIKSA: adaptif=ya wajib ada kutipan. ","")&IF(AND(R10="none",U10<>"n/a_tanpa_evaluasi",U10<>""),"PERIKSA: tanpa evaluasi, adaptif harus n/a. ","")&IF(AND(OR(R10="author_run",R10="author_run+independent",R10="independent_only"),Q10=""),"PERIKSA: isi kelas_dievaluasi. ","")&IF(AND(OR(R10="author_run",R10="author_run+independent",R10="independent_only"),W10=""),"PERIKSA: isi lokasi_bukti. ","")&IF(AND(H10="tidak",R10<>""),"PERIKSA: tanpa teks lengkap, kosongkan kolom evaluasi. ","")) | AC10: include
A11: chenning-2026-adr-agentic-detection-system-enterprise | B11: ADR: An Agentic Detection System for Enterprise Agentic AI Security | C11: 2026 | D11: E2 | E11: kandidat_agent | F11: primary | G11: https://arxiv.org/abs/2605.17380 | H11: ya | I11: defense_primary | J11: ADR | K11: content_inspection_runtime | L11: Sistem deteksi ancaman agen enterprise dua tingkat (triage cepat berbasis heuristik/klasifikator dan penalaran mendalam berbasis LLM) yang menginspeksi telemetri runtime, jejak penalaran, dan pemanggilan tool MCP. | M11: ya | N11: H | O11: R2;R3;R5;R6;R7 | P11: A1;A2;A3;B1;B2;C1;C2;C5;D1;D2;D3;OUT_OF_TAXONOMY:resource_abuse | Q11: A1;A2;C1;C5;D1;D2;D3;OUT_OF_TAXONOMY:resource_abuse | R11: author_run | T11: mixed | U11: tidak | W11: Sec. 4-5, Tabel 2, Gbr 6a, hal. 8-10 | X11: none | Y11: biaya ($0.024/task) & latensi (18.5s) dilaporkan (Sec 5.2, Fig 6b) | Z11: ADR dievaluasi pada ADR-Bench (17 teknik, 5 taktik) & AgentDojo mencakup 8 kelas (termasuk C5 Code Interpreter & Operational Impact: Resource Exhaustion/DoS dipetakan ke OUT_OF_TAXONOMY:resource_abuse). Kode repositori publik modelcon. Catatan deployment: prototipe internal/eksperimental (belum dirilis secara publik). | AA11: =IF(I11="","",IF(OR(I11="attack",I11="survey_review",I11="benchmark_measurement",I11="position_other",I11="not_defense"),"n/a",IF(OR(X11="spec_normatif",X11="produksi_bukti_publik"),"L3",IF(ISNUMBER(SEARCH("independent",R11)),"L2",IF(R11="author_run","L1",IF(R11="none","L0","")))))) | AB11: =IF(I11="","",IF(AND(K11="deterministic_policy",M11="ya"),"PERIKSA: deterministic_policy tetapi LLM/ML ada dalam keputusan. ","")&IF(AND(U11="ya",V11=""),"PERIKSA: adaptif=ya wajib ada kutipan. ","")&IF(AND(R11="none",U11<>"n/a_tanpa_evaluasi",U11<>""),"PERIKSA: tanpa evaluasi, adaptif harus n/a. ","")&IF(AND(OR(R11="author_run",R11="author_run+independent",R11="independent_only"),Q11=""),"PERIKSA: isi kelas_dievaluasi. ","")&IF(AND(OR(R11="author_run",R11="author_run+independent",R11="independent_only"),W11=""),"PERIKSA: isi lokasi_bukti. ","")&IF(AND(H11="tidak",R11<>""),"PERIKSA: tanpa teks lengkap, kosongkan kolom evaluasi. ","")) | AC11: include
A12: christoph-2025-agentbound-securing-execution-boundaries-ai | B12: AgentBound: Securing Execution Boundaries of AI Agents | C12: 2025 | D12: E1 | E12: kandidat_agent | F12: primary | G12: https://arxiv.org/abs/2510.21236 | H12: ya | I12: defense_primary | J12: AgentBound | K12: isolation_containment | L12: Kerangka pengamanan eksekusi server MCP berbasis deklarasi kapabilitas (AgentManifest) dan sandbox kontainer (AgentBox) yang mengisolasi akses berkas, jaringan, dan lingkungan secara deterministik. | M12: tidak | N12: H | O12: R5;R6 | P12: B1;C5;D1 | Q12: C5;D1 | R12: author_run | T12: mixed | U12: tidak | W12: Sec 4; Sec 4.2; Sec 4.3; Table 2; hal. 11-16 | X12: none | Y12: latensi dan overhead kontainer dilaporkan (Sec 4.3) | Z12: Eksekusi server di dalam kontainer AgentBox (Docker) menegakkan batas isolasi proses dan pembatasan kapabilitas manifest; mengevaluasi rug pull (B1), scope server (C5), dan eksfiltrasi data (D1). C1 dicabut karena isolasi proses bukan mediasi otorisasi sesi planner. Catatan deployment: prototipe internal/eksperimental (belum dirilis secara publik). | AA12: =IF(I12="","",IF(OR(I12="attack",I12="survey_review",I12="benchmark_measurement",I12="position_other",I12="not_defense"),"n/a",IF(OR(X12="spec_normatif",X12="produksi_bukti_publik"),"L3",IF(ISNUMBER(SEARCH("independent",R12)),"L2",IF(R12="author_run","L1",IF(R12="none","L0","")))))) | AB12: =IF(I12="","",IF(AND(K12="deterministic_policy",M12="ya"),"PERIKSA: deterministic_policy tetapi LLM/ML ada dalam keputusan. ","")&IF(AND(U12="ya",V12=""),"PERIKSA: adaptif=ya wajib ada kutipan. ","")&IF(AND(R12="none",U12<>"n/a_tanpa_evaluasi",U12<>""),"PERIKSA: tanpa evaluasi, adaptif harus n/a. ","")&IF(AND(OR(R12="author_run",R12="author_run+independent",R12="independent_only"),Q12=""),"PERIKSA: isi kelas_dievaluasi. ","")&IF(AND(OR(R12="author_run",R12="author_run+independent",R12="independent_only"),W12=""),"PERIKSA: isi lokasi_bukti. ","")&IF(AND(H12="tidak",R12<>""),"PERIKSA: tanpa teks lengkap, kosongkan kolom evaluasi. ","")) | AC12: include
A13: dongxu-2026-device-context-protocol-compact-safety | B13: Device Context Protocol: A Compact, Safety-First Architecture for LLM-Driven Control of Constrained Devices | C13: 2026 | D13: E2 | E13: kandidat_agent | F13: primary | G13: https://arxiv.org/abs/2605.26159 | H13: ya | I13: defense_primary | J13: Device Context Protocol | K13: protocol_provision | L13: Protokol biner kompak (DCP) dengan host-side Bridge yang memvalidasi skema kapabilitas wajib per-intent, batasan rentang, serta dry-run sebelum instruksi LLM mencapai perangkat fisik. | M13: tidak | N13: gateway_proxy | O13: R2;R5 | P13: A2;C5 | Q13: A2;C5 | R13: author_run | T13: mixed | U13: tidak | W13: Sec 4; Sec 5; Fig 3; hal. 8-10 | X13: none | Y13: footprint firmware (27.6 KB flash, 0.6 KB RAM) & latensi dilaporkan | Z13: Protokol keamanan berorientasi perangkat terbatas (DCP) dengan host Bridge penegak kapabilitas deterministik. Diuji pada 675 panggilan dari 5 LLM komersial terhadap 6 kategori serangan termasuk injeksi AgentDojo. Catatan deployment: prototipe internal/eksperimental (belum dirilis secara publik). | AA13: =IF(I13="","",IF(OR(I13="attack",I13="survey_review",I13="benchmark_measurement",I13="position_other",I13="not_defense"),"n/a",IF(OR(X13="spec_normatif",X13="produksi_bukti_publik"),"L3",IF(ISNUMBER(SEARCH("independent",R13)),"L2",IF(R13="author_run","L1",IF(R13="none","L0","")))))) | AB13: =IF(I13="","",IF(AND(K13="deterministic_policy",M13="ya"),"PERIKSA: deterministic_policy tetapi LLM/ML ada dalam keputusan. ","")&IF(AND(U13="ya",V13=""),"PERIKSA: adaptif=ya wajib ada kutipan. ","")&IF(AND(R13="none",U13<>"n/a_tanpa_evaluasi",U13<>""),"PERIKSA: tanpa evaluasi, adaptif harus n/a. ","")&IF(AND(OR(R13="author_run",R13="author_run+independent",R13="independent_only"),Q13=""),"PERIKSA: isi kelas_dievaluasi. ","")&IF(AND(OR(R13="author_run",R13="author_run+independent",R13="independent_only"),W13=""),"PERIKSA: isi lokasi_bukti. ","")&IF(AND(H13="tidak",R13<>""),"PERIKSA: tanpa teks lengkap, kosongkan kolom evaluasi. ","")) | AC13: include
A14: fatemeh-2026-federated-mcp-gateway-enforceable-isolation | B14: A Federated MCP Gateway: Enforceable Isolation and Measuring Residual Semantic Attacks | C14: 2026 | D14: E1 | E14: kandidat_agent | F14: primary | G14: https://doi.org/10.1109/noms69089.2026.11668221 | H14: ya | I14: defense_primary | J14: Federated MCP Gateway | K14: isolation_containment | L14: Gateway federasi MCP terpusat dengan kontrol isolasi tenant berbasis JWT, verifikasi skema, dan filter regex/firewall output terhadap serangan semantik residu. | M14: tidak | N14: gateway_proxy | O14: R1;R2;R3;R5 | P14: A2;D1;D2;OUT_OF_TAXONOMY:resource_abuse | Q14: A2;D1;D2;OUT_OF_TAXONOMY:resource_abuse | R14: author_run | T14: authors_own | U14: tidak | W14: Sec. IV, Tabel III, hal. 4-6 | X14: none | Y14: dilaporkan: tingkat blokir dan mismatch per modul penegakan (Tabel III) | Z14: Federated MCP Gateway (defense_primary, L1). Isolasi tenant/identitas (D1;D2), pemfilteran regex (A2), dan kontrol amplifikasi sumber daya 100 req/menit (OUT_OF_TAXONOMY:resource_abuse). Suite 93 kasus sintetik; adaptif=tidak. | AA14: =IF(I14="","",IF(OR(I14="attack",I14="survey_review",I14="benchmark_measurement",I14="position_other",I14="not_defense"),"n/a",IF(OR(X14="spec_normatif",X14="produksi_bukti_publik"),"L3",IF(ISNUMBER(SEARCH("independent",R14)),"L2",IF(R14="author_run","L1",IF(R14="none","L0","")))))) | AB14: =IF(I14="","",IF(AND(K14="deterministic_policy",M14="ya"),"PERIKSA: deterministic_policy tetapi LLM/ML ada dalam keputusan. ","")&IF(AND(U14="ya",V14=""),"PERIKSA: adaptif=ya wajib ada kutipan. ","")&IF(AND(R14="none",U14<>"n/a_tanpa_evaluasi",U14<>""),"PERIKSA: tanpa evaluasi, adaptif harus n/a. ","")&IF(AND(OR(R14="author_run",R14="author_run+independent",R14="independent_only"),Q14=""),"PERIKSA: isi kelas_dievaluasi. ","")&IF(AND(OR(R14="author_run",R14="author_run+independent",R14="independent_only"),W14=""),"PERIKSA: isi lokasi_bukti. ","")&IF(AND(H14="tidak",R14<>""),"PERIKSA: tanpa teks lengkap, kosongkan kolom evaluasi. ","")) | AC14: include
A15: gamini-2026-mcp-secure-runtime-access-control | B15: MCP-Secure: A Runtime Access Control Layer for Privilege-Aware LLM Agent Tooling | C15: 2026 | D15: E1 | E15: kandidat_agent | F15: primary | G15: https://doi.org/10.1109/ojcs.2026.3664314 | H15: ya | I15: defense_primary | J15: MCP-Secure | K15: deterministic_policy | L15: Lapisan kontrol akses runtime host-side berbasis state machine level-sesi dengan izin default read-only dan approval gating untuk eskalasi hak istimewa pemanggilan tool. | M15: tidak | N15: H | O15: R3;R5 | P15: C1;C5 | Q15: C1;C5 | R15: author_run | T15: authors_own | U15: tidak | W15: Sec. IV-V; hal. 508-512 | X15: none | Y15: dilaporkan: overhead runtime minimal mempertahankan utilitas (Sec. V) | Z15: Teks lengkap IEEE OJCS (Vol. 7, pp. 504-513). Evaluasi author_run pada 1.080 eksekusi simulasi adversarial: mengurangi blast radius tool berbahaya/halusinasi dan mengendalikan eskalasi wewenang. Catatan deployment: prototipe internal/eksperimental (belum dirilis secara publik). | AA15: =IF(I15="","",IF(OR(I15="attack",I15="survey_review",I15="benchmark_measurement",I15="position_other",I15="not_defense"),"n/a",IF(OR(X15="spec_normatif",X15="produksi_bukti_publik"),"L3",IF(ISNUMBER(SEARCH("independent",R15)),"L2",IF(R15="author_run","L1",IF(R15="none","L0","")))))) | AB15: =IF(I15="","",IF(AND(K15="deterministic_policy",M15="ya"),"PERIKSA: deterministic_policy tetapi LLM/ML ada dalam keputusan. ","")&IF(AND(U15="ya",V15=""),"PERIKSA: adaptif=ya wajib ada kutipan. ","")&IF(AND(R15="none",U15<>"n/a_tanpa_evaluasi",U15<>""),"PERIKSA: tanpa evaluasi, adaptif harus n/a. ","")&IF(AND(OR(R15="author_run",R15="author_run+independent",R15="independent_only"),Q15=""),"PERIKSA: isi kelas_dievaluasi. ","")&IF(AND(OR(R15="author_run",R15="author_run+independent",R15="independent_only"),W15=""),"PERIKSA: isi lokasi_bukti. ","")&IF(AND(H15="tidak",R15<>""),"PERIKSA: tanpa teks lengkap, kosongkan kolom evaluasi. ","")) | AC15: include
A16: genliang-2026-runtime-authorization-resources-acquired-ai | B16: Runtime Authorization for Resources Acquired by AI Agents | C16: 2026 | D16: E2 | E16: kandidat_agent | F16: primary | G16: https://arxiv.org/abs/2609.14744 | H16: tidak | I16: not_defense | Z16: [AUDIT_v5_EXCLUDE: EC2] Dikeluarkan dari korpus MCP-spesifik oleh audit reviewer kedua v5. Makalah otorisasi sumber daya runtime agen umum di mana MCP hanya format perolehan sumber daya insidental. | AA16: =IF(I16="","",IF(OR(I16="attack",I16="survey_review",I16="benchmark_measurement",I16="position_other",I16="not_defense"),"n/a",IF(OR(X16="spec_normatif",X16="produksi_bukti_publik"),"L3",IF(ISNUMBER(SEARCH("independent",R16)),"L2",IF(R16="author_run","L1",IF(R16="none","L0","")))))) | AB16: =IF(I16="","",IF(AND(K16="deterministic_policy",M16="ya"),"PERIKSA: deterministic_policy tetapi LLM/ML ada dalam keputusan. ","")&IF(AND(U16="ya",V16=""),"PERIKSA: adaptif=ya wajib ada kutipan. ","")&IF(AND(R16="none",U16<>"n/a_tanpa_evaluasi",U16<>""),"PERIKSA: tanpa evaluasi, adaptif harus n/a. ","")&IF(AND(OR(R16="author_run",R16="author_run+independent",R16="independent_only"),Q16=""),"PERIKSA: isi kelas_dievaluasi. ","")&IF(AND(OR(R16="author_run",R16="author_run+independent",R16="independent_only"),W16=""),"PERIKSA: isi lokasi_bukti. ","")&IF(AND(H16="tidak",R16<>""),"PERIKSA: tanpa teks lengkap, kosongkan kolom evaluasi. ","")) | AC16: exclude | AD16: EC2 | AE16: dikeluarkan setelah audit reviewer kedua + rekonsiliasi
A17: giovanni-2026-mandato-protocol-level-enforcement-digitally | B17: Mandato: Protocol-Level Enforcement of Digitally Signed Mandates on AI Agent Actions with Cryptographically Chained Audit Trails | C17: 2026 | D17: E2 | E17: kandidat_agent | F17: primary | G17: https://arxiv.org/abs/2608.14074 | H17: ya | I17: proposal_only | J17: MANDATO | K17: capability_or_token | L17: Proxy tata kelola MCP yang memvalidasi mandat bertanda tangan digital pada aksi agen dan mencatat jejak audit terantai kriptografis secara tamper-evident. | M17: tidak | N17: gateway_proxy | O17: R3;R5 | P17: C1;C2;C3 | R17: none | T17: none | U17: n/a_tanpa_evaluasi | X17: none | Y17: not_reported | Z17: Proxy tata kelola MCP untuk mandat bertanda tangan digital. Penulis menyatakan status epistemik sistem masih dalam pengembangan (system under construction) tanpa hasil empiris. KODER 1 menandai defense_primary dengan jenis_evaluasi: none (L0). | AA17: =IF(I17="","",IF(OR(I17="attack",I17="survey_review",I17="benchmark_measurement",I17="position_other",I17="not_defense"),"n/a",IF(OR(X17="spec_normatif",X17="produksi_bukti_publik"),"L3",IF(ISNUMBER(SEARCH("independent",R17)),"L2",IF(R17="author_run","L1",IF(R17="none","L0","")))))) | AB17: =IF(I17="","",IF(AND(K17="deterministic_policy",M17="ya"),"PERIKSA: deterministic_policy tetapi LLM/ML ada dalam keputusan. ","")&IF(AND(U17="ya",V17=""),"PERIKSA: adaptif=ya wajib ada kutipan. ","")&IF(AND(R17="none",U17<>"n/a_tanpa_evaluasi",U17<>""),"PERIKSA: tanpa evaluasi, adaptif harus n/a. ","")&IF(AND(OR(R17="author_run",R17="author_run+independent",R17="independent_only"),Q17=""),"PERIKSA: isi kelas_dievaluasi. ","")&IF(AND(OR(R17="author_run",R17="author_run+independent",R17="independent_only"),W17=""),"PERIKSA: isi lokasi_bukti. ","")&IF(AND(H17="tidak",R17<>""),"PERIKSA: tanpa teks lengkap, kosongkan kolom evaluasi. ","")) | AC17: include
A18: guanlin-2025-zero-knowledge-audit-internet-agents | B18: Zero-Knowledge Audit for Internet of Agents: Privacy-Preserving Communication Verification with Model Context Protocol | C18: 2025 | D18: E2 | E18: kandidat_agent | F18: primary | G18: https://arxiv.org/abs/2512.14737 | H18: ya | I18: defense_primary | J18: zk-MCP | K18: integrity_provenance | L18: Protokol audit privasi berbasis Zero-Knowledge Proof pada saluran MCP yang memverifikasi kepatuhan format dan keabsahan pesan tanpa mengungkap isi komunikasi. | M18: tidak | N18: gateway_proxy | O18: R4;R6 | P18: C3;D1 | Q18: C3;D1 | R18: author_run | T18: authors_own | U18: tidak | W18: Sec V; Table III; Table IV; hal. 8-11 | X18: none | Y18: latensi bukti ZK (< 50ms) dan overhead transmisi dilaporkan (Sec V) | Z18: Protokol audit privasi berbasis Zero-Knowledge Proof (zk-MCP) terintegrasi pada kanal MCP. Penegakan kriptografis deterministik (Circom ZK circuit). Dievaluasi pada testbed komunikasi multi-agen IoA. Catatan deployment: prototipe internal/eksperimental (belum dirilis secara publik). | AA18: =IF(I18="","",IF(OR(I18="attack",I18="survey_review",I18="benchmark_measurement",I18="position_other",I18="not_defense"),"n/a",IF(OR(X18="spec_normatif",X18="produksi_bukti_publik"),"L3",IF(ISNUMBER(SEARCH("independent",R18)),"L2",IF(R18="author_run","L1",IF(R18="none","L0","")))))) | AB18: =IF(I18="","",IF(AND(K18="deterministic_policy",M18="ya"),"PERIKSA: deterministic_policy tetapi LLM/ML ada dalam keputusan. ","")&IF(AND(U18="ya",V18=""),"PERIKSA: adaptif=ya wajib ada kutipan. ","")&IF(AND(R18="none",U18<>"n/a_tanpa_evaluasi",U18<>""),"PERIKSA: tanpa evaluasi, adaptif harus n/a. ","")&IF(AND(OR(R18="author_run",R18="author_run+independent",R18="independent_only"),Q18=""),"PERIKSA: isi kelas_dievaluasi. ","")&IF(AND(OR(R18="author_run",R18="author_run+independent",R18="independent_only"),W18=""),"PERIKSA: isi lokasi_bukti. ","")&IF(AND(H18="tidak",R18<>""),"PERIKSA: tanpa teks lengkap, kosongkan kolom evaluasi. ","")) | AC18: include
A19: haiyue-2026-agent-audit-security-analysis-system | B19: Agent Audit: A Security Analysis System for LLM Agent Applications | C19: 2026 | D19: E2 | E19: kandidat_agent | F19: primary | G19: https://arxiv.org/abs/2603.22853 | H19: tidak | I19: not_defense | Z19: [AUDIT_v5_EXCLUDE: EC2] Dikeluarkan dari korpus MCP-spesifik oleh audit reviewer kedua v5. Analisis keamanan aplikasi agen LLM umum dengan MCP hanya salah satu format tool insidental. | AA19: =IF(I19="","",IF(OR(I19="attack",I19="survey_review",I19="benchmark_measurement",I19="position_other",I19="not_defense"),"n/a",IF(OR(X19="spec_normatif",X19="produksi_bukti_publik"),"L3",IF(ISNUMBER(SEARCH("independent",R19)),"L2",IF(R19="author_run","L1",IF(R19="none","L0","")))))) | AB19: =IF(I19="","",IF(AND(K19="deterministic_policy",M19="ya"),"PERIKSA: deterministic_policy tetapi LLM/ML ada dalam keputusan. ","")&IF(AND(U19="ya",V19=""),"PERIKSA: adaptif=ya wajib ada kutipan. ","")&IF(AND(R19="none",U19<>"n/a_tanpa_evaluasi",U19<>""),"PERIKSA: tanpa evaluasi, adaptif harus n/a. ","")&IF(AND(OR(R19="author_run",R19="author_run+independent",R19="independent_only"),Q19=""),"PERIKSA: isi kelas_dievaluasi. ","")&IF(AND(OR(R19="author_run",R19="author_run+independent",R19="independent_only"),W19=""),"PERIKSA: isi lokasi_bukti. ","")&IF(AND(H19="tidak",R19<>""),"PERIKSA: tanpa teks lengkap, kosongkan kolom evaluasi. ","")) | AC19: exclude | AD19: EC2 | AE19: audit lanjutan; diterima koordinator
A20: huan-2026-zero-trust-authorization-discovery-enterprise | B20: Zero-Trust Authorization and Discovery for Enterprise MCP | C20: 2026 | D20: E2 | E20: kandidat_agent | F20: primary | G20: https://arxiv.org/abs/2609.22573 | H20: ya | I20: defense_primary | J20: FastMCP Zero-Trust Extensions | K20: deterministic_policy | L20: Ekstensi zero-trust middleware FastMCP yang menyediakan otorisasi per-tool AND/OR deklaratif, autentikasi dual-persona, serta cache introspeksi token untuk validasi kontinu. | M20: tidak | N20: gateway_proxy | O20: R3;R4;R5 | P20: C1;C2;C3;C5 | Q20: C1;C2;C3;C5 | R20: author_run | T20: authors_own | U20: tidak | W20: Sec 4.1; Sec 4.2; Sec 4.3; Table 2; Table 3; Table 4; hal. 6-10 | X20: none | Y20: latensi (p50: 9.9 ms vs 296 ms, Tabel 2) dan trace produksi 7 hari dilaporkan (Sec 4.2) | Z20: Ekstensi zero-trust untuk FastMCP oleh insinyur PayPal yang menambahkan otorisasi per-tool, dual-persona auth, dan cache introspeksi token. Diuji secara adversarial pada testbed alat Kubernetes dan dievaluasi pada jejak produksi PayPal 7 hari. Catatan deployment: prototipe internal/eksperimental (belum dirilis secara publik). | AA20: =IF(I20="","",IF(OR(I20="attack",I20="survey_review",I20="benchmark_measurement",I20="position_other",I20="not_defense"),"n/a",IF(OR(X20="spec_normatif",X20="produksi_bukti_publik"),"L3",IF(ISNUMBER(SEARCH("independent",R20)),"L2",IF(R20="author_run","L1",IF(R20="none","L0","")))))) | AB20: =IF(I20="","",IF(AND(K20="deterministic_policy",M20="ya"),"PERIKSA: deterministic_policy tetapi LLM/ML ada dalam keputusan. ","")&IF(AND(U20="ya",V20=""),"PERIKSA: adaptif=ya wajib ada kutipan. ","")&IF(AND(R20="none",U20<>"n/a_tanpa_evaluasi",U20<>""),"PERIKSA: tanpa evaluasi, adaptif harus n/a. ","")&IF(AND(OR(R20="author_run",R20="author_run+independent",R20="independent_only"),Q20=""),"PERIKSA: isi kelas_dievaluasi. ","")&IF(AND(OR(R20="author_run",R20="author_run+independent",R20="independent_only"),W20=""),"PERIKSA: isi lokasi_bukti. ","")&IF(AND(H20="tidak",R20<>""),"PERIKSA: tanpa teks lengkap, kosongkan kolom evaluasi. ","")) | AC20: include
A21: huihao-2025-mcip-protecting-mcp-safety-via | B21: MCIP: Protecting MCP Safety via Model Contextual Integrity Protocol | C21: 2025 | D21: E1 | E21: kandidat_agent | F21: primary | G21: https://doi.org/10.18653/v1/2025.emnlp-main.62 | H21: ya | I21: defense_primary | J21: MCIP | K21: content_inspection_runtime | L21: Protokol integritas kontekstual dengan model pelindung (MCIP Guardian) yang mengawasi alur konteks interaksi MCP dan mendeteksi aksi tidak aman pada pemanggilan tool. | M21: ya | N21: H | O21: R2;R5;R6 | P21: A1;A2;C5;D1 | Q21: A1;A2;C5;D1 | R21: author_run+independent | S21: yixuan-2025-mcpsecbench-systematic-security-benchmark-playground | T21: mixed | U21: tidak | W21: Sec 6; Sec 7; Table 2; Fig 5; hal. 6-9 | X21: none | Y21: trade-off utilitas BFCL dan resistensi risiko dilaporkan (Tabel 2, Fig 5) | Z21: Kerangka pengamanan MCP berbasis protokol integritas kontekstual (MCIP) dan model pelindung (MCIP Guardian). Dievaluasi secara independen oleh MCPSecBench (yixuan-2025) pada 3 platform MCP (Tabel 1, 2, Fig 4, 6) sehingga mencapai maturitas L2. Catatan deployment: prototipe internal/eksperimental (belum dirilis secara publik). | AA21: =IF(I21="","",IF(OR(I21="attack",I21="survey_review",I21="benchmark_measurement",I21="position_other",I21="not_defense"),"n/a",IF(OR(X21="spec_normatif",X21="produksi_bukti_publik"),"L3",IF(ISNUMBER(SEARCH("independent",R21)),"L2",IF(R21="author_run","L1",IF(R21="none","L0","")))))) | AB21: =IF(I21="","",IF(AND(K21="deterministic_policy",M21="ya"),"PERIKSA: deterministic_policy tetapi LLM/ML ada dalam keputusan. ","")&IF(AND(U21="ya",V21=""),"PERIKSA: adaptif=ya wajib ada kutipan. ","")&IF(AND(R21="none",U21<>"n/a_tanpa_evaluasi",U21<>""),"PERIKSA: tanpa evaluasi, adaptif harus n/a. ","")&IF(AND(OR(R21="author_run",R21="author_run+independent",R21="independent_only"),Q21=""),"PERIKSA: isi kelas_dievaluasi. ","")&IF(AND(OR(R21="author_run",R21="author_run+independent",R21="independent_only"),W21=""),"PERIKSA: isi lokasi_bukti. ","")&IF(AND(H21="tidak",R21<>""),"PERIKSA: tanpa teks lengkap, kosongkan kolom evaluasi. ","")) | AC21: include
A22: ignacio-2026-crud-autonomous-agents-formal-validation | B22: From CRUD to Autonomous Agents: Formal Validation and Zero-Trust Security for Semantic Gateways in AI-Native Enterprise Systems | C22: 2026 | D22: E2 | E22: kandidat_agent | F22: primary | G22: https://arxiv.org/abs/2604.25555 | H22: ya | I22: defense_primary | J22: Semantic Gateway | K22: deterministic_policy | L22: Gateway semantik zero-trust dengan validasi formal transisi state (EPA) dan penegakan kebijakan OPA/Rego deterministik untuk mencegah pelanggaran otorisasi BOLA. | M22: tidak | N22: gateway_proxy | O22: R3;R5 | P22: C1;C2;C5 | Q22: C1;C2;C5 | R22: author_run | T22: authors_own | U22: tidak | W22: Sec 8; Sec 8.3; Sec 8.4; Table 2; Table 3; hal. 14-16 | X22: prototype_open_source | Y22: latensi gateway semantik vs traditional REST baseline dilaporkan (Tabel 3) | Z22: Gateway semantik zero-trust dengan penegakan kebijakan deterministik OPA/Rego dan validasi formal graf EPA. Dievaluasi dengan semantic fuzzer 500 iterasi dan 47 kasus uji, menolak pelanggaran BOLA dan transisi ilegal. Repositori/artefak: https://github.com/PeyranoDev/semantic-gateway-poc. | AA22: =IF(I22="","",IF(OR(I22="attack",I22="survey_review",I22="benchmark_measurement",I22="position_other",I22="not_defense"),"n/a",IF(OR(X22="spec_normatif",X22="produksi_bukti_publik"),"L3",IF(ISNUMBER(SEARCH("independent",R22)),"L2",IF(R22="author_run","L1",IF(R22="none","L0","")))))) | AB22: =IF(I22="","",IF(AND(K22="deterministic_policy",M22="ya"),"PERIKSA: deterministic_policy tetapi LLM/ML ada dalam keputusan. ","")&IF(AND(U22="ya",V22=""),"PERIKSA: adaptif=ya wajib ada kutipan. ","")&IF(AND(R22="none",U22<>"n/a_tanpa_evaluasi",U22<>""),"PERIKSA: tanpa evaluasi, adaptif harus n/a. ","")&IF(AND(OR(R22="author_run",R22="author_run+independent",R22="independent_only"),Q22=""),"PERIKSA: isi kelas_dievaluasi. ","")&IF(AND(OR(R22="author_run",R22="author_run+independent",R22="independent_only"),W22=""),"PERIKSA: isi lokasi_bukti. ","")&IF(AND(H22="tidak",R22<>""),"PERIKSA: tanpa teks lengkap, kosongkan kolom evaluasi. ","")) | AC22: include
A23: ivo-2025-simplified-secure-mcp-gateways-enterprise | B23: Simplified and Secure MCP Gateways for Enterprise AI Integration | C23: 2025 | D23: E2 | E23: kandidat_agent | F23: primary | G23: https://doi.org/10.48550/arxiv.2504.19997 | H23: ya | I23: defense_primary | J23: MCP Gateway | K23: deterministic_policy | L23: Arsitektur gateway pengaman MCP enterprise self-hosted berbasis OAuth2-proxy, reverse proxy Traefik, CrowdSec IDS/WAF, dan tunnel WireGuard. | M23: tidak | N23: gateway_proxy | O23: R4;R5 | P23: C3;C5 | Q23: C3;C5 | R23: author_run | T23: authors_own | U23: tidak | W23: Sec VIII; Table I; Table II; hal. 4-6 | X23: none | Y23: not_reported | Z23: Arsitektur gateway pengaman MCP enterprise self-hosted berbasis OAuth2-proxy, Traefik, CrowdSec, dan tunnel WireGuard. Penegakan deterministik pada gateway proxy menolak permintaan tanpa autentikasi dan token tidak sah. Catatan deployment: prototipe internal/eksperimental (belum dirilis secara publik). | AA23: =IF(I23="","",IF(OR(I23="attack",I23="survey_review",I23="benchmark_measurement",I23="position_other",I23="not_defense"),"n/a",IF(OR(X23="spec_normatif",X23="produksi_bukti_publik"),"L3",IF(ISNUMBER(SEARCH("independent",R23)),"L2",IF(R23="author_run","L1",IF(R23="none","L0","")))))) | AB23: =IF(I23="","",IF(AND(K23="deterministic_policy",M23="ya"),"PERIKSA: deterministic_policy tetapi LLM/ML ada dalam keputusan. ","")&IF(AND(U23="ya",V23=""),"PERIKSA: adaptif=ya wajib ada kutipan. ","")&IF(AND(R23="none",U23<>"n/a_tanpa_evaluasi",U23<>""),"PERIKSA: tanpa evaluasi, adaptif harus n/a. ","")&IF(AND(OR(R23="author_run",R23="author_run+independent",R23="independent_only"),Q23=""),"PERIKSA: isi kelas_dievaluasi. ","")&IF(AND(OR(R23="author_run",R23="author_run+independent",R23="independent_only"),W23=""),"PERIKSA: isi lokasi_bukti. ","")&IF(AND(H23="tidak",R23<>""),"PERIKSA: tanpa teks lengkap, kosongkan kolom evaluasi. ","")) | AC23: include
A24: jalendar-2025-zero-trust-proof-gated-agent | B24: Zero-Trust Proof-Gated Agent Architecture (ZPAA): A Comprehensive Security Model for the Model Context Protocol (MCP) | C24: 2025 | D24: E2 | E24: kandidat_agent | F24: primary | G24: https://doi.org/10.22541/au.175761889.90929465/v1 | H24: tidak | I24: defense_primary | J24: Zero-Trust Proof-Gated Agent Architecture | K24: deterministic_policy | L24: Model arsitektur agen zero-trust berbasis bukti untuk memvalidasi interaksi dan izin pemanggilan Model Context Protocol. | M24: tidak | N24: gateway_proxy | O24: R3;R4 | P24: C3;C1 | Z24: [NON-OA / ABSTRACT-ONLY] Artikel Authorea dengan akses terbatas. Arsitektur agen proof-gated zero-trust untuk memverifikasi bukti kriptografis sebelum eksekusi aksi (C3, C1). | AA24: =IF(I24="","",IF(OR(I24="attack",I24="survey_review",I24="benchmark_measurement",I24="position_other",I24="not_defense"),"n/a",IF(OR(X24="spec_normatif",X24="produksi_bukti_publik"),"L3",IF(ISNUMBER(SEARCH("independent",R24)),"L2",IF(R24="author_run","L1",IF(R24="none","L0","")))))) | AB24: =IF(I24="","",IF(AND(K24="deterministic_policy",M24="ya"),"PERIKSA: deterministic_policy tetapi LLM/ML ada dalam keputusan. ","")&IF(AND(U24="ya",V24=""),"PERIKSA: adaptif=ya wajib ada kutipan. ","")&IF(AND(R24="none",U24<>"n/a_tanpa_evaluasi",U24<>""),"PERIKSA: tanpa evaluasi, adaptif harus n/a. ","")&IF(AND(OR(R24="author_run",R24="author_run+independent",R24="independent_only"),Q24=""),"PERIKSA: isi kelas_dievaluasi. ","")&IF(AND(OR(R24="author_run",R24="author_run+independent",R24="independent_only"),W24=""),"PERIKSA: isi lokasi_bukti. ","")&IF(AND(H24="tidak",R24<>""),"PERIKSA: tanpa teks lengkap, kosongkan kolom evaluasi. ","")) | AC24: include
A25: lichao-2026-safemcp-proactive-power-regulation-llm | B25: SafeMCP: Proactive Power Regulation for LLM Agent Defense via Environment-Grounded Look-Ahead Reasoning | C25: 2026 | D25: E2 | E25: kandidat_agent | F25: primary | G25: https://arxiv.org/abs/2606.01991 | H25: tidak | I25: not_defense | Z25: [AUDIT_v5_EXCLUDE: EC2] Dikeluarkan dari korpus MCP-spesifik oleh audit reviewer kedua v5. Regulasi proaktif agen LLM umum via look-ahead reasoning di mana MCP insidental. | AA25: =IF(I25="","",IF(OR(I25="attack",I25="survey_review",I25="benchmark_measurement",I25="position_other",I25="not_defense"),"n/a",IF(OR(X25="spec_normatif",X25="produksi_bukti_publik"),"L3",IF(ISNUMBER(SEARCH("independent",R25)),"L2",IF(R25="author_run","L1",IF(R25="none","L0","")))))) | AB25: =IF(I25="","",IF(AND(K25="deterministic_policy",M25="ya"),"PERIKSA: deterministic_policy tetapi LLM/ML ada dalam keputusan. ","")&IF(AND(U25="ya",V25=""),"PERIKSA: adaptif=ya wajib ada kutipan. ","")&IF(AND(R25="none",U25<>"n/a_tanpa_evaluasi",U25<>""),"PERIKSA: tanpa evaluasi, adaptif harus n/a. ","")&IF(AND(OR(R25="author_run",R25="author_run+independent",R25="independent_only"),Q25=""),"PERIKSA: isi kelas_dievaluasi. ","")&IF(AND(OR(R25="author_run",R25="author_run+independent",R25="independent_only"),W25=""),"PERIKSA: isi lokasi_bukti. ","")&IF(AND(H25="tidak",R25<>""),"PERIKSA: tanpa teks lengkap, kosongkan kolom evaluasi. ","")) | AC25: exclude | AD25: EC2 | AE25: audit lanjutan; diterima koordinator
A26: manish-2025-etdi-mitigating-tool-squatting-rug | B26: ETDI: Mitigating Tool Squatting and Rug Pull Attacks in Model Context Protocol (MCP) by using OAuth-Enhanced Tool Definitions and Policy-Based Access Control | C26: 2025 | D26: E1 | E26: kandidat_agent | F26: primary | G26: https://arxiv.org/abs/2506.01333 | H26: ya | I26: defense_primary | J26: ETDI | K26: cryptographic_integrity | L26: Spesifikasi antarmuka Enhanced Tool Definition Interface (ETDI) dengan verifikasi identitas kriptografis, versi definisi immutable, dan kebijakan Cedar/OPA untuk mitigasi tool squatting dan rug pull. | M26: tidak | N26: G | O26: R1;R6 | P26: A1;B1 | R26: none | T26: none | U26: n/a_tanpa_evaluasi | W26: Sec. 3-4, hal. 4-6 | X26: none | Y26: not_reported | Z26: Spesifikasi Enhanced Tool Definition Interface (ETDI) dengan verifikasi identitas kriptografis, versi immutable, dan integrasi kebijakan Cedar/OPA untuk mitigasi tool squatting dan rug pull. Tanpa evaluasi empiris (L0). | AA26: =IF(I26="","",IF(OR(I26="attack",I26="survey_review",I26="benchmark_measurement",I26="position_other",I26="not_defense"),"n/a",IF(OR(X26="spec_normatif",X26="produksi_bukti_publik"),"L3",IF(ISNUMBER(SEARCH("independent",R26)),"L2",IF(R26="author_run","L1",IF(R26="none","L0","")))))) | AB26: =IF(I26="","",IF(AND(K26="deterministic_policy",M26="ya"),"PERIKSA: deterministic_policy tetapi LLM/ML ada dalam keputusan. ","")&IF(AND(U26="ya",V26=""),"PERIKSA: adaptif=ya wajib ada kutipan. ","")&IF(AND(R26="none",U26<>"n/a_tanpa_evaluasi",U26<>""),"PERIKSA: tanpa evaluasi, adaptif harus n/a. ","")&IF(AND(OR(R26="author_run",R26="author_run+independent",R26="independent_only"),Q26=""),"PERIKSA: isi kelas_dievaluasi. ","")&IF(AND(OR(R26="author_run",R26="author_run+independent",R26="independent_only"),W26=""),"PERIKSA: isi lokasi_bukti. ","")&IF(AND(H26="tidak",R26<>""),"PERIKSA: tanpa teks lengkap, kosongkan kolom evaluasi. ","")) | AC26: include
A27: mirza-2026-stochastic-deputy-structural-tenant-isolation | B27: The Stochastic Deputy: Structural Tenant Isolation for Tool-Using LLM Agents | C27: 2026 | D27: E2 | E27: kandidat_agent | F27: primary | G27: https://arxiv.org/abs/2609.14780 | H27: ya | I27: defense_primary | J27: Structural Tenant Isolation | K27: deterministic_policy | L27: Pertahanan struktural terhadap masalah stochastic deputy dengan menghapus parameter tenant dari skema tool MCP dan menegakkan isolasi tenant di bawah agen melalui credential binding dan query rewriting. | M27: tidak | N27: S | O27: R3;R5 | P27: C1;C2;D1 | Q27: C1;C2;D1 | R27: author_run | T27: authors_own | U27: tidak | W27: Sec 8; Sec 8.1; Table 1; Table 2; hal. 8-15 | X27: none | Y27: latensi dan rasio optimasi query MySQL dilaporkan (Sec 8, RQ2) | Z27: Pertahanan isolasi multi-tenant struktural (structural tenant isolation) terhadap masalah stochastic deputy dengan menghapus parameter tenant dari skema tool MCP dan mengikat lingkup pada kredensial terverifikasi. Dievaluasi pada 373 uji lintas 8 LLM dan basis data MySQL multi-GB. Catatan deployment: prototipe internal/eksperimental (belum dirilis secara publik). | AA27: =IF(I27="","",IF(OR(I27="attack",I27="survey_review",I27="benchmark_measurement",I27="position_other",I27="not_defense"),"n/a",IF(OR(X27="spec_normatif",X27="produksi_bukti_publik"),"L3",IF(ISNUMBER(SEARCH("independent",R27)),"L2",IF(R27="author_run","L1",IF(R27="none","L0","")))))) | AB27: =IF(I27="","",IF(AND(K27="deterministic_policy",M27="ya"),"PERIKSA: deterministic_policy tetapi LLM/ML ada dalam keputusan. ","")&IF(AND(U27="ya",V27=""),"PERIKSA: adaptif=ya wajib ada kutipan. ","")&IF(AND(R27="none",U27<>"n/a_tanpa_evaluasi",U27<>""),"PERIKSA: tanpa evaluasi, adaptif harus n/a. ","")&IF(AND(OR(R27="author_run",R27="author_run+independent",R27="independent_only"),Q27=""),"PERIKSA: isi kelas_dievaluasi. ","")&IF(AND(OR(R27="author_run",R27="author_run+independent",R27="independent_only"),W27=""),"PERIKSA: isi lokasi_bukti. ","")&IF(AND(H27="tidak",R27<>""),"PERIKSA: tanpa teks lengkap, kosongkan kolom evaluasi. ","")) | AC27: include
A28: nirajan-2026-formal-security-framework-mcp-based | B28: A Formal Security Framework for MCP-Based AI Agents: Threat Taxonomy, Verification Models, and Defense Mechanisms | C28: 2026 | D28: E2 | E28: kandidat_agent | F28: primary | G28: https://arxiv.org/abs/2604.05969 | H28: ya | I28: proposal_only | J28: MCPSHIELD | K28: protocol_provision | L28: Kerangka formal dan arsitektur defense-in-depth empat lapis (MCPSHIELD) berbasis model verifikasi formal Labeled Transition Systems untuk mengamankan ekosistem agen MCP. | M28: tidak | N28: gateway_proxy | O28: R1;R2;R3;R4;R5;R6;R7 | P28: A1;A2;B1;B2;C1;C3;C5;D1;D3 | R28: none | T28: none | U28: n/a_tanpa_evaluasi | X28: none | Y28: not_reported | Z28: Kerangka keamanan formal dan arsitektur defense-in-depth berlapis (MCPSHIELD) berbasis model verifikasi formal Labeled Transition Systems (LTS). Tidak menyertakan evaluasi empiris pertahanan terhadap serangan. KODER 1 menandai defense_primary dengan jenis_evaluasi none (L0). | AA28: =IF(I28="","",IF(OR(I28="attack",I28="survey_review",I28="benchmark_measurement",I28="position_other",I28="not_defense"),"n/a",IF(OR(X28="spec_normatif",X28="produksi_bukti_publik"),"L3",IF(ISNUMBER(SEARCH("independent",R28)),"L2",IF(R28="author_run","L1",IF(R28="none","L0","")))))) | AB28: =IF(I28="","",IF(AND(K28="deterministic_policy",M28="ya"),"PERIKSA: deterministic_policy tetapi LLM/ML ada dalam keputusan. ","")&IF(AND(U28="ya",V28=""),"PERIKSA: adaptif=ya wajib ada kutipan. ","")&IF(AND(R28="none",U28<>"n/a_tanpa_evaluasi",U28<>""),"PERIKSA: tanpa evaluasi, adaptif harus n/a. ","")&IF(AND(OR(R28="author_run",R28="author_run+independent",R28="independent_only"),Q28=""),"PERIKSA: isi kelas_dievaluasi. ","")&IF(AND(OR(R28="author_run",R28="author_run+independent",R28="independent_only"),W28=""),"PERIKSA: isi lokasi_bukti. ","")&IF(AND(H28="tidak",R28<>""),"PERIKSA: tanpa teks lengkap, kosongkan kolom evaluasi. ","")) | AC28: include
A29: parya-2026-mcp-scanner-detecting-security-risks | B29: MCP-Scanner: Detecting Security Risks in Model Context Protocol Systems | C29: 2026 | D29: E1 | E29: kandidat_agent | F29: primary | G29: https://doi.org/10.1145/3786160.3788471 | H29: ya | I29: defense_primary | J29: MCP-Scanner (eSentire MCP-Scanner) | K29: content_inspection_static | L29: Pemindai komprehensif multi-layer (kata kunci, SentenceTransformer embeddings, dan LLM-as-judge) untuk memeriksa keamanan tools, prompts, dan resources server MCP. | M29: ya | N29: offline_analysis | O29: R1;R2;R3;R5;R7 | P29: A1;A2;B2;C1;D3 | Q29: A1;A2;D3 | R29: author_run | T29: mixed | U29: tidak | W29: Sec. 6, Tabel 1 & 2, hal. 6-8 | X29: none | Y29: cakupan deteksi 13 kategori kerentanan pada 14 server MCP (Tabel 1 & 2) | Z29: MCP-Scanner (defense_primary, L1). Evaluasi pemindaian statis AST/regex pada 14 server MCP (Tabel 2). Tabel 1 membandingkan 22 kategori kerentanan komparatif secara literatur (14 kategori diklaim terdeteksi oleh MCP-Scanner); tidak ada eksekusi eksperimen kuantitatif terhadap perkakas lain sehingga ditolak sebagai evaluator L2. | AA29: =IF(I29="","",IF(OR(I29="attack",I29="survey_review",I29="benchmark_measurement",I29="position_other",I29="not_defense"),"n/a",IF(OR(X29="spec_normatif",X29="produksi_bukti_publik"),"L3",IF(ISNUMBER(SEARCH("independent",R29)),"L2",IF(R29="author_run","L1",IF(R29="none","L0","")))))) | AB29: =IF(I29="","",IF(AND(K29="deterministic_policy",M29="ya"),"PERIKSA: deterministic_policy tetapi LLM/ML ada dalam keputusan. ","")&IF(AND(U29="ya",V29=""),"PERIKSA: adaptif=ya wajib ada kutipan. ","")&IF(AND(R29="none",U29<>"n/a_tanpa_evaluasi",U29<>""),"PERIKSA: tanpa evaluasi, adaptif harus n/a. ","")&IF(AND(OR(R29="author_run",R29="author_run+independent",R29="independent_only"),Q29=""),"PERIKSA: isi kelas_dievaluasi. ","")&IF(AND(OR(R29="author_run",R29="author_run+independent",R29="independent_only"),W29=""),"PERIKSA: isi lokasi_bukti. ","")&IF(AND(H29="tidak",R29<>""),"PERIKSA: tanpa teks lengkap, kosongkan kolom evaluasi. ","")) | AC29: include
A30: pek-2026-cascade-component-ablation-corpus-audit | B30: CASCADE: A Component Ablation and Corpus Audit of a Layered Local Defense for MCP-Based Systems | C30: 2026 | D30: E2 | E30: kandidat_agent | F30: primary | G30: https://arxiv.org/abs/2604.17125 | H30: ya | I30: defense_primary | J30: CASCADE | K30: content_inspection_runtime | L30: Pertahanan berlapis lokal untuk sistem MCP yang memadukan filter kemiripan embedding cepat dan model review lokal Llama-3 8B untuk menangani permintaan ambigu/mencurigakan. | M30: ya | N30: H | O30: R2 | P30: A1;A2 | Q30: A1;A2 | R30: author_run | T30: mixed | U30: tidak | W30: Sec 4; Sec 4.1; Sec 4.2; Table 5; Table 6; hal. 8-15 | X30: none | Y30: latensi per tahap, throughput, dan tingkat pemanggilan model review (32.56%) dilaporkan (Sec 4) | Z30: Pertahanan berlapis lokal untuk sistem MCP (CASCADE) memadukan embedding filter deterministik dan model review lokal Llama-3 8B. Dievaluasi secara ketat pada 5.000 sampel korpus riil/augmentasi dengan ablasi komponen menyeluruh. Catatan deployment: prototipe internal/eksperimental (belum dirilis secara publik). | AA30: =IF(I30="","",IF(OR(I30="attack",I30="survey_review",I30="benchmark_measurement",I30="position_other",I30="not_defense"),"n/a",IF(OR(X30="spec_normatif",X30="produksi_bukti_publik"),"L3",IF(ISNUMBER(SEARCH("independent",R30)),"L2",IF(R30="author_run","L1",IF(R30="none","L0","")))))) | AB30: =IF(I30="","",IF(AND(K30="deterministic_policy",M30="ya"),"PERIKSA: deterministic_policy tetapi LLM/ML ada dalam keputusan. ","")&IF(AND(U30="ya",V30=""),"PERIKSA: adaptif=ya wajib ada kutipan. ","")&IF(AND(R30="none",U30<>"n/a_tanpa_evaluasi",U30<>""),"PERIKSA: tanpa evaluasi, adaptif harus n/a. ","")&IF(AND(OR(R30="author_run",R30="author_run+independent",R30="independent_only"),Q30=""),"PERIKSA: isi kelas_dievaluasi. ","")&IF(AND(OR(R30="author_run",R30="author_run+independent",R30="independent_only"),W30=""),"PERIKSA: isi lokasi_bukti. ","")&IF(AND(H30="tidak",R30<>""),"PERIKSA: tanpa teks lengkap, kosongkan kolom evaluasi. ","")) | AC30: include
A31: ping-2026-hybrid-analysis-secure-mcp-tool | B31: Hybrid Analysis for Secure MCP Tool Use in LLM Agents | C31: 2026 | D31: E2 | E31: kandidat_agent | F31: primary | G31: https://arxiv.org/abs/2607.25297 | H31: ya | I31: defense_primary | J31: MTGuard | K31: content_inspection_runtime | L31: Kerangka analisis hibrida siklus hidup (MTGuard) yang mengombinasikan asesmen risiko pra-eksekusi dan verifikasi hasil pasca-eksekusi pada pemanggilan tool MCP. | M31: ya | N31: H | O31: R2;R5 | P31: A1;A2;C5 | Q31: A1;A2;C5 | R31: author_run | T31: mixed | U31: tidak | W31: Sec 5; Table 1; Table 2; Table 3; hal. 6-10 | X31: none | Y31: latensi runtime dan false positive rate dilaporkan (Sec 5, Tabel 2) | Z31: Framework pertahanan analisis hibrida (MTGuard) yang mengombinasikan asesmen pra-eksekusi dan verifikasi pasca-eksekusi pemanggilan tool MCP. Dievaluasi pada agen otomatisasi peramban dan analisis finansial, mencapai rata-rata detection rate 48.3% vs baseline 8.3%. Catatan deployment: prototipe internal/eksperimental (belum dirilis secara publik). | AA31: =IF(I31="","",IF(OR(I31="attack",I31="survey_review",I31="benchmark_measurement",I31="position_other",I31="not_defense"),"n/a",IF(OR(X31="spec_normatif",X31="produksi_bukti_publik"),"L3",IF(ISNUMBER(SEARCH("independent",R31)),"L2",IF(R31="author_run","L1",IF(R31="none","L0","")))))) | AB31: =IF(I31="","",IF(AND(K31="deterministic_policy",M31="ya"),"PERIKSA: deterministic_policy tetapi LLM/ML ada dalam keputusan. ","")&IF(AND(U31="ya",V31=""),"PERIKSA: adaptif=ya wajib ada kutipan. ","")&IF(AND(R31="none",U31<>"n/a_tanpa_evaluasi",U31<>""),"PERIKSA: tanpa evaluasi, adaptif harus n/a. ","")&IF(AND(OR(R31="author_run",R31="author_run+independent",R31="independent_only"),Q31=""),"PERIKSA: isi kelas_dievaluasi. ","")&IF(AND(OR(R31="author_run",R31="author_run+independent",R31="independent_only"),W31=""),"PERIKSA: isi lokasi_bukti. ","")&IF(AND(H31="tidak",R31<>""),"PERIKSA: tanpa teks lengkap, kosongkan kolom evaluasi. ","")) | AC31: include
A32: samuel-2026-secure-sandbox-environment-orchestrating-medical | B32: A Secure Sandbox Environment for Orchestrating Medical AI Agents Using Model Context Protocols and Role-Based Access Control. | C32: 2026 | D32: E2 | E32: kandidat_agent | F32: primary | H32: tidak | I32: defense_primary | J32: Secure Sandbox Environment with RBAC | K32: deterministic_policy | L32: Lingkungan sandbox yang aman dan kontrol akses berbasis peran (RBAC) untuk mengorkestrasi agen AI medis yang berkomunikasi melalui Model Context Protocol. | M32: tidak | N32: gateway_proxy | O32: R2;R4;R5;R6 | P32: A2;D1;C3 | Z32: [NON-OA / ABSTRACT-ONLY] Prosiding AMIA Joint Summits on Translational Science. Lingkungan sandbox dengan RBAC untuk alur kerja medis pada MCP (A2, D1, C3). Klaim default C1 dicabut. | AA32: =IF(I32="","",IF(OR(I32="attack",I32="survey_review",I32="benchmark_measurement",I32="position_other",I32="not_defense"),"n/a",IF(OR(X32="spec_normatif",X32="produksi_bukti_publik"),"L3",IF(ISNUMBER(SEARCH("independent",R32)),"L2",IF(R32="author_run","L1",IF(R32="none","L0","")))))) | AB32: =IF(I32="","",IF(AND(K32="deterministic_policy",M32="ya"),"PERIKSA: deterministic_policy tetapi LLM/ML ada dalam keputusan. ","")&IF(AND(U32="ya",V32=""),"PERIKSA: adaptif=ya wajib ada kutipan. ","")&IF(AND(R32="none",U32<>"n/a_tanpa_evaluasi",U32<>""),"PERIKSA: tanpa evaluasi, adaptif harus n/a. ","")&IF(AND(OR(R32="author_run",R32="author_run+independent",R32="independent_only"),Q32=""),"PERIKSA: isi kelas_dievaluasi. ","")&IF(AND(OR(R32="author_run",R32="author_run+independent",R32="independent_only"),W32=""),"PERIKSA: isi lokasi_bukti. ","")&IF(AND(H32="tidak",R32<>""),"PERIKSA: tanpa teks lengkap, kosongkan kolom evaluasi. ","")) | AC32: include
A33: shanshan-2026-runtime-policy-enforcement-mcp-based | B33: Runtime Policy Enforcement for MCP-Based LLM Agents | C33: 2026 | D33: E1 | E33: kandidat_agent | F33: primary | G33: https://doi.org/10.3390/electronics15132829 | H33: tidak | I33: not_defense | Z33: [AUDIT_v5_EXCLUDE: EC2] Dikeluarkan dari korpus MCP-spesifik oleh audit reviewer kedua v5. (dikeluarkan setelah audit reviewer kedua + rekonsiliasi) | AA33: =IF(I33="","",IF(OR(I33="attack",I33="survey_review",I33="benchmark_measurement",I33="position_other",I33="not_defense"),"n/a",IF(OR(X33="spec_normatif",X33="produksi_bukti_publik"),"L3",IF(ISNUMBER(SEARCH("independent",R33)),"L2",IF(R33="author_run","L1",IF(R33="none","L0","")))))) | AB33: =IF(I33="","",IF(AND(K33="deterministic_policy",M33="ya"),"PERIKSA: deterministic_policy tetapi LLM/ML ada dalam keputusan. ","")&IF(AND(U33="ya",V33=""),"PERIKSA: adaptif=ya wajib ada kutipan. ","")&IF(AND(R33="none",U33<>"n/a_tanpa_evaluasi",U33<>""),"PERIKSA: tanpa evaluasi, adaptif harus n/a. ","")&IF(AND(OR(R33="author_run",R33="author_run+independent",R33="independent_only"),Q33=""),"PERIKSA: isi kelas_dievaluasi. ","")&IF(AND(OR(R33="author_run",R33="author_run+independent",R33="independent_only"),W33=""),"PERIKSA: isi lokasi_bukti. ","")&IF(AND(H33="tidak",R33<>""),"PERIKSA: tanpa teks lengkap, kosongkan kolom evaluasi. ","")) | AC33: exclude | AD33: EC2 | AE33: dikeluarkan setelah audit reviewer kedua + rekonsiliasi
A34: shiqiang-2025-secure-model-context-protocol-large | B34: Secure Model Context Protocol for Large Language Models with Dual Signatures | C34: 2025 | D34: E1 | E34: kandidat_agent | F34: primary | G34: https://doi.org/10.1145/3737897.3767287 | H34: ya | I34: defense_primary | J34: Dual Signature MCP | K34: integrity_provenance | L34: Mekanisme verifikasi tanda tangan digital ganda (developer dan platform tepercaya) pada metadata tool dan berkas server MCP untuk mencegah tampering dan tool poisoning. | M34: tidak | N34: C | O34: R1;R2;R7 | P34: A1;B1;D3 | Q34: A1;B1;D3 | R34: author_run | T34: authors_own | U34: tidak | W34: Sec. 5, Tabel 1, hal. 4-5 | X34: none | Y34: latensi eksekusi 28.9 ms (+2.6 ms vs standar 26.3 ms), overhead memori +1.84% (Tabel 1) | Z34: Dual Signature MCP (defense_primary, L1). Verifikasi tanda tangan ganda mencegah modifikasi kode/tampering server setelah registrasi (B1/D3) dan injeksi prompt tool Add (A1). Latensi +2.6 ms (Tabel 1). | AA34: =IF(I34="","",IF(OR(I34="attack",I34="survey_review",I34="benchmark_measurement",I34="position_other",I34="not_defense"),"n/a",IF(OR(X34="spec_normatif",X34="produksi_bukti_publik"),"L3",IF(ISNUMBER(SEARCH("independent",R34)),"L2",IF(R34="author_run","L1",IF(R34="none","L0","")))))) | AB34: =IF(I34="","",IF(AND(K34="deterministic_policy",M34="ya"),"PERIKSA: deterministic_policy tetapi LLM/ML ada dalam keputusan. ","")&IF(AND(U34="ya",V34=""),"PERIKSA: adaptif=ya wajib ada kutipan. ","")&IF(AND(R34="none",U34<>"n/a_tanpa_evaluasi",U34<>""),"PERIKSA: tanpa evaluasi, adaptif harus n/a. ","")&IF(AND(OR(R34="author_run",R34="author_run+independent",R34="independent_only"),Q34=""),"PERIKSA: isi kelas_dievaluasi. ","")&IF(AND(OR(R34="author_run",R34="author_run+independent",R34="independent_only"),W34=""),"PERIKSA: isi lokasi_bukti. ","")&IF(AND(H34="tidak",R34<>""),"PERIKSA: tanpa teks lengkap, kosongkan kolom evaluasi. ","")) | AC34: include
A35: shriti-2026-aegis-preventing-cross-domain-resource | B35: AEGIS: Preventing Cross-Domain Resource Abuse in MCP | C35: 2026 | D35: E2 | E35: kandidat_agent | F35: primary | G35: https://arxiv.org/abs/2608.20481 | H35: ya | I35: defense_primary | J35: AEGIS | K35: deterministic_policy | L35: Komponen penegakan kebijakan pada gateway AI (ContextForge + OPA) yang menormalisasi ontologi parameter tools dan membatasi pemanggilan berlebihan untuk mencegah abuse sumber daya. | M35: tidak | N35: gateway_proxy | O35: R2;R3 | P35: OUT_OF_TAXONOMY:resource_abuse | Q35: OUT_OF_TAXONOMY:resource_abuse | R35: author_run | T35: authors_own | U35: tidak | W35: Sec. VII-C, Tabel III, hal. 5 | X35: none | Y35: Throughput 30.03 req/s vs 1.34; p95 latency 2863 ms vs 15562 ms; mem max 387.7 MB; waktu 4.17s | Z35: AEGIS: Preventing Cross-Domain Resource Abuse in MCP (defense_primary, L1). Menggunakan ontologi tool dan ambang batas OPA untuk mencegah eksploitasi dan konsumsi sumber daya berlebih lintas server/modalitas (RQ2). Kode internal IBM mcp-context-forge. Catatan deployment: prototipe internal/eksperimental (belum dirilis secara publik). | AA35: =IF(I35="","",IF(OR(I35="attack",I35="survey_review",I35="benchmark_measurement",I35="position_other",I35="not_defense"),"n/a",IF(OR(X35="spec_normatif",X35="produksi_bukti_publik"),"L3",IF(ISNUMBER(SEARCH("independent",R35)),"L2",IF(R35="author_run","L1",IF(R35="none","L0","")))))) | AB35: =IF(I35="","",IF(AND(K35="deterministic_policy",M35="ya"),"PERIKSA: deterministic_policy tetapi LLM/ML ada dalam keputusan. ","")&IF(AND(U35="ya",V35=""),"PERIKSA: adaptif=ya wajib ada kutipan. ","")&IF(AND(R35="none",U35<>"n/a_tanpa_evaluasi",U35<>""),"PERIKSA: tanpa evaluasi, adaptif harus n/a. ","")&IF(AND(OR(R35="author_run",R35="author_run+independent",R35="independent_only"),Q35=""),"PERIKSA: isi kelas_dievaluasi. ","")&IF(AND(OR(R35="author_run",R35="author_run+independent",R35="independent_only"),W35=""),"PERIKSA: isi lokasi_bukti. ","")&IF(AND(H35="tidak",R35<>""),"PERIKSA: tanpa teks lengkap, kosongkan kolom evaluasi. ","")) | AC35: include
A36: suraj-2026-gateway-architecture-enterprise-mcp-authentication | B36: A Gateway Architecture for Enterprise MCP Authentication: Unifying Heterogeneous Auth, Identity Delegation, and the User / Non-User Persona Problem | C36: 2026 | D36: E2 | E36: kandidat_agent | F36: primary | G36: https://arxiv.org/abs/2608.10760 | H36: ya | I36: proposal_only | J36: Enterprise MCP Authentication Gateway | K36: deterministic_policy | L36: Arsitektur gateway terpusat yang menerapkan model autentikasi dua sumbu (persona x kredensial), delegasi identitas OAuth/SSO, dan pengecekan akses service-account untuk mencegah confused deputy pada MCP enterprise. | M36: tidak | N36: gateway_proxy | O36: R1;R2;R3 | P36: C1;C3;A3 | R36: none | T36: none | U36: n/a_tanpa_evaluasi | W36: Sec. 4-7, hal. 3-8 | X36: none | Y36: not_reported | Z36: Makalah industry track (arXiv:2608.10760) mendokumentasikan arsitektur gateway autentikasi MCP di lingkungan internal PayPal. Tanpa evaluasi empiris pertahanan terhadap dataset serangan, dan tanpa dokumentasi rilis produk publik bertanggal mandiri, sehingga deployment dikode none (L0). | AA36: =IF(I36="","",IF(OR(I36="attack",I36="survey_review",I36="benchmark_measurement",I36="position_other",I36="not_defense"),"n/a",IF(OR(X36="spec_normatif",X36="produksi_bukti_publik"),"L3",IF(ISNUMBER(SEARCH("independent",R36)),"L2",IF(R36="author_run","L1",IF(R36="none","L0","")))))) | AB36: =IF(I36="","",IF(AND(K36="deterministic_policy",M36="ya"),"PERIKSA: deterministic_policy tetapi LLM/ML ada dalam keputusan. ","")&IF(AND(U36="ya",V36=""),"PERIKSA: adaptif=ya wajib ada kutipan. ","")&IF(AND(R36="none",U36<>"n/a_tanpa_evaluasi",U36<>""),"PERIKSA: tanpa evaluasi, adaptif harus n/a. ","")&IF(AND(OR(R36="author_run",R36="author_run+independent",R36="independent_only"),Q36=""),"PERIKSA: isi kelas_dievaluasi. ","")&IF(AND(OR(R36="author_run",R36="author_run+independent",R36="independent_only"),W36=""),"PERIKSA: isi lokasi_bukti. ","")&IF(AND(H36="tidak",R36<>""),"PERIKSA: tanpa teks lengkap, kosongkan kolom evaluasi. ","")) | AC36: include
A37: tobias-2026-machine-learning-based-detection-mcp | B37: Machine Learning-Based Detection of MCP Attacks | C37: 2026 | D37: E2 | E37: kandidat_agent | F37: primary | G37: https://arxiv.org/abs/2604.10534 | H37: ya | I37: defense_primary | J37: MCP ML-Based Attack Detector | K37: content_inspection_runtime | L37: Middleware deteksi berbasis machine learning terawasi (BERT, BiLSTM, SVC) yang menginspeksi deskripsi tool MCP sebelum eksekusi untuk mengidentifikasi dan memblokir tool poisoning. | M37: tidak | N37: gateway_proxy | O37: R2;R3 | P37: A1;B1 | Q37: A1 | R37: author_run | T37: third_party_public | U37: tidak | W37: Sec. 4, Tabel 4, hal. 7-10 | X37: none | Y37: Confusion matrix, F1 100% biner, multiclass SVC 90.56% dan BERT 88.33% | Z37: KODER 1 menandai teks lengkap. Model supervised ML (SVC, BERT, BiLSTM) dievaluasi pada dataset publik MCP-Tox; tanpa pengujian penyerang adaptif. Catatan deployment: prototipe internal/eksperimental (belum dirilis secara publik). | AA37: =IF(I37="","",IF(OR(I37="attack",I37="survey_review",I37="benchmark_measurement",I37="position_other",I37="not_defense"),"n/a",IF(OR(X37="spec_normatif",X37="produksi_bukti_publik"),"L3",IF(ISNUMBER(SEARCH("independent",R37)),"L2",IF(R37="author_run","L1",IF(R37="none","L0","")))))) | AB37: =IF(I37="","",IF(AND(K37="deterministic_policy",M37="ya"),"PERIKSA: deterministic_policy tetapi LLM/ML ada dalam keputusan. ","")&IF(AND(U37="ya",V37=""),"PERIKSA: adaptif=ya wajib ada kutipan. ","")&IF(AND(R37="none",U37<>"n/a_tanpa_evaluasi",U37<>""),"PERIKSA: tanpa evaluasi, adaptif harus n/a. ","")&IF(AND(OR(R37="author_run",R37="author_run+independent",R37="independent_only"),Q37=""),"PERIKSA: isi kelas_dievaluasi. ","")&IF(AND(OR(R37="author_run",R37="author_run+independent",R37="independent_only"),W37=""),"PERIKSA: isi lokasi_bukti. ","")&IF(AND(H37="tidak",R37<>""),"PERIKSA: tanpa teks lengkap, kosongkan kolom evaluasi. ","")) | AC37: include
A38: varun-2026-superlocalmemory-privacy-preserving-multi-agent | B38: SuperLocalMemory: Privacy-Preserving Multi-Agent Memory with Bayesian Trust Defense Against Memory Poisoning | C38: 2026 | D38: E2 | E38: kandidat_agent | F38: primary | G38: https://arxiv.org/abs/2603.02240 | H38: tidak | I38: not_defense | Z38: [AUDIT_v5_EXCLUDE: EC2] Dikeluarkan dari korpus MCP-spesifik oleh audit reviewer kedua v5. (audit lanjutan; diterima koordinator) | AA38: =IF(I38="","",IF(OR(I38="attack",I38="survey_review",I38="benchmark_measurement",I38="position_other",I38="not_defense"),"n/a",IF(OR(X38="spec_normatif",X38="produksi_bukti_publik"),"L3",IF(ISNUMBER(SEARCH("independent",R38)),"L2",IF(R38="author_run","L1",IF(R38="none","L0","")))))) | AB38: =IF(I38="","",IF(AND(K38="deterministic_policy",M38="ya"),"PERIKSA: deterministic_policy tetapi LLM/ML ada dalam keputusan. ","")&IF(AND(U38="ya",V38=""),"PERIKSA: adaptif=ya wajib ada kutipan. ","")&IF(AND(R38="none",U38<>"n/a_tanpa_evaluasi",U38<>""),"PERIKSA: tanpa evaluasi, adaptif harus n/a. ","")&IF(AND(OR(R38="author_run",R38="author_run+independent",R38="independent_only"),Q38=""),"PERIKSA: isi kelas_dievaluasi. ","")&IF(AND(OR(R38="author_run",R38="author_run+independent",R38="independent_only"),W38=""),"PERIKSA: isi lokasi_bukti. ","")&IF(AND(H38="tidak",R38<>""),"PERIKSA: tanpa teks lengkap, kosongkan kolom evaluasi. ","")) | AC38: exclude | AD38: EC2 | AE38: audit lanjutan; diterima koordinator
A39: wenbiao-2026-toolminimize-auditing-rewriting-llm-agent | B39: ToolMinimize: Auditing and Rewriting LLM Agent Tool Calls to Minimize Privacy Exposure | C39: 2026 | D39: E2 | E39: kandidat_agent | F39: primary | G39: https://arxiv.org/abs/2608.24957 | H39: tidak | I39: not_defense | Z39: [AUDIT_v5_EXCLUDE: EC2] Dikeluarkan dari korpus MCP-spesifik oleh audit reviewer kedua v5. (dikeluarkan setelah audit reviewer kedua + rekonsiliasi) | AA39: =IF(I39="","",IF(OR(I39="attack",I39="survey_review",I39="benchmark_measurement",I39="position_other",I39="not_defense"),"n/a",IF(OR(X39="spec_normatif",X39="produksi_bukti_publik"),"L3",IF(ISNUMBER(SEARCH("independent",R39)),"L2",IF(R39="author_run","L1",IF(R39="none","L0","")))))) | AB39: =IF(I39="","",IF(AND(K39="deterministic_policy",M39="ya"),"PERIKSA: deterministic_policy tetapi LLM/ML ada dalam keputusan. ","")&IF(AND(U39="ya",V39=""),"PERIKSA: adaptif=ya wajib ada kutipan. ","")&IF(AND(R39="none",U39<>"n/a_tanpa_evaluasi",U39<>""),"PERIKSA: tanpa evaluasi, adaptif harus n/a. ","")&IF(AND(OR(R39="author_run",R39="author_run+independent",R39="independent_only"),Q39=""),"PERIKSA: isi kelas_dievaluasi. ","")&IF(AND(OR(R39="author_run",R39="author_run+independent",R39="independent_only"),W39=""),"PERIKSA: isi lokasi_bukti. ","")&IF(AND(H39="tidak",R39<>""),"PERIKSA: tanpa teks lengkap, kosongkan kolom evaluasi. ","")) | AC39: exclude | AD39: EC2 | AE39: dikeluarkan setelah audit reviewer kedua + rekonsiliasi
A40: wenpeng-2025-mcp-guard-multi-stage-defense | B40: MCP-Guard: A Multi-Stage Defense-in-Depth Framework for Securing Model Context Protocol in Agentic AI | C40: 2025 | D40: E1 | E40: kandidat_agent | F40: primary | G40: https://arxiv.org/abs/2508.10991 | H40: ya | I40: defense_primary | J40: MCP-GUARD | K40: content_inspection_static | L40: Middleware keamanan tiga tahap yang menggabungkan filter sintaksis WAF (Tahap I), detektor neural berbasis embedding E5 ter-fine-tune (Tahap II), dan arbiter LLM (Tahap III) untuk mendeteksi payload berbahaya pada MCP. | M40: ya | N40: gateway_proxy | O40: R2;R6;R7 | P40: A1;A2;B1;B2;D1 | Q40: A1;A2;B1;B2 | R40: author_run | T40: mixed | U40: tidak | W40: Sec. 5, Tabel 4 & 5, Gambar 3, hal. 6-8 | X40: none | Y40: Runtime latency log scale: S1 ~1.2ms, S2 ~42ms, end-to-end pipeline ~120-250ms vs standalone LLM >10,000ms; F1-score 96.01% | Z40: KODER 1 menandai teks lengkap. Pipeline 3-tahap (WAF regex, E5 dense neural embedding, LLM arbitrator). Menggunakan LLM dalam keputusan akhir pada sampel ambigu (P(y|x) ~ 0.5). Catatan deployment: prototipe internal/eksperimental (belum dirilis secara publik). | AA40: =IF(I40="","",IF(OR(I40="attack",I40="survey_review",I40="benchmark_measurement",I40="position_other",I40="not_defense"),"n/a",IF(OR(X40="spec_normatif",X40="produksi_bukti_publik"),"L3",IF(ISNUMBER(SEARCH("independent",R40)),"L2",IF(R40="author_run","L1",IF(R40="none","L0","")))))) | AB40: =IF(I40="","",IF(AND(K40="deterministic_policy",M40="ya"),"PERIKSA: deterministic_policy tetapi LLM/ML ada dalam keputusan. ","")&IF(AND(U40="ya",V40=""),"PERIKSA: adaptif=ya wajib ada kutipan. ","")&IF(AND(R40="none",U40<>"n/a_tanpa_evaluasi",U40<>""),"PERIKSA: tanpa evaluasi, adaptif harus n/a. ","")&IF(AND(OR(R40="author_run",R40="author_run+independent",R40="independent_only"),Q40=""),"PERIKSA: isi kelas_dievaluasi. ","")&IF(AND(OR(R40="author_run",R40="author_run+independent",R40="independent_only"),W40=""),"PERIKSA: isi lokasi_bukti. ","")&IF(AND(H40="tidak",R40<>""),"PERIKSA: tanpa teks lengkap, kosongkan kolom evaluasi. ","")) | AC40: include
A41: wonbae-2026-securemcp-policy-enforced-llm-data | B41: SecureMCP: A Policy-Enforced LLM Data Access Framework for AIoT Systems via Model Context Protocol | C41: 2026 | D41: E2 | E41: kandidat_agent | F41: primary | G41: https://arxiv.org/abs/2605.05260 | H41: ya | I41: defense_primary | J41: SecureMCP | K41: deterministic_policy | L41: Kerangka kerja multi-lapis yang mengintegrasikan mesin RBAC (check_policy), cost gate EXPLAIN MySQL, SQL Interceptor, Risk Level Filter, dan isolasi DB untuk memblokir injeksi dan operasi ilegal pada pipeline NL2SQL MCP. | M41: tidak | N41: gateway_proxy | O41: R2;R3 | P41: B1;C1;C2;A2 | Q41: B1;C1;C2;A2 | R41: author_run | T41: mixed | U41: tidak | W41: Sec. 4 & 5, Tabel 1, 5, 6, hal. 6-12 | X41: prototype_open_source | Y41: EX-in-ALLOW 65.1%-76.4% vs baseline 63.8%; low operational overhead relatif terhadap inferensi LLM; policy compliance 82.3% | Z41: KODER 1 menandai teks lengkap. Pipeline 5 modul (RBAC check_policy, EXPLAIN cost gate, SQL interceptor, risk level filter, DB isolation). Tanpa pengujian penyerang adaptif. Repositori/artefak: https://zenodo.org/records/15000588. | AA41: =IF(I41="","",IF(OR(I41="attack",I41="survey_review",I41="benchmark_measurement",I41="position_other",I41="not_defense"),"n/a",IF(OR(X41="spec_normatif",X41="produksi_bukti_publik"),"L3",IF(ISNUMBER(SEARCH("independent",R41)),"L2",IF(R41="author_run","L1",IF(R41="none","L0","")))))) | AB41: =IF(I41="","",IF(AND(K41="deterministic_policy",M41="ya"),"PERIKSA: deterministic_policy tetapi LLM/ML ada dalam keputusan. ","")&IF(AND(U41="ya",V41=""),"PERIKSA: adaptif=ya wajib ada kutipan. ","")&IF(AND(R41="none",U41<>"n/a_tanpa_evaluasi",U41<>""),"PERIKSA: tanpa evaluasi, adaptif harus n/a. ","")&IF(AND(OR(R41="author_run",R41="author_run+independent",R41="independent_only"),Q41=""),"PERIKSA: isi kelas_dievaluasi. ","")&IF(AND(OR(R41="author_run",R41="author_run+independent",R41="independent_only"),W41=""),"PERIKSA: isi lokasi_bukti. ","")&IF(AND(H41="tidak",R41<>""),"PERIKSA: tanpa teks lengkap, kosongkan kolom evaluasi. ","")) | AC41: include
A42: xinyi-2026-smcp-secure-model-context-protocol | B42: SMCP: Secure Model Context Protocol | C42: 2026 | D42: E2 | E42: kandidat_agent | F42: primary | G42: https://arxiv.org/abs/2602.01129 | H42: ya | I42: proposal_only | J42: SMCP (Secure Model Context Protocol) | K42: protocol_provision | L42: Ekstensi protokol tingkat sistem yang mengintegrasikan manajemen identitas terpadu, autentikasi mutual, propagasi konteks keamanan berkelanjutan, dan penegakan kebijakan granular untuk mengamankan alur kerja MCP. | M42: tidak | N42: gateway_proxy | O42: R1;R2;R3;R4;R5;R6;R7 | P42: A1;B1;C1;C3;D3 | R42: none | T42: none | U42: n/a_tanpa_evaluasi | W42: Sec. 4 & 5, hal. 7-20 | X42: none | Y42: not_reported | Z42: Makalah desain dan spesifikasi ekstensi protokol komprehensif (SMCP) tanpa evaluasi empiris pertahanan terhadap dataset serangan. KODER 1 menandai teks lengkap. | AA42: =IF(I42="","",IF(OR(I42="attack",I42="survey_review",I42="benchmark_measurement",I42="position_other",I42="not_defense"),"n/a",IF(OR(X42="spec_normatif",X42="produksi_bukti_publik"),"L3",IF(ISNUMBER(SEARCH("independent",R42)),"L2",IF(R42="author_run","L1",IF(R42="none","L0","")))))) | AB42: =IF(I42="","",IF(AND(K42="deterministic_policy",M42="ya"),"PERIKSA: deterministic_policy tetapi LLM/ML ada dalam keputusan. ","")&IF(AND(U42="ya",V42=""),"PERIKSA: adaptif=ya wajib ada kutipan. ","")&IF(AND(R42="none",U42<>"n/a_tanpa_evaluasi",U42<>""),"PERIKSA: tanpa evaluasi, adaptif harus n/a. ","")&IF(AND(OR(R42="author_run",R42="author_run+independent",R42="independent_only"),Q42=""),"PERIKSA: isi kelas_dievaluasi. ","")&IF(AND(OR(R42="author_run",R42="author_run+independent",R42="independent_only"),W42=""),"PERIKSA: isi lokasi_bukti. ","")&IF(AND(H42="tidak",R42<>""),"PERIKSA: tanpa teks lengkap, kosongkan kolom evaluasi. ","")) | AC42: include
A43: yang-2026-mitigating-taint-style-vulnerabilities-mcp | B43: Mitigating Taint-Style Vulnerabilities in MCP Servers via Security-Aware Tool Descriptions | C43: 2026 | D43: E2 | E43: kandidat_agent | F43: primary | G43: https://arxiv.org/abs/2607.07461 | H43: ya | I43: defense_primary | J43: SPELLSMITH | K43: content_inspection_static | L43: Mekanisme mitigasi berbasis teks yang memperkaya deskripsi alat MCP dengan batasan keamanan perilaku dan menggunakan modul refleksi mandiri LLM untuk mencegah eksploitasi kerentanan taint-style. | M43: ya | N43: C | O43: R2;R5;R7 | P43: A1;B1;C5 | Q43: B1;C5 | R43: author_run | T43: mixed | U43: tidak | W43: Sec. 6, Tabel 6 & 7, hal. 8-11 | X43: none | Y43: ASR menurun dari 80.8% menjadi 1.5% (post-reflection); overhead komputasi inferensi refleksi tambahan | Z43: KODER 1 menandai teks lengkap. SPELLSMITH memanfaatkan augmentasi deskripsi alat dan refleksi mandiri LLM (GPT-4o) untuk memitigasi kerentanan taint-style pada alat MCP. Catatan deployment: prototipe internal/eksperimental (belum dirilis secara publik). | AA43: =IF(I43="","",IF(OR(I43="attack",I43="survey_review",I43="benchmark_measurement",I43="position_other",I43="not_defense"),"n/a",IF(OR(X43="spec_normatif",X43="produksi_bukti_publik"),"L3",IF(ISNUMBER(SEARCH("independent",R43)),"L2",IF(R43="author_run","L1",IF(R43="none","L0","")))))) | AB43: =IF(I43="","",IF(AND(K43="deterministic_policy",M43="ya"),"PERIKSA: deterministic_policy tetapi LLM/ML ada dalam keputusan. ","")&IF(AND(U43="ya",V43=""),"PERIKSA: adaptif=ya wajib ada kutipan. ","")&IF(AND(R43="none",U43<>"n/a_tanpa_evaluasi",U43<>""),"PERIKSA: tanpa evaluasi, adaptif harus n/a. ","")&IF(AND(OR(R43="author_run",R43="author_run+independent",R43="independent_only"),Q43=""),"PERIKSA: isi kelas_dievaluasi. ","")&IF(AND(OR(R43="author_run",R43="author_run+independent",R43="independent_only"),W43=""),"PERIKSA: isi lokasi_bukti. ","")&IF(AND(H43="tidak",R43<>""),"PERIKSA: tanpa teks lengkap, kosongkan kolom evaluasi. ","")) | AC43: include
A44: yifeng-2025-who-grants-agent-power-defending | B44: Who Grants the Agent Power? Defending Against Instruction Injection via Task-Centric Access Control | C44: 2025 | D44: E2 | E44: kandidat_agent | F44: primary | G44: https://arxiv.org/abs/2510.26212 | H44: tidak | I44: not_defense | Z44: [AUDIT_v5_EXCLUDE: EC2] Dikeluarkan dari korpus MCP-spesifik oleh audit reviewer kedua v5. (audit lanjutan; diterima koordinator) | AA44: =IF(I44="","",IF(OR(I44="attack",I44="survey_review",I44="benchmark_measurement",I44="position_other",I44="not_defense"),"n/a",IF(OR(X44="spec_normatif",X44="produksi_bukti_publik"),"L3",IF(ISNUMBER(SEARCH("independent",R44)),"L2",IF(R44="author_run","L1",IF(R44="none","L0","")))))) | AB44: =IF(I44="","",IF(AND(K44="deterministic_policy",M44="ya"),"PERIKSA: deterministic_policy tetapi LLM/ML ada dalam keputusan. ","")&IF(AND(U44="ya",V44=""),"PERIKSA: adaptif=ya wajib ada kutipan. ","")&IF(AND(R44="none",U44<>"n/a_tanpa_evaluasi",U44<>""),"PERIKSA: tanpa evaluasi, adaptif harus n/a. ","")&IF(AND(OR(R44="author_run",R44="author_run+independent",R44="independent_only"),Q44=""),"PERIKSA: isi kelas_dievaluasi. ","")&IF(AND(OR(R44="author_run",R44="author_run+independent",R44="independent_only"),W44=""),"PERIKSA: isi lokasi_bukti. ","")&IF(AND(H44="tidak",R44<>""),"PERIKSA: tanpa teks lengkap, kosongkan kolom evaluasi. ","")) | AC44: exclude | AD44: EC2 | AE44: audit lanjutan; diterima koordinator
A45: yiheng-2026-component-manipulation-system-compromise-understanding | B45: From Component Manipulation to System Compromise: Understanding and Detecting Malicious MCP Servers | C45: 2026 | D45: E2 | E45: kandidat_agent | F45: primary | G45: https://arxiv.org/abs/2604.01905 | H45: ya | I45: defense_primary | J45: Connor | K45: content_inspection_static | L45: Detektor deviasi perilaku dua tahap yang menggabungkan analisis statis konfigurasi/kode pre-eksekusi dengan pelacakan lintasan eksekusi dan penilai deviasi berbasis LLM untuk mendeteksi server MCP berbahaya. | M45: ya | N45: gateway_proxy | O45: R2;R7 | P45: A1;A3;B3;D3 | Q45: A1;A3;B3 | R45: author_run | T45: mixed | U45: tidak | W45: Sec. 6, Tabel 7 & 8, hal. 22-25 | X45: prototype_open_source | Y45: F1-score 94.6% (mengungguli SOTA sebesar 8.9% - 59.6%), pre-execution latency 3.2s, in-execution tracing overhead | Z45: KODER 1 menandai teks lengkap. Connor mengombinasikan analisis statis pre-eksekusi (Joern/CPG) dan deteksi deviasi perilaku runtime dengan model LLM (GPT-5/Claude Sonnet 4). Repositori/artefak: https://github.com/yiheng98/Connor. | AA45: =IF(I45="","",IF(OR(I45="attack",I45="survey_review",I45="benchmark_measurement",I45="position_other",I45="not_defense"),"n/a",IF(OR(X45="spec_normatif",X45="produksi_bukti_publik"),"L3",IF(ISNUMBER(SEARCH("independent",R45)),"L2",IF(R45="author_run","L1",IF(R45="none","L0","")))))) | AB45: =IF(I45="","",IF(AND(K45="deterministic_policy",M45="ya"),"PERIKSA: deterministic_policy tetapi LLM/ML ada dalam keputusan. ","")&IF(AND(U45="ya",V45=""),"PERIKSA: adaptif=ya wajib ada kutipan. ","")&IF(AND(R45="none",U45<>"n/a_tanpa_evaluasi",U45<>""),"PERIKSA: tanpa evaluasi, adaptif harus n/a. ","")&IF(AND(OR(R45="author_run",R45="author_run+independent",R45="independent_only"),Q45=""),"PERIKSA: isi kelas_dievaluasi. ","")&IF(AND(OR(R45="author_run",R45="author_run+independent",R45="independent_only"),W45=""),"PERIKSA: isi lokasi_bukti. ","")&IF(AND(H45="tidak",R45<>""),"PERIKSA: tanpa teks lengkap, kosongkan kolom evaluasi. ","")) | AC45: include
A46: ying-2026-options-not-clicks-lattice-refinement | B46: Options, Not Clicks: Lattice Refinement for Consent-Driven MCP Authorization | C46: 2026 | D46: E2 | E46: kandidat_agent | F46: primary | G46: https://arxiv.org/abs/2605.11360 | H46: ya | I46: defense_primary | J46: ConLeash | K46: deterministic_policy | L46: Middleware persetujuan sisi klien berbasis neuro-simbolik yang menggunakan lattice containment dan Datalog deterministik untuk menegakkan otorisasi berlingkup batas dan menyaring eskalasi izin MCP. | M46: tidak | N46: C | O46: R1;R2;R3 | P46: C1;A2;B2 | Q46: C1;A2 | R46: author_run | T46: third_party_public | U46: tidak | W46: Sec. 8, Tabel 2 & 3, hal. 11-14 | X46: none | Y46: 8.2 ms reasoning overhead per step; F1 98.7%; menangkap 99.4% eskalasi izin; user study N=16 | Z46: KODER 1 menandai teks lengkap. ConLeash adalah middleware neuro-simbolik; LLM hanya sebagai penerjemah fakta, sedangkan keputusan otorisasi lattice containment sepenuhnya deterministik via Datalog. Catatan deployment: prototipe internal/eksperimental (belum dirilis secara publik). | AA46: =IF(I46="","",IF(OR(I46="attack",I46="survey_review",I46="benchmark_measurement",I46="position_other",I46="not_defense"),"n/a",IF(OR(X46="spec_normatif",X46="produksi_bukti_publik"),"L3",IF(ISNUMBER(SEARCH("independent",R46)),"L2",IF(R46="author_run","L1",IF(R46="none","L0","")))))) | AB46: =IF(I46="","",IF(AND(K46="deterministic_policy",M46="ya"),"PERIKSA: deterministic_policy tetapi LLM/ML ada dalam keputusan. ","")&IF(AND(U46="ya",V46=""),"PERIKSA: adaptif=ya wajib ada kutipan. ","")&IF(AND(R46="none",U46<>"n/a_tanpa_evaluasi",U46<>""),"PERIKSA: tanpa evaluasi, adaptif harus n/a. ","")&IF(AND(OR(R46="author_run",R46="author_run+independent",R46="independent_only"),Q46=""),"PERIKSA: isi kelas_dievaluasi. ","")&IF(AND(OR(R46="author_run",R46="author_run+independent",R46="independent_only"),W46=""),"PERIKSA: isi lokasi_bukti. ","")&IF(AND(H46="tidak",R46<>""),"PERIKSA: tanpa teks lengkap, kosongkan kolom evaluasi. ","")) | AC46: include
A47: zehua-2026-no-box-vulnerability-analysis-description | B47: No-Box Vulnerability Analysis: Description-only Detection of Indirect Prompt Injection Vulnerabilities in MCP Servers | C47: 2026 | D47: E2 | E47: kandidat_agent | F47: primary | G47: https://arxiv.org/abs/2609.10854 | H47: ya | I47: defense_primary | J47: MCPSEC | K47: content_inspection_static | L47: Pipeline analisis kerentanan no-box yang mengaudit metadata registrasi server MCP untuk mendeteksi potensi aliran data dan kerentanan indirect prompt injection tanpa akses source code atau runtime. | M47: ya | N47: offline_analysis | O47: R7 | P47: B2 | Q47: B2 | R47: author_run | T47: mixed | U47: tidak | W47: Sec. VII, Tabel II, hal. 7-10 | X47: none | Y47: 98.9% recall (94 dari 95 vulnerable tools terdeteksi) vs baseline LLM 84.2%; runtime metadata analysis | Z47: KODER 1 menandai teks lengkap. MCPSEC adalah sistem analisis kerentanan no-box berbasis metadata alat untuk mendeteksi indirect prompt injection (B2) sebelum deployment. Catatan deployment: prototipe internal/eksperimental (belum dirilis secara publik). | AA47: =IF(I47="","",IF(OR(I47="attack",I47="survey_review",I47="benchmark_measurement",I47="position_other",I47="not_defense"),"n/a",IF(OR(X47="spec_normatif",X47="produksi_bukti_publik"),"L3",IF(ISNUMBER(SEARCH("independent",R47)),"L2",IF(R47="author_run","L1",IF(R47="none","L0","")))))) | AB47: =IF(I47="","",IF(AND(K47="deterministic_policy",M47="ya"),"PERIKSA: deterministic_policy tetapi LLM/ML ada dalam keputusan. ","")&IF(AND(U47="ya",V47=""),"PERIKSA: adaptif=ya wajib ada kutipan. ","")&IF(AND(R47="none",U47<>"n/a_tanpa_evaluasi",U47<>""),"PERIKSA: tanpa evaluasi, adaptif harus n/a. ","")&IF(AND(OR(R47="author_run",R47="author_run+independent",R47="independent_only"),Q47=""),"PERIKSA: isi kelas_dievaluasi. ","")&IF(AND(OR(R47="author_run",R47="author_run+independent",R47="independent_only"),W47=""),"PERIKSA: isi lokasi_bukti. ","")&IF(AND(H47="tidak",R47<>""),"PERIKSA: tanpa teks lengkap, kosongkan kolom evaluasi. ","")) | AC47: include
A48: zhenhong-2026-mcpshield-security-cognition-layer-adaptive | B48: MCPShield: A Security Cognition Layer for Adaptive Trust Calibration in Model Context Protocol Agents | C48: 2026 | D48: E2 | E48: kandidat_agent | F48: primary | G48: https://arxiv.org/abs/2602.14281 | H48: ya | I48: defense_primary | J48: MCPShield | K48: content_inspection_static | L48: Lapisan kognisi keamanan plug-in yang menggabungkan probing kognitif pra-invokasi, proyeksi terisolasi saat eksekusi, dan penalaran periodik pasca-invokasi untuk mengalibrasi kepercayaan agen MCP. | M48: ya | N48: gateway_proxy | O48: R2;R7 | P48: A1;A3;B1;B2;D3 | Q48: A1;A3;B1;B2;D3 | R48: author_run | T48: mixed | U48: tidak | W48: Sec. 5, Tabel 1, 2, 3, hal. 7-8 | X48: none | Y48: Tingkat pertahanan rata-rata 95.30% vs 10.05% baseline; false positive deny rate rendah (Tabel 2); runtime dan token overhead (Gbr 3 & 4) | Z48: KODER 1 menandai teks lengkap. Mengevaluasi 6 suite serangan termasuk Adaptive Attack (Zhan et al., 2025) yang merupakan benchmark tetap pihak ketiga yang dirancang terhadap pertahanan lain, bukan serangan yang disetel terhadap MCPShield (adaptif=tidak, sesuai Pedoman 7.3). Catatan deployment: prototipe internal/eksperimental (belum dirilis secara publik). | AA48: =IF(I48="","",IF(OR(I48="attack",I48="survey_review",I48="benchmark_measurement",I48="position_other",I48="not_defense"),"n/a",IF(OR(X48="spec_normatif",X48="produksi_bukti_publik"),"L3",IF(ISNUMBER(SEARCH("independent",R48)),"L2",IF(R48="author_run","L1",IF(R48="none","L0","")))))) | AB48: =IF(I48="","",IF(AND(K48="deterministic_policy",M48="ya"),"PERIKSA: deterministic_policy tetapi LLM/ML ada dalam keputusan. ","")&IF(AND(U48="ya",V48=""),"PERIKSA: adaptif=ya wajib ada kutipan. ","")&IF(AND(R48="none",U48<>"n/a_tanpa_evaluasi",U48<>""),"PERIKSA: tanpa evaluasi, adaptif harus n/a. ","")&IF(AND(OR(R48="author_run",R48="author_run+independent",R48="independent_only"),Q48=""),"PERIKSA: isi kelas_dievaluasi. ","")&IF(AND(OR(R48="author_run",R48="author_run+independent",R48="independent_only"),W48=""),"PERIKSA: isi lokasi_bukti. ","")&IF(AND(H48="tidak",R48<>""),"PERIKSA: tanpa teks lengkap, kosongkan kolom evaluasi. ","")) | AC48: include
A49: zhiqiang-2025-mindguard-intrinsic-decision-inspection-securing | B49: MindGuard: Intrinsic Decision Inspection for Securing LLM Agents Against Metadata Poisoning | C49: 2025 | D49: E2 | E49: kandidat_agent | F49: primary | G49: https://arxiv.org/abs/2508.20412 | H49: ya | I49: defense_primary | J49: MindGuard | K49: content_inspection_runtime | L49: Plugin inspeksi keputusan intrinsik yang menganalisis matriks aktivasi perhatian (DDG & Total Attention Energy) pada LLM host untuk mendeteksi metadata poisoning tanpa model eksternal. | M49: ya | N49: C | O49: R2;R3 | P49: A1;B3;B1 | Q49: A1 | R49: author_run | T49: mixed | U49: ya | V49: Attacker crafts a subtle payload to alter LLM's decision without a detectable attention activation. | W49: Sec. 6.5; Fig. 8b; hal. 11 | X49: none | Y49: Average Precision > 97.6%, akurasi atribusi > 98.6%, hemat 1,000+ token per invokasi, subsecond runtime cost | Z49: MindGuard mengekstraksi matriks atensi runtime LLM (TAE). Serangan adaptif Attention Minimization (Sec. 6.5, Fig. 8b). C4 ditolak. Catatan deployment: prototipe internal/eksperimental (belum dirilis secara publik). | AA49: =IF(I49="","",IF(OR(I49="attack",I49="survey_review",I49="benchmark_measurement",I49="position_other",I49="not_defense"),"n/a",IF(OR(X49="spec_normatif",X49="produksi_bukti_publik"),"L3",IF(ISNUMBER(SEARCH("independent",R49)),"L2",IF(R49="author_run","L1",IF(R49="none","L0","")))))) | AB49: =IF(I49="","",IF(AND(K49="deterministic_policy",M49="ya"),"PERIKSA: deterministic_policy tetapi LLM/ML ada dalam keputusan. ","")&IF(AND(U49="ya",V49=""),"PERIKSA: adaptif=ya wajib ada kutipan. ","")&IF(AND(R49="none",U49<>"n/a_tanpa_evaluasi",U49<>""),"PERIKSA: tanpa evaluasi, adaptif harus n/a. ","")&IF(AND(OR(R49="author_run",R49="author_run+independent",R49="independent_only"),Q49=""),"PERIKSA: isi kelas_dievaluasi. ","")&IF(AND(OR(R49="author_run",R49="author_run+independent",R49="independent_only"),W49=""),"PERIKSA: isi lokasi_bukti. ","")&IF(AND(H49="tidak",R49<>""),"PERIKSA: tanpa teks lengkap, kosongkan kolom evaluasi. ","")) | AC49: include
A50: zhiyang-2026-acle-mcp-attested-capability-leases | B50: ACLE-MCP: Attested Capability Leases for Execution-Time Trust in Remote LLM Tool Use | C50: 2026 | D50: E2 | E50: kandidat_agent | F50: primary | G50: https://arxiv.org/abs/2609.02690 | H50: ya | I50: defense_primary | J50: ACLE-MCP | K50: protocol_provision | L50: Arsitektur capability lease berlingkup invokasi dengan atestasi vTPM dan Execution Gate pada sisi penyedia alat untuk memvalidasi beban kerja dan memitigasi celah kepercayaan pasca-otorisasi remote MCP. | M50: tidak | N50: S | O50: R2;R3 | P50: A3;C1;C3;D3 | Q50: A3;C1;C3;D3 | R50: author_run | T50: authors_own | U50: tidak | W50: Sec. Evaluation, Tabel 1 & Gbr 3, hal. 6-8 | X50: none | Y50: P95 latency overhead 25.7% (normal allowed calls) vs OAuth-only; memblokir 100% keluarga serangan yang dievaluasi | Z50: KODER 1 menandai teks lengkap. Arsitektur capability lease berlingkup invokasi dengan atestasi vTPM dan Execution Gate pada sisi server MCP untuk menutup celah post-authorization trust gap. Catatan deployment: prototipe internal/eksperimental (belum dirilis secara publik). | AA50: =IF(I50="","",IF(OR(I50="attack",I50="survey_review",I50="benchmark_measurement",I50="position_other",I50="not_defense"),"n/a",IF(OR(X50="spec_normatif",X50="produksi_bukti_publik"),"L3",IF(ISNUMBER(SEARCH("independent",R50)),"L2",IF(R50="author_run","L1",IF(R50="none","L0","")))))) | AB50: =IF(I50="","",IF(AND(K50="deterministic_policy",M50="ya"),"PERIKSA: deterministic_policy tetapi LLM/ML ada dalam keputusan. ","")&IF(AND(U50="ya",V50=""),"PERIKSA: adaptif=ya wajib ada kutipan. ","")&IF(AND(R50="none",U50<>"n/a_tanpa_evaluasi",U50<>""),"PERIKSA: tanpa evaluasi, adaptif harus n/a. ","")&IF(AND(OR(R50="author_run",R50="author_run+independent",R50="independent_only"),Q50=""),"PERIKSA: isi kelas_dievaluasi. ","")&IF(AND(OR(R50="author_run",R50="author_run+independent",R50="independent_only"),W50=""),"PERIKSA: isi lokasi_bukti. ","")&IF(AND(H50="tidak",R50<>""),"PERIKSA: tanpa teks lengkap, kosongkan kolom evaluasi. ","")) | AC50: include
A51: zhonghao-2025-aegismcp-online-graph-intrusion-detection | B51: AegisMCP: Online Graph Intrusion Detection for Tool-Augmented LLMs on Edge Devices | C51: 2025 | D51: E2 | E51: kandidat_agent | F51: primary | G51: https://arxiv.org/abs/2510.19462 | H51: ya | I51: defense_primary | J51: AegisMCP | K51: content_inspection_runtime | L51: Sistem deteksi intrusi tingkat protokol berbasis graf temporal heterogen (NEBULA-Schema) yang mendeteksi anomali perilaku dan chaining alat MCP secara near-real-time pada perangkat edge. | M51: tidak | N51: gateway_proxy | O51: R2;R7 | P51: A2;A3;B1;D3 | Q51: A2;A3;D3 | R51: author_run | T51: authors_own | U51: tidak | W51: Sec. VI, Tabel II, Gambar 4, hal. 7-10 | X51: none | Y51: Sub-second latency (inferensi per jendela < 1s pada Intel N150-class CPU edge hardware); F1 > 0.92 | Z51: KODER 1 menandai teks lengkap. Detektor intrusi streaming berbasis representasi graf temporal (NEBULA-Schema) berjalan di CPU edge tanpa LLM. Evasion dianalisis secara kualitatif di Sec. C. Catatan deployment: prototipe internal/eksperimental (belum dirilis secara publik). | AA51: =IF(I51="","",IF(OR(I51="attack",I51="survey_review",I51="benchmark_measurement",I51="position_other",I51="not_defense"),"n/a",IF(OR(X51="spec_normatif",X51="produksi_bukti_publik"),"L3",IF(ISNUMBER(SEARCH("independent",R51)),"L2",IF(R51="author_run","L1",IF(R51="none","L0","")))))) | AB51: =IF(I51="","",IF(AND(K51="deterministic_policy",M51="ya"),"PERIKSA: deterministic_policy tetapi LLM/ML ada dalam keputusan. ","")&IF(AND(U51="ya",V51=""),"PERIKSA: adaptif=ya wajib ada kutipan. ","")&IF(AND(R51="none",U51<>"n/a_tanpa_evaluasi",U51<>""),"PERIKSA: tanpa evaluasi, adaptif harus n/a. ","")&IF(AND(OR(R51="author_run",R51="author_run+independent",R51="independent_only"),Q51=""),"PERIKSA: isi kelas_dievaluasi. ","")&IF(AND(OR(R51="author_run",R51="author_run+independent",R51="independent_only"),W51=""),"PERIKSA: isi lokasi_bukti. ","")&IF(AND(H51="tidak",R51<>""),"PERIKSA: tanpa teks lengkap, kosongkan kolom evaluasi. ","")) | AC51: include
A52: zhuoran-2026-mcp-sandboxscan-wasm-based-secure | B52: MCP-SandboxScan: WASM-based Secure Execution and Runtime Analysis for MCP Tools | C52: 2026 | D52: E2 | E52: kandidat_agent | F52: primary | G52: https://arxiv.org/abs/2601.01241 | H52: ya | I52: defense_primary | J52: MCP-SandboxScan (SandScope) | K52: isolation_containment | L52: Kerangka kerja audit dan sandboxing berbasis WASM/WASI yang mengisolasi eksekusi alat MCP dan mendeteksi runtime witness kebocoran data sumber-ke-muara (canary) pada output protokol. | M52: tidak | N52: gateway_proxy | O52: R2;R5;R6 | P52: A2;D1;D3 | Q52: A2;D1 | R52: author_run | T52: mixed | U52: tidak | W52: Sec. 4, Tabel 1 & 2, hal. 7-10 | X52: none | Y52: Shallow dynamic scan 35 repo, latensi scan ~detik, deteksi kebocoran canary akurat | Z52: KODER 1 menandai teks lengkap. SandScope menggabungkan sandboxing WASM/WASI dengan deteksi saksi aliran data (canary) dan profiling semantik tools/list. Pengujian transformasi mencakup ROT13, hex, base64. Catatan deployment: prototipe internal/eksperimental (belum dirilis secara publik). | AA52: =IF(I52="","",IF(OR(I52="attack",I52="survey_review",I52="benchmark_measurement",I52="position_other",I52="not_defense"),"n/a",IF(OR(X52="spec_normatif",X52="produksi_bukti_publik"),"L3",IF(ISNUMBER(SEARCH("independent",R52)),"L2",IF(R52="author_run","L1",IF(R52="none","L0","")))))) | AB52: =IF(I52="","",IF(AND(K52="deterministic_policy",M52="ya"),"PERIKSA: deterministic_policy tetapi LLM/ML ada dalam keputusan. ","")&IF(AND(U52="ya",V52=""),"PERIKSA: adaptif=ya wajib ada kutipan. ","")&IF(AND(R52="none",U52<>"n/a_tanpa_evaluasi",U52<>""),"PERIKSA: tanpa evaluasi, adaptif harus n/a. ","")&IF(AND(OR(R52="author_run",R52="author_run+independent",R52="independent_only"),Q52=""),"PERIKSA: isi kelas_dievaluasi. ","")&IF(AND(OR(R52="author_run",R52="author_run+independent",R52="independent_only"),W52=""),"PERIKSA: isi lokasi_bukti. ","")&IF(AND(H52="tidak",R52<>""),"PERIKSA: tanpa teks lengkap, kosongkan kolom evaluasi. ","")) | AC52: include
A53: gabriela-2025-security-posture-evaluation-model-context | B53: Security Posture Evaluation of Model Context Protocol Servers Against Prompt Injection | C53: 2025 | D53: E1 | E53: kandidat_agent | F53: proposal_only | G53: https://doi.org/10.1109/siitme67657.2025.11293682 | H53: tidak | I53: benchmark_measurement | Z53: [NON-OA / ABSTRACT-ONLY] Makalah IEEE SIITME 2025 dengan akses tertutup (DOI: 10.1109/siitme67657.2025.11293682). Studi evaluasi postur keamanan server MCP terhadap prompt injection (studi pengukuran/evaluasi empiris tanpa usulan mitigasi baru). KODER 1 menandai proposal_only secara otomatis. | AA53: =IF(I53="","",IF(OR(I53="attack",I53="survey_review",I53="benchmark_measurement",I53="position_other",I53="not_defense"),"n/a",IF(OR(X53="spec_normatif",X53="produksi_bukti_publik"),"L3",IF(ISNUMBER(SEARCH("independent",R53)),"L2",IF(R53="author_run","L1",IF(R53="none","L0","")))))) | AB53: =IF(I53="","",IF(AND(K53="deterministic_policy",M53="ya"),"PERIKSA: deterministic_policy tetapi LLM/ML ada dalam keputusan. ","")&IF(AND(U53="ya",V53=""),"PERIKSA: adaptif=ya wajib ada kutipan. ","")&IF(AND(R53="none",U53<>"n/a_tanpa_evaluasi",U53<>""),"PERIKSA: tanpa evaluasi, adaptif harus n/a. ","")&IF(AND(OR(R53="author_run",R53="author_run+independent",R53="independent_only"),Q53=""),"PERIKSA: isi kelas_dievaluasi. ","")&IF(AND(OR(R53="author_run",R53="author_run+independent",R53="independent_only"),W53=""),"PERIKSA: isi lokasi_bukti. ","")&IF(AND(H53="tidak",R53<>""),"PERIKSA: tanpa teks lengkap, kosongkan kolom evaluasi. ","")) | AC53: include
A54: grigoris-2025-securing-mcp-based-agent-workflows | B54: Securing MCP-based Agent Workflows | C54: 2025 | D54: E1 | E54: kandidat_agent | F54: proposal_only | G54: https://doi.org/10.1145/3766882.3767177 | H54: ya | I54: defense_primary | J54: SAMOS | K54: deterministic_policy | L54: Sistem Information Flow Control (IFC) tingkat gateway MCP yang menegakkan kebijakan keamanan berbasis label kerahasiaan read/write dan anotasi kapabilitas tool. | M54: tidak | N54: gateway_proxy | O54: R2;R3;R5 | P54: A2;D1;D2 | Q54: A2;D1;D2 | R54: author_run | T54: authors_own | U54: tidak | W54: Sec. 3-4, Tabel 1, hal. 3-5 | X54: none | Y54: not_reported | Z54: Teks lengkap tersedia di papers/acm. Validasi studi kasus nyata pencegahan kebocoran repositori privat GitHub MCP server di Claude Desktop. | AA54: =IF(I54="","",IF(OR(I54="attack",I54="survey_review",I54="benchmark_measurement",I54="position_other",I54="not_defense"),"n/a",IF(OR(X54="spec_normatif",X54="produksi_bukti_publik"),"L3",IF(ISNUMBER(SEARCH("independent",R54)),"L2",IF(R54="author_run","L1",IF(R54="none","L0","")))))) | AB54: =IF(I54="","",IF(AND(K54="deterministic_policy",M54="ya"),"PERIKSA: deterministic_policy tetapi LLM/ML ada dalam keputusan. ","")&IF(AND(U54="ya",V54=""),"PERIKSA: adaptif=ya wajib ada kutipan. ","")&IF(AND(R54="none",U54<>"n/a_tanpa_evaluasi",U54<>""),"PERIKSA: tanpa evaluasi, adaptif harus n/a. ","")&IF(AND(OR(R54="author_run",R54="author_run+independent",R54="independent_only"),Q54=""),"PERIKSA: isi kelas_dievaluasi. ","")&IF(AND(OR(R54="author_run",R54="author_run+independent",R54="independent_only"),W54=""),"PERIKSA: isi lokasi_bukti. ","")&IF(AND(H54="tidak",R54<>""),"PERIKSA: tanpa teks lengkap, kosongkan kolom evaluasi. ","")) | AC54: include
A55: herman-2025-securing-model-context-protocol-mcp | B55: Securing the Model Context Protocol (MCP): Risks, Controls, and Governance | C55: 2025 | D55: E2 | E55: kandidat_agent | F55: proposal_only | G55: https://arxiv.org/abs/2511.20920 | H55: ya | I55: proposal_only | J55: MCP Defense-in-Depth Control Framework | K55: deterministic_policy | L55: Kerangka kerja kontrol pertahanan berlapis dan arsitektur gateway yang menerapkan autentikasi granular, pelacakan provenansi, sandboxing kontainer, dan penegakan kebijakan inline DLP untuk MCP enterprise. | M55: tidak | N55: gateway_proxy | O55: R1;R2;R4;R5;R6;R7 | P55: A1;A2;A3;B1;B2;C3;D3 | R55: none | T55: none | U55: n/a_tanpa_evaluasi | W55: Sec. 4 & 5, hal. 8-15 | X55: none | Y55: not_reported | Z55: Makalah usulan kontrol pertahanan berlapis (Vanta & MintMCP) tanpa pengujian empiris kuantitatif terhadap dataset serangan. Penulis menyatakan tidak menyajikan tolok ukur biaya penegakan. KODER 1 menandai teks lengkap. | AA55: =IF(I55="","",IF(OR(I55="attack",I55="survey_review",I55="benchmark_measurement",I55="position_other",I55="not_defense"),"n/a",IF(OR(X55="spec_normatif",X55="produksi_bukti_publik"),"L3",IF(ISNUMBER(SEARCH("independent",R55)),"L2",IF(R55="author_run","L1",IF(R55="none","L0","")))))) | AB55: =IF(I55="","",IF(AND(K55="deterministic_policy",M55="ya"),"PERIKSA: deterministic_policy tetapi LLM/ML ada dalam keputusan. ","")&IF(AND(U55="ya",V55=""),"PERIKSA: adaptif=ya wajib ada kutipan. ","")&IF(AND(R55="none",U55<>"n/a_tanpa_evaluasi",U55<>""),"PERIKSA: tanpa evaluasi, adaptif harus n/a. ","")&IF(AND(OR(R55="author_run",R55="author_run+independent",R55="independent_only"),Q55=""),"PERIKSA: isi kelas_dievaluasi. ","")&IF(AND(OR(R55="author_run",R55="author_run+independent",R55="independent_only"),W55=""),"PERIKSA: isi lokasi_bukti. ","")&IF(AND(H55="tidak",R55<>""),"PERIKSA: tanpa teks lengkap, kosongkan kolom evaluasi. ","")) | AC55: include
A56: jaehyun-2025-preserving-onem2m-security-semantics-llm | B56: Preserving oneM2M Security Semantics in LLM-IoT Integration with Model Context Protocol | C56: 2025 | D56: E1 | E56: kandidat_agent | F56: proposal_only | G56: https://doi.org/10.1109/AIoT66900.2025.00032 | H56: ya | I56: defense_primary | J56: MCP-IPE (MCP Interworking Proxy Entity) | K56: deterministic_policy | L56: Proxy interworking yang memvalidasi Personal Access Token (PAT) agen, mengikat AE-ID, dan menegakkan kebijakan kontrol akses (ACP) oneM2M deny-by-default. | M56: tidak | N56: gateway_proxy | O56: R1;R2;R3;R5 | P56: C1;C3;OUT_OF_TAXONOMY:resource_abuse | Q56: C1;C3;OUT_OF_TAXONOMY:resource_abuse | R56: author_run | T56: authors_own | U56: tidak | W56: Sec. VI, Gbr 6, hal. 5-7 | X56: none | Y56: dilaporkan: acceptance rate pada 100 percobaan per 8 skenario STRIDE (Gbr 6) | Z56: MCP-IPE (defense_primary, L1). Penegakan ACP deny-by-default (C1), autentikasi token tidak valid (C3), dan mitigasi rate-burst 429 flooding (STRIDE DoS -> OUT_OF_TAXONOMY:resource_abuse) pada 8 skenario x 100 percobaan (Gbr 6). | AA56: =IF(I56="","",IF(OR(I56="attack",I56="survey_review",I56="benchmark_measurement",I56="position_other",I56="not_defense"),"n/a",IF(OR(X56="spec_normatif",X56="produksi_bukti_publik"),"L3",IF(ISNUMBER(SEARCH("independent",R56)),"L2",IF(R56="author_run","L1",IF(R56="none","L0","")))))) | AB56: =IF(I56="","",IF(AND(K56="deterministic_policy",M56="ya"),"PERIKSA: deterministic_policy tetapi LLM/ML ada dalam keputusan. ","")&IF(AND(U56="ya",V56=""),"PERIKSA: adaptif=ya wajib ada kutipan. ","")&IF(AND(R56="none",U56<>"n/a_tanpa_evaluasi",U56<>""),"PERIKSA: tanpa evaluasi, adaptif harus n/a. ","")&IF(AND(OR(R56="author_run",R56="author_run+independent",R56="independent_only"),Q56=""),"PERIKSA: isi kelas_dievaluasi. ","")&IF(AND(OR(R56="author_run",R56="author_run+independent",R56="independent_only"),W56=""),"PERIKSA: isi lokasi_bukti. ","")&IF(AND(H56="tidak",R56<>""),"PERIKSA: tanpa teks lengkap, kosongkan kolom evaluasi. ","")) | AC56: include
A57: jayson-2026-security-defense-mechanisms-model-context | B57: Security Defense Mechanisms in Model Context Protocol Implementations: A Systematic Literature Review | C57: 2026 | D57: E1 | E57: kandidat_agent | F57: proposal_only | G57: https://doi.org/10.1007/978-3-032-25187-9_44 | H57: ya | I57: survey_review | Z57: Teks lengkap tersedia di papers/springer. Tinjauan literatur sistematis (PRISMA) atas 73 studi pertahanan MCP (2022-2025). Mengonfirmasi hanya 23.3% studi melaporkan efektivitas kuantitatif. | AA57: =IF(I57="","",IF(OR(I57="attack",I57="survey_review",I57="benchmark_measurement",I57="position_other",I57="not_defense"),"n/a",IF(OR(X57="spec_normatif",X57="produksi_bukti_publik"),"L3",IF(ISNUMBER(SEARCH("independent",R57)),"L2",IF(R57="author_run","L1",IF(R57="none","L0","")))))) | AB57: =IF(I57="","",IF(AND(K57="deterministic_policy",M57="ya"),"PERIKSA: deterministic_policy tetapi LLM/ML ada dalam keputusan. ","")&IF(AND(U57="ya",V57=""),"PERIKSA: adaptif=ya wajib ada kutipan. ","")&IF(AND(R57="none",U57<>"n/a_tanpa_evaluasi",U57<>""),"PERIKSA: tanpa evaluasi, adaptif harus n/a. ","")&IF(AND(OR(R57="author_run",R57="author_run+independent",R57="independent_only"),Q57=""),"PERIKSA: isi kelas_dievaluasi. ","")&IF(AND(OR(R57="author_run",R57="author_run+independent",R57="independent_only"),W57=""),"PERIKSA: isi lokasi_bukti. ","")&IF(AND(H57="tidak",R57<>""),"PERIKSA: tanpa teks lengkap, kosongkan kolom evaluasi. ","")) | AC57: include
A58: junfeng-2025-we-should-identify-mitigate-third | B58: We Should Identify and Mitigate Third-Party Safety Risks in MCP-Powered Agent Systems | C58: 2025 | D58: E2 | E58: kandidat_agent | F58: proposal_only | G58: https://arxiv.org/abs/2506.13666 | H58: ya | I58: position_other | Z58: Makalah posisi (position paper) dari NUS & USTC yang menyoroti risiko keselamatan pihak ketiga pada sistem agen MCP dan mengusulkan kerangka diagnostik/benchmark SAFEMCP serta agenda riset masa depan. Bukan usulan mekanisme mitigasi baru. | AA58: =IF(I58="","",IF(OR(I58="attack",I58="survey_review",I58="benchmark_measurement",I58="position_other",I58="not_defense"),"n/a",IF(OR(X58="spec_normatif",X58="produksi_bukti_publik"),"L3",IF(ISNUMBER(SEARCH("independent",R58)),"L2",IF(R58="author_run","L1",IF(R58="none","L0","")))))) | AB58: =IF(I58="","",IF(AND(K58="deterministic_policy",M58="ya"),"PERIKSA: deterministic_policy tetapi LLM/ML ada dalam keputusan. ","")&IF(AND(U58="ya",V58=""),"PERIKSA: adaptif=ya wajib ada kutipan. ","")&IF(AND(R58="none",U58<>"n/a_tanpa_evaluasi",U58<>""),"PERIKSA: tanpa evaluasi, adaptif harus n/a. ","")&IF(AND(OR(R58="author_run",R58="author_run+independent",R58="independent_only"),Q58=""),"PERIKSA: isi kelas_dievaluasi. ","")&IF(AND(OR(R58="author_run",R58="author_run+independent",R58="independent_only"),W58=""),"PERIKSA: isi lokasi_bukti. ","")&IF(AND(H58="tidak",R58<>""),"PERIKSA: tanpa teks lengkap, kosongkan kolom evaluasi. ","")) | AC58: include
A59: kiarash-2026-trustworthy-ai-llm-scalability-risk | B59: Trustworthy AI LLM Scalability Risk Index (LSRI): A Cybersecurity Framework Assessing Agentic-AI Security & Software Model Supply Chain Safety Boosting AI-Generated Malware Defense & Explainability Mitigating Emerging Risks of Generative AI | C59: 2026 | D59: E1 | E59: kandidat_agent | F59: proposal_only | G59: https://arxiv.org/abs/2602.19021 | H59: tidak | I59: not_defense | Z59: [AUDIT_v5_EXCLUDE: EC2] Dikeluarkan dari korpus MCP-spesifik oleh audit reviewer kedua v5. (audit lanjutan; diterima koordinator) | AA59: =IF(I59="","",IF(OR(I59="attack",I59="survey_review",I59="benchmark_measurement",I59="position_other",I59="not_defense"),"n/a",IF(OR(X59="spec_normatif",X59="produksi_bukti_publik"),"L3",IF(ISNUMBER(SEARCH("independent",R59)),"L2",IF(R59="author_run","L1",IF(R59="none","L0","")))))) | AB59: =IF(I59="","",IF(AND(K59="deterministic_policy",M59="ya"),"PERIKSA: deterministic_policy tetapi LLM/ML ada dalam keputusan. ","")&IF(AND(U59="ya",V59=""),"PERIKSA: adaptif=ya wajib ada kutipan. ","")&IF(AND(R59="none",U59<>"n/a_tanpa_evaluasi",U59<>""),"PERIKSA: tanpa evaluasi, adaptif harus n/a. ","")&IF(AND(OR(R59="author_run",R59="author_run+independent",R59="independent_only"),Q59=""),"PERIKSA: isi kelas_dievaluasi. ","")&IF(AND(OR(R59="author_run",R59="author_run+independent",R59="independent_only"),W59=""),"PERIKSA: isi lokasi_bukti. ","")&IF(AND(H59="tidak",R59<>""),"PERIKSA: tanpa teks lengkap, kosongkan kolom evaluasi. ","")) | AC59: exclude | AD59: EC2 | AE59: audit lanjutan; diterima koordinator
A60: l-2025-mcp-security-notification-tool-poisoning | B60: MCP Security Notification: Tool Poisoning Attacks | C60: 2025 | D60: E4 | E60: kandidat_agent | F60: proposal_only | H60: ya | I60: attack | Z60: Notifikasi keamanan industri / security advisory dari Invariant Labs (Tier E4) yang mendemonstrasikan serangan tool poisoning, shadowing, dan rug pulls pada klien MCP (Cursor). Sesuai Pedoman, dikodekan sebagai attack. | AA60: =IF(I60="","",IF(OR(I60="attack",I60="survey_review",I60="benchmark_measurement",I60="position_other",I60="not_defense"),"n/a",IF(OR(X60="spec_normatif",X60="produksi_bukti_publik"),"L3",IF(ISNUMBER(SEARCH("independent",R60)),"L2",IF(R60="author_run","L1",IF(R60="none","L0","")))))) | AB60: =IF(I60="","",IF(AND(K60="deterministic_policy",M60="ya"),"PERIKSA: deterministic_policy tetapi LLM/ML ada dalam keputusan. ","")&IF(AND(U60="ya",V60=""),"PERIKSA: adaptif=ya wajib ada kutipan. ","")&IF(AND(R60="none",U60<>"n/a_tanpa_evaluasi",U60<>""),"PERIKSA: tanpa evaluasi, adaptif harus n/a. ","")&IF(AND(OR(R60="author_run",R60="author_run+independent",R60="independent_only"),Q60=""),"PERIKSA: isi kelas_dievaluasi. ","")&IF(AND(OR(R60="author_run",R60="author_run+independent",R60="independent_only"),W60=""),"PERIKSA: isi lokasi_bukti. ","")&IF(AND(H60="tidak",R60<>""),"PERIKSA: tanpa teks lengkap, kosongkan kolom evaluasi. ","")) | AC60: include
A61: llu-2026-trustworthy-model-context-protocol-mcp | B61: The Trustworthy Model Context Protocol (MCP) Registry: An Architectural Blueprint for Cryptographic Provenance and Runtime Integrity | C61: 2026 | D61: E1 | E61: kandidat_agent | F61: proposal_only | G61: https://doi.org/10.3390/fi18050243 | H61: ya | I61: defense_primary | J61: proto-mcp (Trustworthy MCP Registry) | K61: integrity_provenance | L61: Arsitektur registri terpercaya tiga lapis berbasis dokumen /.well-known/mcp.json, Sigstore keyless signing, log transparansi, dan validasi tanda tangan JWK runtime untuk mencegah mutasi kapabilitas dan serangan rug pull. | M61: tidak | N61: registry | O61: R7 | P61: B1;B2;D3 | Q61: B1 | R61: author_run | T61: authors_own | U61: tidak | W61: Sec. 4-5; hal. 8-12 | X61: none | Y61: overhead tanda tangan kriptografis 0.61 ms per operasi (Sec. 5) | Z61: Teks lengkap MDPI Future Internet (18(5), 243). Evaluasi author_run prototipe proto-mcp terhadap 100 simulasi serangan rug pull (B1): 100% ditolak; overhead penandatanganan kriptografis 0.61 ms. Catatan deployment: prototipe internal/eksperimental (belum dirilis secara publik). | AA61: =IF(I61="","",IF(OR(I61="attack",I61="survey_review",I61="benchmark_measurement",I61="position_other",I61="not_defense"),"n/a",IF(OR(X61="spec_normatif",X61="produksi_bukti_publik"),"L3",IF(ISNUMBER(SEARCH("independent",R61)),"L2",IF(R61="author_run","L1",IF(R61="none","L0","")))))) | AB61: =IF(I61="","",IF(AND(K61="deterministic_policy",M61="ya"),"PERIKSA: deterministic_policy tetapi LLM/ML ada dalam keputusan. ","")&IF(AND(U61="ya",V61=""),"PERIKSA: adaptif=ya wajib ada kutipan. ","")&IF(AND(R61="none",U61<>"n/a_tanpa_evaluasi",U61<>""),"PERIKSA: tanpa evaluasi, adaptif harus n/a. ","")&IF(AND(OR(R61="author_run",R61="author_run+independent",R61="independent_only"),Q61=""),"PERIKSA: isi kelas_dievaluasi. ","")&IF(AND(OR(R61="author_run",R61="author_run+independent",R61="independent_only"),W61=""),"PERIKSA: isi lokasi_bukti. ","")&IF(AND(H61="tidak",R61<>""),"PERIKSA: tanpa teks lengkap, kosongkan kolom evaluasi. ","")) | AC61: include
A62: manish-2026-model-context-protocol-security-landscape | B62: The Model Context Protocol Security Landscape: A Systematic Analysis of Inherent Vulnerabilities and Defensive Inadequacies | C62: 2026 | D62: E1 | E62: kandidat_agent | F62: proposal_only | G62: https://doi.org/10.1007/978-3-032-31998-2_13 | H62: ya | I62: survey_review | Z62: Teks lengkap tersedia di papers/springer. Survei sistematis 18 studi akademik kunci (2024-2025) dan mengusulkan MCP Inherent Risk Taxonomy (MIRT). | AA62: =IF(I62="","",IF(OR(I62="attack",I62="survey_review",I62="benchmark_measurement",I62="position_other",I62="not_defense"),"n/a",IF(OR(X62="spec_normatif",X62="produksi_bukti_publik"),"L3",IF(ISNUMBER(SEARCH("independent",R62)),"L2",IF(R62="author_run","L1",IF(R62="none","L0","")))))) | AB62: =IF(I62="","",IF(AND(K62="deterministic_policy",M62="ya"),"PERIKSA: deterministic_policy tetapi LLM/ML ada dalam keputusan. ","")&IF(AND(U62="ya",V62=""),"PERIKSA: adaptif=ya wajib ada kutipan. ","")&IF(AND(R62="none",U62<>"n/a_tanpa_evaluasi",U62<>""),"PERIKSA: tanpa evaluasi, adaptif harus n/a. ","")&IF(AND(OR(R62="author_run",R62="author_run+independent",R62="independent_only"),Q62=""),"PERIKSA: isi kelas_dievaluasi. ","")&IF(AND(OR(R62="author_run",R62="author_run+independent",R62="independent_only"),W62=""),"PERIKSA: isi lokasi_bukti. ","")&IF(AND(H62="tidak",R62<>""),"PERIKSA: tanpa teks lengkap, kosongkan kolom evaluasi. ","")) | AC62: include
A63: mehrdad-2026-mcp-dpt-defense-placement-taxonomy | B63: MCP-DPT: A Defense-Placement Taxonomy and Coverage Analysis for Model Context Protocol Security | C63: 2026 | D63: E2 | E63: kandidat_agent | F63: proposal_only | G63: https://arxiv.org/abs/2604.07551 | H63: ya | I63: survey_review | Z63: KODER 1 menandai teks lengkap. Makalah taksonomi dan tinjauan pemetaan pertahanan (Systematization of Knowledge) mengenai penempatan pertahanan keamanan MCP (MCP-DPT) yang memetakan pertahanan industri dan akademis yang ada. Sesuai Pedoman, dikodekan sebagai survey_review. | AA63: =IF(I63="","",IF(OR(I63="attack",I63="survey_review",I63="benchmark_measurement",I63="position_other",I63="not_defense"),"n/a",IF(OR(X63="spec_normatif",X63="produksi_bukti_publik"),"L3",IF(ISNUMBER(SEARCH("independent",R63)),"L2",IF(R63="author_run","L1",IF(R63="none","L0","")))))) | AB63: =IF(I63="","",IF(AND(K63="deterministic_policy",M63="ya"),"PERIKSA: deterministic_policy tetapi LLM/ML ada dalam keputusan. ","")&IF(AND(U63="ya",V63=""),"PERIKSA: adaptif=ya wajib ada kutipan. ","")&IF(AND(R63="none",U63<>"n/a_tanpa_evaluasi",U63<>""),"PERIKSA: tanpa evaluasi, adaptif harus n/a. ","")&IF(AND(OR(R63="author_run",R63="author_run+independent",R63="independent_only"),Q63=""),"PERIKSA: isi kelas_dievaluasi. ","")&IF(AND(OR(R63="author_run",R63="author_run+independent",R63="independent_only"),W63=""),"PERIKSA: isi lokasi_bukti. ","")&IF(AND(H63="tidak",R63<>""),"PERIKSA: tanpa teks lengkap, kosongkan kolom evaluasi. ","")) | AC63: include
A64: michelle-2025-missing-securing-model-context-protocol | B64: The Missing S: Securing the Model Context Protocol | C64: 2025 | D64: E1 | E64: kandidat_agent | F64: proposal_only | G64: https://doi.org/10.1109/ICoAIT67446.2025.11308830 | H64: ya | I64: defense_primary | J64: Missing S / DistilBERT Command Injection Detector | K64: content_inspection_runtime | L64: Detektor injeksi perintah runtime berbasis model Transformer (DistilBERT fine-tuned) untuk memeriksa argumen pemanggilan tool pada protokol MCP. | M64: ya | N64: gateway_proxy | O64: R2;R5 | P64: C5 | Q64: C5 | R64: author_run | T64: authors_own | U64: tidak | W64: Sec. IV, Tabel II, hal. 4-5 | X64: prototype_open_source | Y64: akurasi 99.92%, precision 99.85%, recall 100% pada 2.400 sampel uji | Z64: Teks lengkap tersedia di papers/ieee. Kode dan model tersedia publik di https://github.com/chelleajax/Securing-the-MCP. | AA64: =IF(I64="","",IF(OR(I64="attack",I64="survey_review",I64="benchmark_measurement",I64="position_other",I64="not_defense"),"n/a",IF(OR(X64="spec_normatif",X64="produksi_bukti_publik"),"L3",IF(ISNUMBER(SEARCH("independent",R64)),"L2",IF(R64="author_run","L1",IF(R64="none","L0","")))))) | AB64: =IF(I64="","",IF(AND(K64="deterministic_policy",M64="ya"),"PERIKSA: deterministic_policy tetapi LLM/ML ada dalam keputusan. ","")&IF(AND(U64="ya",V64=""),"PERIKSA: adaptif=ya wajib ada kutipan. ","")&IF(AND(R64="none",U64<>"n/a_tanpa_evaluasi",U64<>""),"PERIKSA: tanpa evaluasi, adaptif harus n/a. ","")&IF(AND(OR(R64="author_run",R64="author_run+independent",R64="independent_only"),Q64=""),"PERIKSA: isi kelas_dievaluasi. ","")&IF(AND(OR(R64="author_run",R64="author_run+independent",R64="independent_only"),W64=""),"PERIKSA: isi lokasi_bukti. ","")&IF(AND(H64="tidak",R64<>""),"PERIKSA: tanpa teks lengkap, kosongkan kolom evaluasi. ","")) | AC64: include
A65: nisharg-2025-model-context-protocol-mcp-lightweight | B65: Model Context Protocol (MCP): A Lightweight, Modular Framework for Tool-Augmented LLM Agents | C65: 2025 | D65: E1 | E65: kandidat_agent | F65: proposal_only | G65: https://doi.org/10.1109/ISED67359.2025.11405153 | H65: tidak | I65: position_other | Z65: [NON-OA / ABSTRACT-ONLY] Makalah IEEE ISED 2025 (DOI: 10.1109/ISED67359.2025.11405153). Makalah arsitektur rekayasa sistem/platform yang menyajikan gambaran umum MCP sebagai kerangka kerja modular untuk agen LLM dengan perkakas. Bukan usulan mekanisme mitigasi pertahanan serangan. | AA65: =IF(I65="","",IF(OR(I65="attack",I65="survey_review",I65="benchmark_measurement",I65="position_other",I65="not_defense"),"n/a",IF(OR(X65="spec_normatif",X65="produksi_bukti_publik"),"L3",IF(ISNUMBER(SEARCH("independent",R65)),"L2",IF(R65="author_run","L1",IF(R65="none","L0","")))))) | AB65: =IF(I65="","",IF(AND(K65="deterministic_policy",M65="ya"),"PERIKSA: deterministic_policy tetapi LLM/ML ada dalam keputusan. ","")&IF(AND(U65="ya",V65=""),"PERIKSA: adaptif=ya wajib ada kutipan. ","")&IF(AND(R65="none",U65<>"n/a_tanpa_evaluasi",U65<>""),"PERIKSA: tanpa evaluasi, adaptif harus n/a. ","")&IF(AND(OR(R65="author_run",R65="author_run+independent",R65="independent_only"),Q65=""),"PERIKSA: isi kelas_dievaluasi. ","")&IF(AND(OR(R65="author_run",R65="author_run+independent",R65="independent_only"),W65=""),"PERIKSA: isi lokasi_bukti. ","")&IF(AND(H65="tidak",R65<>""),"PERIKSA: tanpa teks lengkap, kosongkan kolom evaluasi. ","")) | AC65: include
A66: om-2025-comprehensive-security-framework-model-context | B66: A Comprehensive Security Framework for the Model Context Protocol (MCP) in Multi-Agent AI Systems | C66: 2025 | D66: E1 | E66: kandidat_agent | F66: proposal_only | G66: https://doi.org/10.1109/acai68217.2025.11406667 | H66: ya | I66: defense_primary | J66: Multi-Layer Security Framework (SecureFlow) | K66: deterministic_policy | L66: Kerangka pertahanan multi-layer untuk sistem multi-agen MCP yang memadukan OPA policy-as-code, scoped JWT, isolasi AgentNamespace, dan Saga state consistency. | M66: tidak | N66: gateway_proxy | O66: R1;R2;R3;R5;R7 | P66: A1;A2;B1;B2;C1;C2;D1 | R66: none | T66: none | U66: n/a_tanpa_evaluasi | X66: none | Y66: not_reported | Z66: Multi-layer security framework (SecureFlow). Tidak ada data empiris di Sec IV-VI, dikodekan defense_primary L0 sesuai Addendum v1.2 Bagian 3. | AA66: =IF(I66="","",IF(OR(I66="attack",I66="survey_review",I66="benchmark_measurement",I66="position_other",I66="not_defense"),"n/a",IF(OR(X66="spec_normatif",X66="produksi_bukti_publik"),"L3",IF(ISNUMBER(SEARCH("independent",R66)),"L2",IF(R66="author_run","L1",IF(R66="none","L0","")))))) | AB66: =IF(I66="","",IF(AND(K66="deterministic_policy",M66="ya"),"PERIKSA: deterministic_policy tetapi LLM/ML ada dalam keputusan. ","")&IF(AND(U66="ya",V66=""),"PERIKSA: adaptif=ya wajib ada kutipan. ","")&IF(AND(R66="none",U66<>"n/a_tanpa_evaluasi",U66<>""),"PERIKSA: tanpa evaluasi, adaptif harus n/a. ","")&IF(AND(OR(R66="author_run",R66="author_run+independent",R66="independent_only"),Q66=""),"PERIKSA: isi kelas_dievaluasi. ","")&IF(AND(OR(R66="author_run",R66="author_run+independent",R66="independent_only"),W66=""),"PERIKSA: isi lokasi_bukti. ","")&IF(AND(H66="tidak",R66<>""),"PERIKSA: tanpa teks lengkap, kosongkan kolom evaluasi. ","")) | AC66: include
A67: rodrigo-2026-design-security-framework-multi-agent | B67: Design of a Security Framework for Multi-Agent Systems Based on Model Context Protocol in SOC Environments | C67: 2026 | D67: E1 | E67: kandidat_agent | F67: proposal_only | G67: https://doi.org/10.3390/app16167915 | H67: ya | I67: defense_primary | J67: SOC MCP Security Middleware | K67: deterministic_policy | L67: Middleware keamanan lima lapis (access control, rate limiting, validasi input/output, audit log) terintegrasi Wazuh SIEM untuk alur kerja multi-agen SOC. | M67: tidak | N67: gateway_proxy | O67: R1;R2;R7 | P67: A1;A2;A3;B2;D3 | Q67: A1;A2;B2 | R67: author_run | T67: authors_own | U67: tidak | W67: Sec. 4-5; hal. 8-12 | X67: none | Y67: dilaporkan: latensi middleware minimal pada pipeline SOC Wazuh (Sec. 5) | Z67: Teks lengkap MDPI Applied Sciences (16(16), 7915). Evaluasi author_run 600 eksekusi pada pipeline SOC terhubung Wazuh SIEM: memblokir 100% serangan teridentifikasi dari 29 vektor ancaman tanpa false rejections. Catatan deployment: prototipe internal/eksperimental (belum dirilis secara publik). | AA67: =IF(I67="","",IF(OR(I67="attack",I67="survey_review",I67="benchmark_measurement",I67="position_other",I67="not_defense"),"n/a",IF(OR(X67="spec_normatif",X67="produksi_bukti_publik"),"L3",IF(ISNUMBER(SEARCH("independent",R67)),"L2",IF(R67="author_run","L1",IF(R67="none","L0","")))))) | AB67: =IF(I67="","",IF(AND(K67="deterministic_policy",M67="ya"),"PERIKSA: deterministic_policy tetapi LLM/ML ada dalam keputusan. ","")&IF(AND(U67="ya",V67=""),"PERIKSA: adaptif=ya wajib ada kutipan. ","")&IF(AND(R67="none",U67<>"n/a_tanpa_evaluasi",U67<>""),"PERIKSA: tanpa evaluasi, adaptif harus n/a. ","")&IF(AND(OR(R67="author_run",R67="author_run+independent",R67="independent_only"),Q67=""),"PERIKSA: isi kelas_dievaluasi. ","")&IF(AND(OR(R67="author_run",R67="author_run+independent",R67="independent_only"),W67=""),"PERIKSA: isi lokasi_bukti. ","")&IF(AND(H67="tidak",R67<>""),"PERIKSA: tanpa teks lengkap, kosongkan kolom evaluasi. ","")) | AC67: include
A68: rohit-2024-model-context-protocol-mcp-security | B68: Model Context Protocol (MCP) Security and Tenancy Boundaries | C68: 2024 | D68: E1 | E68: kandidat_agent | F68: proposal_only | G68: https://doi.org/10.63282/3050-9416.ijaibdcms-v5i1p118 | H68: ya | I68: defense_primary | J68: Tenant-Aware MCP Framework | K68: deterministic_policy | L68: Kerangka keamanan multi-tenant MCP yang menerapkan penandaan konteks kriptografis (tenant_id, session_id), validasi kebijakan runtime OPA, dan isolasi Nitro Enclaves untuk mencegah context bleed antar-tenant. | M68: tidak | N68: gateway_proxy | O68: R2;R3;R5;R6 | P68: A2;C2;C3;D1 | Q68: A2;C2;D1 | R68: author_run | T68: authors_own | U68: tidak | W68: Sec. 4.2; Sec. 5.1; hal. 184-186 | X68: none | Y68: latensi +2.7% (Sec. 5.1.1, hal. 185) / latensi isolasi 35 ms ke 48 ms (Sec. 4.2.2, hal. 184) | Z68: Teks lengkap diunduh dari IJAIBDCMS (OJS). Simulasi >10.000 runs, 1.000 concurrent tenants: mengeliminasi context leakage rate dari 2.6% ke 0% (Sec. 5.1.1); akurasi isolasi 99.97%; latensi overhead 2.7%. | AA68: =IF(I68="","",IF(OR(I68="attack",I68="survey_review",I68="benchmark_measurement",I68="position_other",I68="not_defense"),"n/a",IF(OR(X68="spec_normatif",X68="produksi_bukti_publik"),"L3",IF(ISNUMBER(SEARCH("independent",R68)),"L2",IF(R68="author_run","L1",IF(R68="none","L0","")))))) | AB68: =IF(I68="","",IF(AND(K68="deterministic_policy",M68="ya"),"PERIKSA: deterministic_policy tetapi LLM/ML ada dalam keputusan. ","")&IF(AND(U68="ya",V68=""),"PERIKSA: adaptif=ya wajib ada kutipan. ","")&IF(AND(R68="none",U68<>"n/a_tanpa_evaluasi",U68<>""),"PERIKSA: tanpa evaluasi, adaptif harus n/a. ","")&IF(AND(OR(R68="author_run",R68="author_run+independent",R68="independent_only"),Q68=""),"PERIKSA: isi kelas_dievaluasi. ","")&IF(AND(OR(R68="author_run",R68="author_run+independent",R68="independent_only"),W68=""),"PERIKSA: isi lokasi_bukti. ","")&IF(AND(H68="tidak",R68<>""),"PERIKSA: tanpa teks lengkap, kosongkan kolom evaluasi. ","")) | AC68: include
A69: s-2025-model-context-protocol-context-aware | B69: Model Context Protocol: A Context-Aware Framework for Enhancing Cybersecurity in Dynamic Environments | C69: 2025 | D69: E1 | E69: kandidat_agent | F69: proposal_only | G69: https://doi.org/10.55041/ijsrem49289 | H69: tidak | I69: not_defense | Z69: [AUDIT_v5_EXCLUDE: EC1] Dikeluarkan dari korpus MCP-spesifik oleh audit reviewer kedua v5. (audit lanjutan; diterima koordinator) | AA69: =IF(I69="","",IF(OR(I69="attack",I69="survey_review",I69="benchmark_measurement",I69="position_other",I69="not_defense"),"n/a",IF(OR(X69="spec_normatif",X69="produksi_bukti_publik"),"L3",IF(ISNUMBER(SEARCH("independent",R69)),"L2",IF(R69="author_run","L1",IF(R69="none","L0","")))))) | AB69: =IF(I69="","",IF(AND(K69="deterministic_policy",M69="ya"),"PERIKSA: deterministic_policy tetapi LLM/ML ada dalam keputusan. ","")&IF(AND(U69="ya",V69=""),"PERIKSA: adaptif=ya wajib ada kutipan. ","")&IF(AND(R69="none",U69<>"n/a_tanpa_evaluasi",U69<>""),"PERIKSA: tanpa evaluasi, adaptif harus n/a. ","")&IF(AND(OR(R69="author_run",R69="author_run+independent",R69="independent_only"),Q69=""),"PERIKSA: isi kelas_dievaluasi. ","")&IF(AND(OR(R69="author_run",R69="author_run+independent",R69="independent_only"),W69=""),"PERIKSA: isi lokasi_bukti. ","")&IF(AND(H69="tidak",R69<>""),"PERIKSA: tanpa teks lengkap, kosongkan kolom evaluasi. ","")) | AC69: exclude | AD69: EC1 | AE69: audit lanjutan; diterima koordinator
A70: s-2025-zero-trust-security-frameworks-model | B70: Zero-Trust Security Frameworks for Model Context Protocol (MCP) Server Communications | C70: 2025 | D70: E1 | E70: kandidat_agent | F70: proposal_only | G70: https://doi.org/10.37082/ijirmps.v13.i6.232959 | H70: ya | I70: proposal_only | J70: MCP Zero-Trust Architecture Framework | K70: deterministic_policy | L70: Kerangka kerja Zero-Trust Architecture (ZTA) untuk komunikasi server MCP yang menerapkan autentikasi mutual mTLS, mikro-segmentasi jaringan, penegakan kebijakan dinamis PDP/PEP, dan telemetri logging berkelanjutan. | M70: tidak | N70: gateway_proxy | O70: R1;R2;R4;R5;R6;R7 | P70: A1;A2;A3;B1;B2;C3;D3 | R70: none | T70: none | U70: n/a_tanpa_evaluasi | W70: Sec. 3 & 4, hal. 4-6 | X70: none | Y70: not_reported | Z70: Makalah usulan arsitektur zero-trust untuk komunikasi server MCP (PDP/PEP, mTLS, mikrosegmentasi) tanpa evaluasi empiris pertahanan terhadap dataset serangan. KODER 1 menandai teks lengkap. | AA70: =IF(I70="","",IF(OR(I70="attack",I70="survey_review",I70="benchmark_measurement",I70="position_other",I70="not_defense"),"n/a",IF(OR(X70="spec_normatif",X70="produksi_bukti_publik"),"L3",IF(ISNUMBER(SEARCH("independent",R70)),"L2",IF(R70="author_run","L1",IF(R70="none","L0","")))))) | AB70: =IF(I70="","",IF(AND(K70="deterministic_policy",M70="ya"),"PERIKSA: deterministic_policy tetapi LLM/ML ada dalam keputusan. ","")&IF(AND(U70="ya",V70=""),"PERIKSA: adaptif=ya wajib ada kutipan. ","")&IF(AND(R70="none",U70<>"n/a_tanpa_evaluasi",U70<>""),"PERIKSA: tanpa evaluasi, adaptif harus n/a. ","")&IF(AND(OR(R70="author_run",R70="author_run+independent",R70="independent_only"),Q70=""),"PERIKSA: isi kelas_dievaluasi. ","")&IF(AND(OR(R70="author_run",R70="author_run+independent",R70="independent_only"),W70=""),"PERIKSA: isi lokasi_bukti. ","")&IF(AND(H70="tidak",R70<>""),"PERIKSA: tanpa teks lengkap, kosongkan kolom evaluasi. ","")) | AC70: include
A71: sanjeeva-2026-security-threats-model-context-protocol | B71: Security Threats in the Model Context Protocol: A Comprehensive Survey and Trust Boundary Mitigation Framework for Agentic AI Systems | C71: 2026 | D71: E1 | E71: kandidat_agent | F71: proposal_only | G71: https://doi.org/10.21275/sr26316110418 | H71: tidak | I71: survey_review | Z71: [NON-OA / ABSTRACT-ONLY] Makalah survei komprehensif ancaman keamanan MCP (IJSR, DOI: 10.21275/sr26316110418) yang mensintesis 7 CVE, 11 insiden keamanan, dan taksonomi 10 kelas ancaman serta meninjau 41 makalah pertahanan. Sesuai Pedoman, dikodekan sebagai survey_review. | AA71: =IF(I71="","",IF(OR(I71="attack",I71="survey_review",I71="benchmark_measurement",I71="position_other",I71="not_defense"),"n/a",IF(OR(X71="spec_normatif",X71="produksi_bukti_publik"),"L3",IF(ISNUMBER(SEARCH("independent",R71)),"L2",IF(R71="author_run","L1",IF(R71="none","L0","")))))) | AB71: =IF(I71="","",IF(AND(K71="deterministic_policy",M71="ya"),"PERIKSA: deterministic_policy tetapi LLM/ML ada dalam keputusan. ","")&IF(AND(U71="ya",V71=""),"PERIKSA: adaptif=ya wajib ada kutipan. ","")&IF(AND(R71="none",U71<>"n/a_tanpa_evaluasi",U71<>""),"PERIKSA: tanpa evaluasi, adaptif harus n/a. ","")&IF(AND(OR(R71="author_run",R71="author_run+independent",R71="independent_only"),Q71=""),"PERIKSA: isi kelas_dievaluasi. ","")&IF(AND(OR(R71="author_run",R71="author_run+independent",R71="independent_only"),W71=""),"PERIKSA: isi lokasi_bukti. ","")&IF(AND(H71="tidak",R71<>""),"PERIKSA: tanpa teks lengkap, kosongkan kolom evaluasi. ","")) | AC71: include
A72: sunil-2026-zero-trust-supply-chain-security | B72: A Zero-Trust Supply Chain Security Framework for Model Context Protocol-based AI Systems | C72: 2026 | D72: E1 | E72: kandidat_agent | F72: proposal_only | G72: https://doi.org/10.1109/iccbi68589.2026.11619741 | H72: ya | I72: defense_primary | J72: ContextGuard | K72: integrity_provenance | L72: Kerangka kerja zero-trust rantai pasok MCP yang menggabungkan verifikasi kriptografis (CVL), deteksi drift semantik definisi tool (DIMS), dan penegakan kebijakan (PEP). | M72: tidak | N72: gateway_proxy | O72: R1;R2;R7 | P72: A1;D1;D3 | Q72: A1;D1;D3 | R72: author_run | T72: authors_own | U72: tidak | W72: Sec. VI-VII, Tabel 2 & 3, hal. 4-5 | X72: prototype_open_source | Y72: latensi otorisasi bertambah +1.58 ms (3.42 ms vs baseline 1.84 ms, Tabel 3) | Z72: Teks lengkap tersedia di papers/ieee. Evaluasi pada korpus 40 tool (30 berbahaya, 10 jinak) dengan deteksi 96.7%. Kode publik di https://github.com/sunilgentyala/contextguard. | AA72: =IF(I72="","",IF(OR(I72="attack",I72="survey_review",I72="benchmark_measurement",I72="position_other",I72="not_defense"),"n/a",IF(OR(X72="spec_normatif",X72="produksi_bukti_publik"),"L3",IF(ISNUMBER(SEARCH("independent",R72)),"L2",IF(R72="author_run","L1",IF(R72="none","L0","")))))) | AB72: =IF(I72="","",IF(AND(K72="deterministic_policy",M72="ya"),"PERIKSA: deterministic_policy tetapi LLM/ML ada dalam keputusan. ","")&IF(AND(U72="ya",V72=""),"PERIKSA: adaptif=ya wajib ada kutipan. ","")&IF(AND(R72="none",U72<>"n/a_tanpa_evaluasi",U72<>""),"PERIKSA: tanpa evaluasi, adaptif harus n/a. ","")&IF(AND(OR(R72="author_run",R72="author_run+independent",R72="independent_only"),Q72=""),"PERIKSA: isi kelas_dievaluasi. ","")&IF(AND(OR(R72="author_run",R72="author_run+independent",R72="independent_only"),W72=""),"PERIKSA: isi lokasi_bukti. ","")&IF(AND(H72="tidak",R72<>""),"PERIKSA: tanpa teks lengkap, kosongkan kolom evaluasi. ","")) | AC72: include
A73: theophilus-2026-systematic-security-analysis-model-context | B73: A Systematic Security Analysis of Model Context Protocol: Vulnerabilities, Exploits, and Mitigations | C73: 2026 | D73: E1 | E73: kandidat_agent | F73: proposal_only | G73: https://doi.org/10.1109/ICAIC67076.2026.11395848 | H73: ya | I73: defense_secondary | J73: Hardened MCP Defenses (Prompt Shielding, RBAC, Rate Limiting) | K73: deterministic_policy | L73: Pengerasan server MCP berlapis menggunakan Prompt Shielding (filter konteks), RBAC least-privilege, dan Rate Limiting sumber daya. | M73: tidak | N73: S | O73: R2;R3;R5 | P73: A2;C1;C5;D1;OUT_OF_TAXONOMY:resource_abuse | Q73: A2;C1;C5;D1;OUT_OF_TAXONOMY:resource_abuse | R73: author_run | T73: authors_own | U73: tidak | W73: Sec. X-A, Tabel IV, hal. 6-7 | X73: none | Y73: dilaporkan: reduksi ASR serangan (RBAC -51.3%, Prompt Shield -47.5%, Rate Limit -37.2%, Tabel IV) | Z73: Hardened MCP Defenses (defense_secondary, L1). Tabel IV: Prompt Shielding (A2/C5/D1), RBAC (C1), dan Rate Limiting (OUT_OF_TAXONOMY:resource_abuse). Penurunan ASR signifikan pada 15 server MCP. | AA73: =IF(I73="","",IF(OR(I73="attack",I73="survey_review",I73="benchmark_measurement",I73="position_other",I73="not_defense"),"n/a",IF(OR(X73="spec_normatif",X73="produksi_bukti_publik"),"L3",IF(ISNUMBER(SEARCH("independent",R73)),"L2",IF(R73="author_run","L1",IF(R73="none","L0","")))))) | AB73: =IF(I73="","",IF(AND(K73="deterministic_policy",M73="ya"),"PERIKSA: deterministic_policy tetapi LLM/ML ada dalam keputusan. ","")&IF(AND(U73="ya",V73=""),"PERIKSA: adaptif=ya wajib ada kutipan. ","")&IF(AND(R73="none",U73<>"n/a_tanpa_evaluasi",U73<>""),"PERIKSA: tanpa evaluasi, adaptif harus n/a. ","")&IF(AND(OR(R73="author_run",R73="author_run+independent",R73="independent_only"),Q73=""),"PERIKSA: isi kelas_dievaluasi. ","")&IF(AND(OR(R73="author_run",R73="author_run+independent",R73="independent_only"),W73=""),"PERIKSA: isi lokasi_bukti. ","")&IF(AND(H73="tidak",R73<>""),"PERIKSA: tanpa teks lengkap, kosongkan kolom evaluasi. ","")) | AC73: include
A74: vineeth-2026-enterprise-grade-security-model-context | B74: Enterprise-Grade Security for the Model Context Protocol (MCP): Frameworks and Mitigation Strategies | C74: 2026 | D74: E1 | E74: kandidat_agent | F74: proposal_only | G74: https://arxiv.org/abs/2504.08623 | H74: ya | I74: proposal_only | J74: Enterprise-Grade MCP Security Framework | K74: deterministic_policy | L74: Kerangka kerja pertahanan berlapis (defense-in-depth) enterprise untuk MCP yang menerapkan kontrol zero trust, pemodelan ancaman MAESTRO, autentikasi granular, dan audit telemetri. | M74: tidak | N74: gateway_proxy | O74: R1;R2;R4;R5;R6;R7 | P74: A1;A2;A3;B1;B2;C3;D3 | R74: none | T74: none | U74: n/a_tanpa_evaluasi | W74: Sec. III & IV, hal. 4-9 | X74: none | Y74: not_reported | Z74: KODER 1 menandai teks lengkap. Makalah usulan kerangka kerja pertahanan enterprise berlapis berbasis Zero Trust dan MAESTRO tanpa evaluasi empiris terhadap dataset serangan. Sesuai Pedoman, dikodekan sebagai proposal_only. | AA74: =IF(I74="","",IF(OR(I74="attack",I74="survey_review",I74="benchmark_measurement",I74="position_other",I74="not_defense"),"n/a",IF(OR(X74="spec_normatif",X74="produksi_bukti_publik"),"L3",IF(ISNUMBER(SEARCH("independent",R74)),"L2",IF(R74="author_run","L1",IF(R74="none","L0","")))))) | AB74: =IF(I74="","",IF(AND(K74="deterministic_policy",M74="ya"),"PERIKSA: deterministic_policy tetapi LLM/ML ada dalam keputusan. ","")&IF(AND(U74="ya",V74=""),"PERIKSA: adaptif=ya wajib ada kutipan. ","")&IF(AND(R74="none",U74<>"n/a_tanpa_evaluasi",U74<>""),"PERIKSA: tanpa evaluasi, adaptif harus n/a. ","")&IF(AND(OR(R74="author_run",R74="author_run+independent",R74="independent_only"),Q74=""),"PERIKSA: isi kelas_dievaluasi. ","")&IF(AND(OR(R74="author_run",R74="author_run+independent",R74="independent_only"),W74=""),"PERIKSA: isi lokasi_bukti. ","")&IF(AND(H74="tidak",R74<>""),"PERIKSA: tanpa teks lengkap, kosongkan kolom evaluasi. ","")) | AC74: include
A75: weibo-2025-when-mcp-servers-attack-taxonomy | B75: When MCP Servers Attack: Taxonomy, Feasibility, and Mitigation | C75: 2025 | D75: E2 | E75: kandidat_agent | F75: proposal_only | G75: https://arxiv.org/abs/2509.24272 | H75: ya | I75: attack | Z75: KODER 1 menandai teks lengkap. Studi sistematis dan taksonomi serangan server MCP berbahaya (12 kategori serangan, PoC servers) yang mengevaluasi kerentanan host dan kegagalan scanner yang ada. Sesuai Pedoman, dikodekan sebagai attack. | AA75: =IF(I75="","",IF(OR(I75="attack",I75="survey_review",I75="benchmark_measurement",I75="position_other",I75="not_defense"),"n/a",IF(OR(X75="spec_normatif",X75="produksi_bukti_publik"),"L3",IF(ISNUMBER(SEARCH("independent",R75)),"L2",IF(R75="author_run","L1",IF(R75="none","L0","")))))) | AB75: =IF(I75="","",IF(AND(K75="deterministic_policy",M75="ya"),"PERIKSA: deterministic_policy tetapi LLM/ML ada dalam keputusan. ","")&IF(AND(U75="ya",V75=""),"PERIKSA: adaptif=ya wajib ada kutipan. ","")&IF(AND(R75="none",U75<>"n/a_tanpa_evaluasi",U75<>""),"PERIKSA: tanpa evaluasi, adaptif harus n/a. ","")&IF(AND(OR(R75="author_run",R75="author_run+independent",R75="independent_only"),Q75=""),"PERIKSA: isi kelas_dievaluasi. ","")&IF(AND(OR(R75="author_run",R75="author_run+independent",R75="independent_only"),W75=""),"PERIKSA: isi lokasi_bukti. ","")&IF(AND(H75="tidak",R75<>""),"PERIKSA: tanpa teks lengkap, kosongkan kolom evaluasi. ","")) | AC75: include
A76: xinyi-2026-model-context-protocol-mcp-landscape | B76: Model Context Protocol (MCP): Landscape, Security Threats, and Future Research Directions | C76: 2026 | D76: E1 | E76: kandidat_agent | F76: proposal_only | G76: https://arxiv.org/abs/2503.23278 | H76: ya | I76: survey_review | Z76: KODER 1 menandai teks lengkap. Makalah survei komprehensif mengenai lanskap ekosistem MCP, arsitektur protokol, ancaman keamanan, dan arah riset masa depan. Sesuai Pedoman, dikodekan sebagai survey_review. | AA76: =IF(I76="","",IF(OR(I76="attack",I76="survey_review",I76="benchmark_measurement",I76="position_other",I76="not_defense"),"n/a",IF(OR(X76="spec_normatif",X76="produksi_bukti_publik"),"L3",IF(ISNUMBER(SEARCH("independent",R76)),"L2",IF(R76="author_run","L1",IF(R76="none","L0","")))))) | AB76: =IF(I76="","",IF(AND(K76="deterministic_policy",M76="ya"),"PERIKSA: deterministic_policy tetapi LLM/ML ada dalam keputusan. ","")&IF(AND(U76="ya",V76=""),"PERIKSA: adaptif=ya wajib ada kutipan. ","")&IF(AND(R76="none",U76<>"n/a_tanpa_evaluasi",U76<>""),"PERIKSA: tanpa evaluasi, adaptif harus n/a. ","")&IF(AND(OR(R76="author_run",R76="author_run+independent",R76="independent_only"),Q76=""),"PERIKSA: isi kelas_dievaluasi. ","")&IF(AND(OR(R76="author_run",R76="author_run+independent",R76="independent_only"),W76=""),"PERIKSA: isi lokasi_bukti. ","")&IF(AND(H76="tidak",R76<>""),"PERIKSA: tanpa teks lengkap, kosongkan kolom evaluasi. ","")) | AC76: include
A77: john-2026-mcp-safety-audit-llms-model | B77: MCP safety audit: LLMs with the model context protocol allow major security exploits | C77: 2026 | D77: E2 | E77: kandidat_agent | F77: secondary | G77: https://arxiv.org/abs/2504.03767 | H77: ya | I77: defense_secondary | J77: McpSafetyScanner | K77: content_inspection_static | L77: Pemindai kerentanan multi-agen otomatis (McpSafetyScanner) bertenaga LLM yang memindai konfigurasi perkakas MCP, mendeteksi potensi eksploitasi (MCE, RAC, pencurian kredensial), dan menghasilkan saran remediasi keamanan. | M77: ya | N77: offline_analysis | O77: R2;R6;R7 | P77: A1;A2;C5;D1;D3 | Q77: A2;C5;D1 | R77: author_run+independent | S77: pengyu-2026-viper-mcp-detecting-exploiting-taint; zhiyuan-2026-confused-deputy-attack-model-context | T77: authors_own | U77: tidak | W77: Sec. 5 & 7, Tabel 2 & 3, Gbr 20 & 21, hal. 6-9, 25-27 | X77: prototype_open_source | Y77: Runtime kurang dari satu menit per pemindaian pada Apple M2 Max MacBook Pro | Z77: McpSafetyScanner (defense_secondary, L2). Audit otomatis konfigurasi MCP untuk MCE/RAC (C5), prompt/tool manipulation (A2), credential theft (D1). Dua evaluator independen: VIPER-MCP (Tabel 2, hal. 11) dan Zhiyuan-2026 (Tabel 8, hal. 21). Repositori resmi: github.com/johnhalloran321/mcpSafetyScanner. Repositori/artefak: https://github.com/johnhalloran321/mcpSafetyScanner. | AA77: =IF(I77="","",IF(OR(I77="attack",I77="survey_review",I77="benchmark_measurement",I77="position_other",I77="not_defense"),"n/a",IF(OR(X77="spec_normatif",X77="produksi_bukti_publik"),"L3",IF(ISNUMBER(SEARCH("independent",R77)),"L2",IF(R77="author_run","L1",IF(R77="none","L0","")))))) | AB77: =IF(I77="","",IF(AND(K77="deterministic_policy",M77="ya"),"PERIKSA: deterministic_policy tetapi LLM/ML ada dalam keputusan. ","")&IF(AND(U77="ya",V77=""),"PERIKSA: adaptif=ya wajib ada kutipan. ","")&IF(AND(R77="none",U77<>"n/a_tanpa_evaluasi",U77<>""),"PERIKSA: tanpa evaluasi, adaptif harus n/a. ","")&IF(AND(OR(R77="author_run",R77="author_run+independent",R77="independent_only"),Q77=""),"PERIKSA: isi kelas_dievaluasi. ","")&IF(AND(OR(R77="author_run",R77="author_run+independent",R77="independent_only"),W77=""),"PERIKSA: isi lokasi_bukti. ","")&IF(AND(H77="tidak",R77<>""),"PERIKSA: tanpa teks lengkap, kosongkan kolom evaluasi. ","")) | AC77: include
A78: panduranga-2026-delegation-trust-empirical-gap-analysis | B78: Delegation Without Trust: An Empirical Gap Analysis of Identity, Authorization, and Runtime Governance in Multi-Agent LLM Systems | C78: 2026 | D78: E2 | E78: kandidat_agent | F78: secondary | G78: https://arxiv.org/abs/2609.00267 | H78: ya | I78: defense_secondary | J78: Trust Broker (Delegation Governance Broker) | K78: capability_or_token | L78: Broker tata kelola delegasi berbasis kapabilitas yang menerapkan sender-constrained tokens, workload identity (SPIFFE/mTLS), dan pembatasan radius dampak untuk mencegah eskalasi wewenang dan pembajakan delegasi agen. | M78: tidak | N78: gateway_proxy | O78: R1;R2;R3;R5 | P78: A1;A3;B2;C1;C3 | Q78: C1;C3 | R78: author_run | T78: authors_own | U78: ya | V78: Beyond the four scenarios, we run a suite that actively attacks the broker's own design: forging a token from scratch. | W78: Sec. 7; Table 4; hal. 7-8 | X78: none | Y78: Broker latency minimal tanpa pemanggilan LLM; membatasi blast radius dari 8.100 aksi menjadi rata-rata 1.5 aksi | Z78: Trust Broker menggunakan token kapabilitas Macaroon/Biscuit-style dengan caveat teratenuasi dan SVID mTLS. Tanpa repo publik (deployment=none). Adaptif=ya (11 serangan terarah desain oleh penulis). | AA78: =IF(I78="","",IF(OR(I78="attack",I78="survey_review",I78="benchmark_measurement",I78="position_other",I78="not_defense"),"n/a",IF(OR(X78="spec_normatif",X78="produksi_bukti_publik"),"L3",IF(ISNUMBER(SEARCH("independent",R78)),"L2",IF(R78="author_run","L1",IF(R78="none","L0","")))))) | AB78: =IF(I78="","",IF(AND(K78="deterministic_policy",M78="ya"),"PERIKSA: deterministic_policy tetapi LLM/ML ada dalam keputusan. ","")&IF(AND(U78="ya",V78=""),"PERIKSA: adaptif=ya wajib ada kutipan. ","")&IF(AND(R78="none",U78<>"n/a_tanpa_evaluasi",U78<>""),"PERIKSA: tanpa evaluasi, adaptif harus n/a. ","")&IF(AND(OR(R78="author_run",R78="author_run+independent",R78="independent_only"),Q78=""),"PERIKSA: isi kelas_dievaluasi. ","")&IF(AND(OR(R78="author_run",R78="author_run+independent",R78="independent_only"),W78=""),"PERIKSA: isi lokasi_bukti. ","")&IF(AND(H78="tidak",R78<>""),"PERIKSA: tanpa teks lengkap, kosongkan kolom evaluasi. ","")) | AC78: include
A79: shi-2026-when-manual-lies-realistic-benchmark | B79: When the Manual Lies: A Realistic Benchmark to Evaluate MCP Poisoning Attacks for LLM Agents | C79: 2026 | D79: E1 | E79: kandidat_agent | F79: secondary | G79: https://arxiv.org/abs/2605.24069 | H79: ya | I79: benchmark_measurement | Z79: KODER 1 menandai teks lengkap. Makalah benchmark empiris (MCP-TDP Security Benchmark) yang mengevaluasi kerentanan serangan peracunan deskripsi alat pada agen MCP dan menguji kelemahan baseline guardrail yang ada (LlamaGuard) tanpa mengusulkan mitigasi baru penulis. Sesuai Pedoman, dikodekan sebagai benchmark_measurement. | AA79: =IF(I79="","",IF(OR(I79="attack",I79="survey_review",I79="benchmark_measurement",I79="position_other",I79="not_defense"),"n/a",IF(OR(X79="spec_normatif",X79="produksi_bukti_publik"),"L3",IF(ISNUMBER(SEARCH("independent",R79)),"L2",IF(R79="author_run","L1",IF(R79="none","L0","")))))) | AB79: =IF(I79="","",IF(AND(K79="deterministic_policy",M79="ya"),"PERIKSA: deterministic_policy tetapi LLM/ML ada dalam keputusan. ","")&IF(AND(U79="ya",V79=""),"PERIKSA: adaptif=ya wajib ada kutipan. ","")&IF(AND(R79="none",U79<>"n/a_tanpa_evaluasi",U79<>""),"PERIKSA: tanpa evaluasi, adaptif harus n/a. ","")&IF(AND(OR(R79="author_run",R79="author_run+independent",R79="independent_only"),Q79=""),"PERIKSA: isi kelas_dievaluasi. ","")&IF(AND(OR(R79="author_run",R79="author_run+independent",R79="independent_only"),W79=""),"PERIKSA: isi lokasi_bukti. ","")&IF(AND(H79="tidak",R79<>""),"PERIKSA: tanpa teks lengkap, kosongkan kolom evaluasi. ","")) | AC79: include
A80: tarek-2025-bridging-ai-software-security-comparative | B80: Bridging AI and Software Security: A Comparative Vulnerability Assessment of LLM Agent Deployment Paradigms | C80: 2025 | D80: E2 | E80: kandidat_agent | F80: secondary | G80: https://arxiv.org/abs/2507.06323 | H80: ya | I80: benchmark_measurement | Z80: KODER 1 menandai teks lengkap. Studi penilaian kerentanan komparatif empiris (3.250 skenario serangan) yang membandingkan paradigma Function Calling vs MCP pada 7 model bahasa tanpa mengusulkan mitigasi baru penulis. Sesuai Pedoman, dikodekan sebagai benchmark_measurement. | AA80: =IF(I80="","",IF(OR(I80="attack",I80="survey_review",I80="benchmark_measurement",I80="position_other",I80="not_defense"),"n/a",IF(OR(X80="spec_normatif",X80="produksi_bukti_publik"),"L3",IF(ISNUMBER(SEARCH("independent",R80)),"L2",IF(R80="author_run","L1",IF(R80="none","L0","")))))) | AB80: =IF(I80="","",IF(AND(K80="deterministic_policy",M80="ya"),"PERIKSA: deterministic_policy tetapi LLM/ML ada dalam keputusan. ","")&IF(AND(U80="ya",V80=""),"PERIKSA: adaptif=ya wajib ada kutipan. ","")&IF(AND(R80="none",U80<>"n/a_tanpa_evaluasi",U80<>""),"PERIKSA: tanpa evaluasi, adaptif harus n/a. ","")&IF(AND(OR(R80="author_run",R80="author_run+independent",R80="independent_only"),Q80=""),"PERIKSA: isi kelas_dievaluasi. ","")&IF(AND(OR(R80="author_run",R80="author_run+independent",R80="independent_only"),W80=""),"PERIKSA: isi lokasi_bukti. ","")&IF(AND(H80="tidak",R80<>""),"PERIKSA: tanpa teks lengkap, kosongkan kolom evaluasi. ","")) | AC80: include
A81: yuanhe-2025-leechhijack-covert-computational-resource-exploitation | B81: LeechHijack: Covert Computational Resource Exploitation in Intelligent Agent Systems | C81: 2025 | D81: E2 | E81: kandidat_agent | F81: secondary | G81: https://arxiv.org/abs/2512.02321 | H81: ya | I81: defense_secondary | J81: LLM-as-a-Judge Defense for LeechHijack | K81: content_inspection_runtime | L81: Detektor berbasis LLM-as-a-judge yang menganalisis prompt dan respons tool untuk mendeteksi pembajakan komputasi terselubung pada agen MCP. | M81: ya | N81: gateway_proxy | O81: R2 | P81: OUT_OF_TAXONOMY:resource_abuse | Q81: OUT_OF_TAXONOMY:resource_abuse | R81: author_run | T81: authors_own | U81: tidak | W81: Sec. 5.6 & 6, Tabel 12-15 | X81: none | Y81: not_reported | Z81: Makalah serangan LeechHijack yang mengimplementasikan dan mengevaluasi mekanisme mitigasi LLM-as-a-judge (F1 hingga 0,96, rata-rata 0,71 di Tabel 12-15). Dikodekan sebagai defense_secondary sesuai Pedoman Bagian 3. | AA81: =IF(I81="","",IF(OR(I81="attack",I81="survey_review",I81="benchmark_measurement",I81="position_other",I81="not_defense"),"n/a",IF(OR(X81="spec_normatif",X81="produksi_bukti_publik"),"L3",IF(ISNUMBER(SEARCH("independent",R81)),"L2",IF(R81="author_run","L1",IF(R81="none","L0","")))))) | AB81: =IF(I81="","",IF(AND(K81="deterministic_policy",M81="ya"),"PERIKSA: deterministic_policy tetapi LLM/ML ada dalam keputusan. ","")&IF(AND(U81="ya",V81=""),"PERIKSA: adaptif=ya wajib ada kutipan. ","")&IF(AND(R81="none",U81<>"n/a_tanpa_evaluasi",U81<>""),"PERIKSA: tanpa evaluasi, adaptif harus n/a. ","")&IF(AND(OR(R81="author_run",R81="author_run+independent",R81="independent_only"),Q81=""),"PERIKSA: isi kelas_dievaluasi. ","")&IF(AND(OR(R81="author_run",R81="author_run+independent",R81="independent_only"),W81=""),"PERIKSA: isi lokasi_bukti. ","")&IF(AND(H81="tidak",R81<>""),"PERIKSA: tanpa teks lengkap, kosongkan kolom evaluasi. ","")) | AC81: include
A82: arash-2025-mcp-bridge-lightweight-llm-agnostic | B82: MCP Bridge: A Lightweight, LLM-Agnostic RESTful Proxy for Model Context Protocol Servers | C82: 2025 | D82: E2 | E82: kandidat_cek_recall | F82: none | G82: https://arxiv.org/abs/2504.08999 | H82: ya | I82: position_other | Z82: Agent Recall: BUKAN_PERTAHANAN - Makalah rekayasa sistem/platform proxy RESTful untuk eksekusi server MCP di lingkungan resource-constrained; evaluasi berfokus pada latensi, throughput, dan fine-tuning Qwen3 pada MCPToolBench++, tanpa evaluasi mitigasi serangan keamanan. | AA82: =IF(I82="","",IF(OR(I82="attack",I82="survey_review",I82="benchmark_measurement",I82="position_other",I82="not_defense"),"n/a",IF(OR(X82="spec_normatif",X82="produksi_bukti_publik"),"L3",IF(ISNUMBER(SEARCH("independent",R82)),"L2",IF(R82="author_run","L1",IF(R82="none","L0","")))))) | AB82: =IF(I82="","",IF(AND(K82="deterministic_policy",M82="ya"),"PERIKSA: deterministic_policy tetapi LLM/ML ada dalam keputusan. ","")&IF(AND(U82="ya",V82=""),"PERIKSA: adaptif=ya wajib ada kutipan. ","")&IF(AND(R82="none",U82<>"n/a_tanpa_evaluasi",U82<>""),"PERIKSA: tanpa evaluasi, adaptif harus n/a. ","")&IF(AND(OR(R82="author_run",R82="author_run+independent",R82="independent_only"),Q82=""),"PERIKSA: isi kelas_dievaluasi. ","")&IF(AND(OR(R82="author_run",R82="author_run+independent",R82="independent_only"),W82=""),"PERIKSA: isi lokasi_bukti. ","")&IF(AND(H82="tidak",R82<>""),"PERIKSA: tanpa teks lengkap, kosongkan kolom evaluasi. ","")) | AC82: include
A83: biwei-2025-mcp-not-stand-misuse-cryptography | B83: "MCP Does Not Stand for Misuse Cryptography Protocol": Uncovering Cryptographic Misuse in Model Context Protocol at Scale | C83: 2025 | D83: E2 | E83: kandidat_cek_recall | F83: none | G83: https://arxiv.org/abs/2512.03775 | H83: ya | I83: defense_primary | J83: MICRYSCOPE | K83: content_inspection_static | L83: Kerangka analisis statis berbasis taint analysis dan intermediate representation untuk mendeteksi penyalahgunaan kriptografi (hardcoded keys, algoritma lemah, insecure transport) pada server MCP. | M83: tidak | N83: offline_analysis | O83: R4;R5 | P83: C3;C5 | Q83: C3;C5 | R83: author_run | T83: third_party_public | U83: tidak | W83: Sec. 5, Fig. 8, Tabel 2-4 | X83: none | Y83: not_reported | Z83: Kerangka pemindaian statis MICRYSCOPE untuk audit kriptografi pada implementasi server MCP ekosistem terbuka. Catatan deployment: prototipe internal/eksperimental (belum dirilis secara publik). | AA83: =IF(I83="","",IF(OR(I83="attack",I83="survey_review",I83="benchmark_measurement",I83="position_other",I83="not_defense"),"n/a",IF(OR(X83="spec_normatif",X83="produksi_bukti_publik"),"L3",IF(ISNUMBER(SEARCH("independent",R83)),"L2",IF(R83="author_run","L1",IF(R83="none","L0","")))))) | AB83: =IF(I83="","",IF(AND(K83="deterministic_policy",M83="ya"),"PERIKSA: deterministic_policy tetapi LLM/ML ada dalam keputusan. ","")&IF(AND(U83="ya",V83=""),"PERIKSA: adaptif=ya wajib ada kutipan. ","")&IF(AND(R83="none",U83<>"n/a_tanpa_evaluasi",U83<>""),"PERIKSA: tanpa evaluasi, adaptif harus n/a. ","")&IF(AND(OR(R83="author_run",R83="author_run+independent",R83="independent_only"),Q83=""),"PERIKSA: isi kelas_dievaluasi. ","")&IF(AND(OR(R83="author_run",R83="author_run+independent",R83="independent_only"),W83=""),"PERIKSA: isi lokasi_bukti. ","")&IF(AND(H83="tidak",R83<>""),"PERIKSA: tanpa teks lengkap, kosongkan kolom evaluasi. ","")) | AC83: include
A84: charoes-2026-model-context-protocol-threat-modeling | B84: Model Context Protocol Threat Modeling and Analyzing Vulnerabilities to Prompt Injection with Tool Poisoning | C84: 2026 | D84: E1 | E84: kandidat_cek_recall | F84: none | G84: https://arxiv.org/abs/2603.22489 | H84: ya | I84: survey_review | Z84: Pemodelan ancaman komprehensif STRIDE/DREAD (57 ancaman) untuk klien MCP dan evaluasi empiris kerentanan tool poisoning pada 7 klien MCP. Dikodekan sebagai survey_review (threat model) sesuai Pedoman Bagian 3. | AA84: =IF(I84="","",IF(OR(I84="attack",I84="survey_review",I84="benchmark_measurement",I84="position_other",I84="not_defense"),"n/a",IF(OR(X84="spec_normatif",X84="produksi_bukti_publik"),"L3",IF(ISNUMBER(SEARCH("independent",R84)),"L2",IF(R84="author_run","L1",IF(R84="none","L0","")))))) | AB84: =IF(I84="","",IF(AND(K84="deterministic_policy",M84="ya"),"PERIKSA: deterministic_policy tetapi LLM/ML ada dalam keputusan. ","")&IF(AND(U84="ya",V84=""),"PERIKSA: adaptif=ya wajib ada kutipan. ","")&IF(AND(R84="none",U84<>"n/a_tanpa_evaluasi",U84<>""),"PERIKSA: tanpa evaluasi, adaptif harus n/a. ","")&IF(AND(OR(R84="author_run",R84="author_run+independent",R84="independent_only"),Q84=""),"PERIKSA: isi kelas_dievaluasi. ","")&IF(AND(OR(R84="author_run",R84="author_run+independent",R84="independent_only"),W84=""),"PERIKSA: isi lokasi_bukti. ","")&IF(AND(H84="tidak",R84<>""),"PERIKSA: tanpa teks lengkap, kosongkan kolom evaluasi. ","")) | AC84: include
A85: haoran-2025-quantifying-conversation-drift-mcp-via | B85: Quantifying Conversation Drift in MCP via Latent Polytope | C85: 2025 | D85: E2 | E85: kandidat_cek_recall | F85: none | G85: https://arxiv.org/abs/2508.06418 | H85: ya | I85: defense_primary | J85: SECMCP | K85: content_inspection_runtime | L85: Mendeteksi pergeseran percakapan (conversation drift) pada interaksi MCP dengan mengukur lintasan ruang laten menggunakan analisis politop laten untuk memitigasi manipulasi resource adversarial. | M85: tidak | N85: gateway_proxy | O85: R2;R6 | P85: A2;D2 | Q85: A2;D2 | R85: author_run | T85: mixed | U85: tidak | W85: Sec. 4-5, Table 1-3, Fig. 3 | X85: none | Y85: dilaporkan: dampak utilitas jinak dapat diabaikan (Tabel 3) | Z85: SECMCP mendeteksi conversation drift pada interaksi MCP lewat pemodelan politop laten terhadap injeksi resource berbahaya. Catatan deployment: prototipe internal/eksperimental (belum dirilis secara publik). | AA85: =IF(I85="","",IF(OR(I85="attack",I85="survey_review",I85="benchmark_measurement",I85="position_other",I85="not_defense"),"n/a",IF(OR(X85="spec_normatif",X85="produksi_bukti_publik"),"L3",IF(ISNUMBER(SEARCH("independent",R85)),"L2",IF(R85="author_run","L1",IF(R85="none","L0","")))))) | AB85: =IF(I85="","",IF(AND(K85="deterministic_policy",M85="ya"),"PERIKSA: deterministic_policy tetapi LLM/ML ada dalam keputusan. ","")&IF(AND(U85="ya",V85=""),"PERIKSA: adaptif=ya wajib ada kutipan. ","")&IF(AND(R85="none",U85<>"n/a_tanpa_evaluasi",U85<>""),"PERIKSA: tanpa evaluasi, adaptif harus n/a. ","")&IF(AND(OR(R85="author_run",R85="author_run+independent",R85="independent_only"),Q85=""),"PERIKSA: isi kelas_dievaluasi. ","")&IF(AND(OR(R85="author_run",R85="author_run+independent",R85="independent_only"),W85=""),"PERIKSA: isi lokasi_bukti. ","")&IF(AND(H85="tidak",R85<>""),"PERIKSA: tanpa teks lengkap, kosongkan kolom evaluasi. ","")) | AC85: include
A86: huijun-2026-first-measurement-study-authentication-security | B86: A First Measurement Study on Authentication Security in Real-World Remote MCP Servers | C86: 2026 | D86: E2 | E86: kandidat_cek_recall | F86: none | G86: https://arxiv.org/abs/2605.22333 | H86: ya | I86: benchmark_measurement | Z86: Agent Recall: BUKAN_PERTAHANAN - Studi pengukuran empiris skala besar terhadap keamanan autentikasi OAuth pada 7.973 remote server MCP di dunia nyata, mengungkap 325 cacat keamanan dan 9 CVE (contoh eksplisit Pedoman Bagian 3: Zhou et al. = benchmark_measurement). | AA86: =IF(I86="","",IF(OR(I86="attack",I86="survey_review",I86="benchmark_measurement",I86="position_other",I86="not_defense"),"n/a",IF(OR(X86="spec_normatif",X86="produksi_bukti_publik"),"L3",IF(ISNUMBER(SEARCH("independent",R86)),"L2",IF(R86="author_run","L1",IF(R86="none","L0","")))))) | AB86: =IF(I86="","",IF(AND(K86="deterministic_policy",M86="ya"),"PERIKSA: deterministic_policy tetapi LLM/ML ada dalam keputusan. ","")&IF(AND(U86="ya",V86=""),"PERIKSA: adaptif=ya wajib ada kutipan. ","")&IF(AND(R86="none",U86<>"n/a_tanpa_evaluasi",U86<>""),"PERIKSA: tanpa evaluasi, adaptif harus n/a. ","")&IF(AND(OR(R86="author_run",R86="author_run+independent",R86="independent_only"),Q86=""),"PERIKSA: isi kelas_dievaluasi. ","")&IF(AND(OR(R86="author_run",R86="author_run+independent",R86="independent_only"),W86=""),"PERIKSA: isi lokasi_bukti. ","")&IF(AND(H86="tidak",R86<>""),"PERIKSA: tanpa teks lengkap, kosongkan kolom evaluasi. ","")) | AC86: include
A87: mehrdad-2026-trustshiftprobe-characterizing-benchmarking-defending-staged | B87: TrustShiftProbe: Characterizing, Benchmarking, and Defending Staged Trust Attacks on MCP Servers | C87: 2026 | D87: E2 | E87: kandidat_cek_recall | F87: none | G87: https://arxiv.org/abs/2608.23763 | H87: ya | I87: defense_primary | J87: SHIELD | K87: content_inspection_runtime | L87: Pertahanan runtime multi-tingkat pada batas transport MCP yang mengaudit payload respons server terhadap profil baseline perilaku yang dipelajari selama jendela kepercayaan bersih. | M87: tidak | N87: gateway_proxy | O87: R2;R5;R7 | P87: B1;C5;D1 | Q87: B1;C5;D1 | R87: author_run | T87: authors_own | U87: tidak | W87: Sec. VI, Table III & IV, Fig. 4 | X87: none | Y87: dilaporkan: overhead latensi runtime (Tabel IV) | Z87: SHIELD adalah pertahanan runtime batas transport MCP terhadap serangan defeksi bertahap (TrustShift) pada server MCP. Catatan deployment: prototipe internal/eksperimental (belum dirilis secara publik). | AA87: =IF(I87="","",IF(OR(I87="attack",I87="survey_review",I87="benchmark_measurement",I87="position_other",I87="not_defense"),"n/a",IF(OR(X87="spec_normatif",X87="produksi_bukti_publik"),"L3",IF(ISNUMBER(SEARCH("independent",R87)),"L2",IF(R87="author_run","L1",IF(R87="none","L0","")))))) | AB87: =IF(I87="","",IF(AND(K87="deterministic_policy",M87="ya"),"PERIKSA: deterministic_policy tetapi LLM/ML ada dalam keputusan. ","")&IF(AND(U87="ya",V87=""),"PERIKSA: adaptif=ya wajib ada kutipan. ","")&IF(AND(R87="none",U87<>"n/a_tanpa_evaluasi",U87<>""),"PERIKSA: tanpa evaluasi, adaptif harus n/a. ","")&IF(AND(OR(R87="author_run",R87="author_run+independent",R87="independent_only"),Q87=""),"PERIKSA: isi kelas_dievaluasi. ","")&IF(AND(OR(R87="author_run",R87="author_run+independent",R87="independent_only"),W87=""),"PERIKSA: isi lokasi_bukti. ","")&IF(AND(H87="tidak",R87<>""),"PERIKSA: tanpa teks lengkap, kosongkan kolom evaluasi. ","")) | AC87: include
A88: mohsen-2026-securing-ai-agents-cyber-physical | B88: Securing AI Agents in Cyber-Physical Systems: A Survey of Environmental Interactions, Deepfake Threats, and Defenses | C88: 2026 | D88: E2 | E88: kandidat_cek_recall | F88: none | G88: https://arxiv.org/abs/2601.20184 | H88: ya | I88: survey_review | Z88: Agent Recall: BUKAN_PERTAHANAN - Makalah survei/tinjauan komprehensif ancaman keamanan agen AI pada cyber-physical systems termasuk kerentanan mediasi MCP dan kerangka SENTINEL (sesuai Pedoman Bagian 3 Penegasan: survei pertahanan diklasifikasikan sebagai survey_review). | AA88: =IF(I88="","",IF(OR(I88="attack",I88="survey_review",I88="benchmark_measurement",I88="position_other",I88="not_defense"),"n/a",IF(OR(X88="spec_normatif",X88="produksi_bukti_publik"),"L3",IF(ISNUMBER(SEARCH("independent",R88)),"L2",IF(R88="author_run","L1",IF(R88="none","L0","")))))) | AB88: =IF(I88="","",IF(AND(K88="deterministic_policy",M88="ya"),"PERIKSA: deterministic_policy tetapi LLM/ML ada dalam keputusan. ","")&IF(AND(U88="ya",V88=""),"PERIKSA: adaptif=ya wajib ada kutipan. ","")&IF(AND(R88="none",U88<>"n/a_tanpa_evaluasi",U88<>""),"PERIKSA: tanpa evaluasi, adaptif harus n/a. ","")&IF(AND(OR(R88="author_run",R88="author_run+independent",R88="independent_only"),Q88=""),"PERIKSA: isi kelas_dievaluasi. ","")&IF(AND(OR(R88="author_run",R88="author_run+independent",R88="independent_only"),W88=""),"PERIKSA: isi lokasi_bukti. ","")&IF(AND(H88="tidak",R88<>""),"PERIKSA: tanpa teks lengkap, kosongkan kolom evaluasi. ","")) | AC88: include
A89: n-2025-breaking-protocol-security-analysis-model | B89: Breaking the Protocol: Security Analysis of the Model Context Protocol Specification and Prompt Injection Vulnerabilities in Tool-Integrated LLM Agents | C89: 2025 | D89: E1 | E89: kandidat_cek_recall | F89: none | G89: https://doi.org/10.25559/sitito.021.202503.420-428 | H89: ya | I89: defense_secondary | J89: AttestMCP | K89: integrity_provenance | L89: Ekstensi protokol AttestMCP berbasis sertifikat kapabilitas federated CA, autentikasi pesan HMAC-SHA256, origin tagging, dan sliding window nonces untuk menjamin integritas pertukaran pesan MCP. | M89: tidak | N89: C | O89: R1;R2;R4;R6 | P89: A2;C3;C5;D1 | Q89: A2;D1 | R89: author_run | T89: authors_own | U89: tidak | W89: Sec. VI; Table IX & X; hal. 5-6 | X89: none | Y89: latensi 2.4 ms (warm) / 8.3 ms (cold) per pesan (Tabel IX) | Z89: Teks lengkap diunduh via arXiv:2601.17549. Evaluasi empiris author_run pada benchmark ProtoAmp (847 skenario): menurunkan ASR sebesar 76.5% (dari 52.8% ke 12.4%, Tabel X); overhead latensi 2.4 ms warm / 8.3 ms cold (Tabel IX). Catatan deployment: prototipe internal/eksperimental (belum dirilis secara publik). | AA89: =IF(I89="","",IF(OR(I89="attack",I89="survey_review",I89="benchmark_measurement",I89="position_other",I89="not_defense"),"n/a",IF(OR(X89="spec_normatif",X89="produksi_bukti_publik"),"L3",IF(ISNUMBER(SEARCH("independent",R89)),"L2",IF(R89="author_run","L1",IF(R89="none","L0","")))))) | AB89: =IF(I89="","",IF(AND(K89="deterministic_policy",M89="ya"),"PERIKSA: deterministic_policy tetapi LLM/ML ada dalam keputusan. ","")&IF(AND(U89="ya",V89=""),"PERIKSA: adaptif=ya wajib ada kutipan. ","")&IF(AND(R89="none",U89<>"n/a_tanpa_evaluasi",U89<>""),"PERIKSA: tanpa evaluasi, adaptif harus n/a. ","")&IF(AND(OR(R89="author_run",R89="author_run+independent",R89="independent_only"),Q89=""),"PERIKSA: isi kelas_dievaluasi. ","")&IF(AND(OR(R89="author_run",R89="author_run+independent",R89="independent_only"),W89=""),"PERIKSA: isi lokasi_bukti. ","")&IF(AND(H89="tidak",R89<>""),"PERIKSA: tanpa teks lengkap, kosongkan kolom evaluasi. ","")) | AC89: include
A90: pei-2026-rethinking-mcp-security-large-scale | B90: Rethinking MCP Security: A Large-Scale Study of Runtime MCP Servers and Security Scanner Reliability | C90: 2026 | D90: E2 | E90: kandidat_cek_recall | F90: none | G90: https://arxiv.org/abs/2607.11086 | H90: ya | I90: benchmark_measurement | Z90: Agent Recall: BUKAN_PERTAHANAN - Studi pengukuran dan penyusunan dataset MCPZoo (64.611 server MCP) untuk menguji serta mengukur reliabilitas security scanner yang ada di ekosistem MCP. | AA90: =IF(I90="","",IF(OR(I90="attack",I90="survey_review",I90="benchmark_measurement",I90="position_other",I90="not_defense"),"n/a",IF(OR(X90="spec_normatif",X90="produksi_bukti_publik"),"L3",IF(ISNUMBER(SEARCH("independent",R90)),"L2",IF(R90="author_run","L1",IF(R90="none","L0","")))))) | AB90: =IF(I90="","",IF(AND(K90="deterministic_policy",M90="ya"),"PERIKSA: deterministic_policy tetapi LLM/ML ada dalam keputusan. ","")&IF(AND(U90="ya",V90=""),"PERIKSA: adaptif=ya wajib ada kutipan. ","")&IF(AND(R90="none",U90<>"n/a_tanpa_evaluasi",U90<>""),"PERIKSA: tanpa evaluasi, adaptif harus n/a. ","")&IF(AND(OR(R90="author_run",R90="author_run+independent",R90="independent_only"),Q90=""),"PERIKSA: isi kelas_dievaluasi. ","")&IF(AND(OR(R90="author_run",R90="author_run+independent",R90="independent_only"),W90=""),"PERIKSA: isi lokasi_bukti. ","")&IF(AND(H90="tidak",R90<>""),"PERIKSA: tanpa teks lengkap, kosongkan kolom evaluasi. ","")) | AC90: include
A91: pengyu-2026-viper-mcp-detecting-exploiting-taint | B91: VIPER-MCP: Detecting and Exploiting Taint-Style Vulnerabilities in Model Context Protocol Servers | C91: 2026 | D91: E2 | E91: kandidat_cek_recall | F91: none | G91: https://arxiv.org/abs/2605.21392 | H91: ya | I91: defense_primary | J91: VIPER-MCP | K91: content_inspection_static | L91: Kerangka pendeteksi kerentanan server MCP berbasis pelacakan taint hybrid (statis-dinamis) dan fuzzing terisolasi untuk mengidentifikasi eksfiltrasi dan injeksi perintah. | M91: tidak | N91: offline_analysis | O91: R2;R5 | P91: A2;C5;D1 | Q91: A2;C5;D1 | R91: author_run | T91: mixed | U91: tidak | W91: Sec. 5.3, Tabel 2, hal. 10-11 | X91: none | Y91: dilaporkan: waktu analisis rata-rata per server (Sec. 5.3) | Z91: VIPER-MCP (defense_primary, L1). Evaluator independen bagi McpSafetyScanner sebagai baseline pesaing di Tabel 2 (hal. 11: FPR 43.1%, FNR 63.8%). Catatan deployment: prototipe internal/eksperimental (belum dirilis secara publik). | AA91: =IF(I91="","",IF(OR(I91="attack",I91="survey_review",I91="benchmark_measurement",I91="position_other",I91="not_defense"),"n/a",IF(OR(X91="spec_normatif",X91="produksi_bukti_publik"),"L3",IF(ISNUMBER(SEARCH("independent",R91)),"L2",IF(R91="author_run","L1",IF(R91="none","L0","")))))) | AB91: =IF(I91="","",IF(AND(K91="deterministic_policy",M91="ya"),"PERIKSA: deterministic_policy tetapi LLM/ML ada dalam keputusan. ","")&IF(AND(U91="ya",V91=""),"PERIKSA: adaptif=ya wajib ada kutipan. ","")&IF(AND(R91="none",U91<>"n/a_tanpa_evaluasi",U91<>""),"PERIKSA: tanpa evaluasi, adaptif harus n/a. ","")&IF(AND(OR(R91="author_run",R91="author_run+independent",R91="independent_only"),Q91=""),"PERIKSA: isi kelas_dievaluasi. ","")&IF(AND(OR(R91="author_run",R91="author_run+independent",R91="independent_only"),W91=""),"PERIKSA: isi lokasi_bukti. ","")&IF(AND(H91="tidak",R91<>""),"PERIKSA: tanpa teks lengkap, kosongkan kolom evaluasi. ","")) | AC91: include
A92: pintu-2025-mcp-puf-context-hardened-ml | B92: MCP-PUF: A Context-Hardened, ML-Assisted Authentication Protocol for Secure Healthcare IoT | C92: 2025 | D92: E1 | E92: kandidat_cek_recall | F92: none | G92: https://doi.org/10.1109/TEMSMET65536.2025.11467437 | H92: tidak | I92: not_defense | Z92: [AUDIT_v5_EXCLUDE: EC5] Dikeluarkan dari korpus MCP-spesifik oleh audit reviewer kedua v5. (dikeluarkan setelah audit reviewer kedua + rekonsiliasi) | Catatan lama: Agent Recall: BUKAN_PERTAHANAN - Makalah domain autentikasi hardware IoT kesehatan menggunakan Physical Unclonable Functions (PUF) pada STM32; bukan mekanisme pertahanan keamanan sistem berbasis MCP untuk LLM. | AA92: =IF(I92="","",IF(OR(I92="attack",I92="survey_review",I92="benchmark_measurement",I92="position_other",I92="not_defense"),"n/a",IF(OR(X92="spec_normatif",X92="produksi_bukti_publik"),"L3",IF(ISNUMBER(SEARCH("independent",R92)),"L2",IF(R92="author_run","L1",IF(R92="none","L0","")))))) | AB92: =IF(I92="","",IF(AND(K92="deterministic_policy",M92="ya"),"PERIKSA: deterministic_policy tetapi LLM/ML ada dalam keputusan. ","")&IF(AND(U92="ya",V92=""),"PERIKSA: adaptif=ya wajib ada kutipan. ","")&IF(AND(R92="none",U92<>"n/a_tanpa_evaluasi",U92<>""),"PERIKSA: tanpa evaluasi, adaptif harus n/a. ","")&IF(AND(OR(R92="author_run",R92="author_run+independent",R92="independent_only"),Q92=""),"PERIKSA: isi kelas_dievaluasi. ","")&IF(AND(OR(R92="author_run",R92="author_run+independent",R92="independent_only"),W92=""),"PERIKSA: isi lokasi_bukti. ","")&IF(AND(H92="tidak",R92<>""),"PERIKSA: tanpa teks lengkap, kosongkan kolom evaluasi. ","")) | AC92: exclude | AD92: EC5 | AE92: dikeluarkan setelah audit reviewer kedua + rekonsiliasi
A93: saeid-2025-semantic-attacks-tool-augmented-llms | B93: Semantic Attacks on Tool-Augmented LLMs: Securing the Model Context Protocol Against Descriptor-Level Manipulation | C93: 2025 | D93: E2 | E93: kandidat_cek_recall | F93: none | G93: https://arxiv.org/abs/2512.06556 | H93: ya | I93: defense_primary | J93: unnamed:layered semantic defense | K93: content_inspection_runtime | L93: Pertahanan berlapis yang menggabungkan verifikasi integritas deskriptor tool, pemeriksaan semantik pra-konteks via LLM pembantu, dan guardrail runtime untuk mencegah manipulasi deskriptor. | M93: ya | N93: gateway_proxy | O93: R2;R7 | P93: A1;A3;B1 | Q93: A1;A3;B1 | R93: author_run | T93: authors_own | U93: tidak | W93: Sec. IV, Table 2-4, hal. 6-9 | X93: none | Y93: dilaporkan: trade-off latensi dan keamanan antar arsitektur LLM (Sec. IV-C) | Z93: Mengevaluasi pertahanan berlapis terhadap manipulasi semantik deskriptor tool pada lingkungan MCP. | AA93: =IF(I93="","",IF(OR(I93="attack",I93="survey_review",I93="benchmark_measurement",I93="position_other",I93="not_defense"),"n/a",IF(OR(X93="spec_normatif",X93="produksi_bukti_publik"),"L3",IF(ISNUMBER(SEARCH("independent",R93)),"L2",IF(R93="author_run","L1",IF(R93="none","L0","")))))) | AB93: =IF(I93="","",IF(AND(K93="deterministic_policy",M93="ya"),"PERIKSA: deterministic_policy tetapi LLM/ML ada dalam keputusan. ","")&IF(AND(U93="ya",V93=""),"PERIKSA: adaptif=ya wajib ada kutipan. ","")&IF(AND(R93="none",U93<>"n/a_tanpa_evaluasi",U93<>""),"PERIKSA: tanpa evaluasi, adaptif harus n/a. ","")&IF(AND(OR(R93="author_run",R93="author_run+independent",R93="independent_only"),Q93=""),"PERIKSA: isi kelas_dievaluasi. ","")&IF(AND(OR(R93="author_run",R93="author_run+independent",R93="independent_only"),W93=""),"PERIKSA: isi lokasi_bukti. ","")&IF(AND(H93="tidak",R93<>""),"PERIKSA: tanpa teks lengkap, kosongkan kolom evaluasi. ","")) | AC93: include
A94: saeid-2026-verifiable-manifest-signing-transparency-enforcement | B94: Verifiable Manifest Signing and Transparency Enforcement for Secure MCP-Based LLM Pipelines | C94: 2026 | D94: E2 | E94: kandidat_cek_recall | F94: none | G94: https://arxiv.org/abs/2601.23132 | H94: ya | I94: defense_primary | J94: Verifiable Manifest Enforcement | K94: integrity_provenance | L94: Penegakan keamanan level manifes pada pemanggilan tool MCP menggunakan tanda tangan digital, verifikasi runtime, pengecekan kesegaran, dan pencatatan log transparansi yang dapat diaudit. | M94: tidak | N94: gateway_proxy | O94: R2;R7;PRA | P94: A1;B1;D3 | Q94: A1;B1;D3 | R94: author_run | T94: authors_own | U94: tidak | W94: Sec. IV, Table 1-3, Fig. 3 | X94: none | Y94: dilaporkan: latensi verifikasi dan overhead kriptografi (Sec. IV-A) | Z94: Kerangka penegakan tanda tangan digital dan log transparansi untuk manifes pemanggilan tool MCP. | AA94: =IF(I94="","",IF(OR(I94="attack",I94="survey_review",I94="benchmark_measurement",I94="position_other",I94="not_defense"),"n/a",IF(OR(X94="spec_normatif",X94="produksi_bukti_publik"),"L3",IF(ISNUMBER(SEARCH("independent",R94)),"L2",IF(R94="author_run","L1",IF(R94="none","L0","")))))) | AB94: =IF(I94="","",IF(AND(K94="deterministic_policy",M94="ya"),"PERIKSA: deterministic_policy tetapi LLM/ML ada dalam keputusan. ","")&IF(AND(U94="ya",V94=""),"PERIKSA: adaptif=ya wajib ada kutipan. ","")&IF(AND(R94="none",U94<>"n/a_tanpa_evaluasi",U94<>""),"PERIKSA: tanpa evaluasi, adaptif harus n/a. ","")&IF(AND(OR(R94="author_run",R94="author_run+independent",R94="independent_only"),Q94=""),"PERIKSA: isi kelas_dievaluasi. ","")&IF(AND(OR(R94="author_run",R94="author_run+independent",R94="independent_only"),W94=""),"PERIKSA: isi lokasi_bukti. ","")&IF(AND(H94="tidak",R94<>""),"PERIKSA: tanpa teks lengkap, kosongkan kolom evaluasi. ","")) | AC94: include
A95: shaswata-2026-agenticcyops-securing-multi-agentic-ai | B95: AgenticCyOps: Securing Multi-Agentic AI Integration in Enterprise Cyber Operations | C95: 2026 | D95: E2 | E95: kandidat_cek_recall | F95: none | G95: https://arxiv.org/abs/2603.09134 | H95: tidak | I95: not_defense | Z95: [AUDIT_v5_EXCLUDE: EC2] Dikeluarkan dari korpus MCP-spesifik oleh audit reviewer kedua v5 (peran sebelumnya proposal_only didemotasi karena di luar korpus MCP). (audit lanjutan; diterima koordinator) | Catatan lama: Agent Recall: PROPOSAL_ONLY - Mengusulkan kerangka arsitektur AgenticCyOps untuk integrasi multi-agent SOC menggunakan MCP; evaluasi menggunakan analisis struktural/pemetaan prinsip, tetapi secara eksplisit mengakui belum melakukan simulasi adversarial empiris dan belum mengukur runtime overhead. | AA95: =IF(I95="","",IF(OR(I95="attack",I95="survey_review",I95="benchmark_measurement",I95="position_other",I95="not_defense"),"n/a",IF(OR(X95="spec_normatif",X95="produksi_bukti_publik"),"L3",IF(ISNUMBER(SEARCH("independent",R95)),"L2",IF(R95="author_run","L1",IF(R95="none","L0","")))))) | AB95: =IF(I95="","",IF(AND(K95="deterministic_policy",M95="ya"),"PERIKSA: deterministic_policy tetapi LLM/ML ada dalam keputusan. ","")&IF(AND(U95="ya",V95=""),"PERIKSA: adaptif=ya wajib ada kutipan. ","")&IF(AND(R95="none",U95<>"n/a_tanpa_evaluasi",U95<>""),"PERIKSA: tanpa evaluasi, adaptif harus n/a. ","")&IF(AND(OR(R95="author_run",R95="author_run+independent",R95="independent_only"),Q95=""),"PERIKSA: isi kelas_dievaluasi. ","")&IF(AND(OR(R95="author_run",R95="author_run+independent",R95="independent_only"),W95=""),"PERIKSA: isi lokasi_bukti. ","")&IF(AND(H95="tidak",R95<>""),"PERIKSA: tanpa teks lengkap, kosongkan kolom evaluasi. ","")) | AC95: exclude | AD95: EC2 | AE95: audit lanjutan; diterima koordinator
A96: sonu-2025-mcp-guardian-security-first-layer | B96: MCP Guardian: A Security-First Layer for Safeguarding MCP-Based AI System | C96: 2025 | D96: E2 | E96: kandidat_cek_recall | F96: none | G96: https://arxiv.org/abs/2504.12757 | H96: ya | I96: defense_primary | J96: MCP Guardian | K96: deterministic_policy | L96: Lapisan middleware perantara klien dan server MCP yang menerapkan autentikasi, pembatasan laju (rate limiting), logging audit, dan pemindaian WAF terhadap payload berbahaya. | M96: tidak | N96: gateway_proxy | O96: R1;R2;R4 | P96: A2;C3;C5;OUT_OF_TAXONOMY:resource_abuse | Q96: A2;C3;C5;OUT_OF_TAXONOMY:resource_abuse | R96: author_run | T96: authors_own | U96: tidak | W96: Sec. 5, Table 1, hal. 7-9 | X96: none | Y96: dilaporkan: latensi baseline vs dengan Guardian (Sec. 5) | Z96: MCP Guardian (defense_primary, L1). Middleware proksi dengan autentikasi (C3), WAF pemfilteran prompt & command injection (A2;C5), serta rate-limiting terhadap high-frequency abuse (OUT_OF_TAXONOMY:resource_abuse, Sec. 4.1.1). Catatan deployment: prototipe internal/eksperimental (belum dirilis secara publik). | AA96: =IF(I96="","",IF(OR(I96="attack",I96="survey_review",I96="benchmark_measurement",I96="position_other",I96="not_defense"),"n/a",IF(OR(X96="spec_normatif",X96="produksi_bukti_publik"),"L3",IF(ISNUMBER(SEARCH("independent",R96)),"L2",IF(R96="author_run","L1",IF(R96="none","L0","")))))) | AB96: =IF(I96="","",IF(AND(K96="deterministic_policy",M96="ya"),"PERIKSA: deterministic_policy tetapi LLM/ML ada dalam keputusan. ","")&IF(AND(U96="ya",V96=""),"PERIKSA: adaptif=ya wajib ada kutipan. ","")&IF(AND(R96="none",U96<>"n/a_tanpa_evaluasi",U96<>""),"PERIKSA: tanpa evaluasi, adaptif harus n/a. ","")&IF(AND(OR(R96="author_run",R96="author_run+independent",R96="independent_only"),Q96=""),"PERIKSA: isi kelas_dievaluasi. ","")&IF(AND(OR(R96="author_run",R96="author_run+independent",R96="independent_only"),W96=""),"PERIKSA: isi lokasi_bukti. ","")&IF(AND(H96="tidak",R96<>""),"PERIKSA: tanpa teks lengkap, kosongkan kolom evaluasi. ","")) | AC96: include
A97: suliu-2026-airguard-guarding-agent-actions-runtime | B97: AIRGuard: Guarding Agent Actions with Runtime Authority Control | C97: 2026 | D97: E2 | E97: kandidat_cek_recall | F97: none | G97: https://arxiv.org/abs/2605.28914 | H97: tidak | I97: not_defense | Z97: [AUDIT_v5_EXCLUDE: EC2] Dikeluarkan dari korpus MCP-spesifik oleh audit reviewer kedua v5 (peran sebelumnya defense_primary didemotasi karena di luar korpus MCP). (audit lanjutan; diterima koordinator) | Catatan lama: Agent Recall: KANDIDAT_AKTIF - Terbukti mengevaluasi mitigasi: Mengembangkan dan mengevaluasi AIRGuard (runtime guard kontrol otoritas aksi untuk memitigasi authority confusion pada pemanggilan tool MCP; dievaluasi pada AgentTrap menurunkan attack success rate Sonnet 4.6 dari 36.3% ke 5.5% dan menjaga utilitas 76.0% pada DTAP-150). | AA97: =IF(I97="","",IF(OR(I97="attack",I97="survey_review",I97="benchmark_measurement",I97="position_other",I97="not_defense"),"n/a",IF(OR(X97="spec_normatif",X97="produksi_bukti_publik"),"L3",IF(ISNUMBER(SEARCH("independent",R97)),"L2",IF(R97="author_run","L1",IF(R97="none","L0","")))))) | AB97: =IF(I97="","",IF(AND(K97="deterministic_policy",M97="ya"),"PERIKSA: deterministic_policy tetapi LLM/ML ada dalam keputusan. ","")&IF(AND(U97="ya",V97=""),"PERIKSA: adaptif=ya wajib ada kutipan. ","")&IF(AND(R97="none",U97<>"n/a_tanpa_evaluasi",U97<>""),"PERIKSA: tanpa evaluasi, adaptif harus n/a. ","")&IF(AND(OR(R97="author_run",R97="author_run+independent",R97="independent_only"),Q97=""),"PERIKSA: isi kelas_dievaluasi. ","")&IF(AND(OR(R97="author_run",R97="author_run+independent",R97="independent_only"),W97=""),"PERIKSA: isi lokasi_bukti. ","")&IF(AND(H97="tidak",R97<>""),"PERIKSA: tanpa teks lengkap, kosongkan kolom evaluasi. ","")) | AC97: exclude | AD97: EC2 | AE97: audit lanjutan; diterima koordinator
A98: yutao-2026-description-code-inconsistency-real-world | B98: Description-Code Inconsistency in Real-world MCP Servers: Measurement, Detection, and Security Implications | C98: 2026 | D98: E2 | E98: kandidat_cek_recall | F98: none | G98: https://arxiv.org/abs/2606.04769 | H98: ya | I98: benchmark_measurement | Z98: Agent Recall: BUKAN_PERTAHANAN - Studi pengukuran empiris terhadap Description-Code Inconsistency (DCI) pada 19.200 pasangan deskripsi-kode dari 2.214 server MCP menggunakan DCIChecker; mengkaji prevalensi celah keamanan dan menyarankan mitigasi pada diskusi. | AA98: =IF(I98="","",IF(OR(I98="attack",I98="survey_review",I98="benchmark_measurement",I98="position_other",I98="not_defense"),"n/a",IF(OR(X98="spec_normatif",X98="produksi_bukti_publik"),"L3",IF(ISNUMBER(SEARCH("independent",R98)),"L2",IF(R98="author_run","L1",IF(R98="none","L0","")))))) | AB98: =IF(I98="","",IF(AND(K98="deterministic_policy",M98="ya"),"PERIKSA: deterministic_policy tetapi LLM/ML ada dalam keputusan. ","")&IF(AND(U98="ya",V98=""),"PERIKSA: adaptif=ya wajib ada kutipan. ","")&IF(AND(R98="none",U98<>"n/a_tanpa_evaluasi",U98<>""),"PERIKSA: tanpa evaluasi, adaptif harus n/a. ","")&IF(AND(OR(R98="author_run",R98="author_run+independent",R98="independent_only"),Q98=""),"PERIKSA: isi kelas_dievaluasi. ","")&IF(AND(OR(R98="author_run",R98="author_run+independent",R98="independent_only"),W98=""),"PERIKSA: isi lokasi_bukti. ","")&IF(AND(H98="tidak",R98<>""),"PERIKSA: tanpa teks lengkap, kosongkan kolom evaluasi. ","")) | AC98: include
A99: abhinav-2025-throttling-web-agents-using-reasoning | B99: Throttling Web Agents Using Reasoning Gates | C99: 2025 | D99: E2 | E99: scan_cepat | F99: none | G99: https://arxiv.org/abs/2509.01619 | I99: not_defense | Z99: [AUDIT_v5_EXCLUDE: EC2] Dikeluarkan dari korpus MCP-spesifik oleh audit reviewer kedua v5. (dikeluarkan setelah audit reviewer kedua + rekonsiliasi) | Catatan lama: Throttling berbasis puzzle komputasi untuk melindungi server web dari scraping bot/agent, di luar fokus keamanan internal MCP. | AA99: =IF(I99="","",IF(OR(I99="attack",I99="survey_review",I99="benchmark_measurement",I99="position_other",I99="not_defense"),"n/a",IF(OR(X99="spec_normatif",X99="produksi_bukti_publik"),"L3",IF(ISNUMBER(SEARCH("independent",R99)),"L2",IF(R99="author_run","L1",IF(R99="none","L0","")))))) | AB99: =IF(I99="","",IF(AND(K99="deterministic_policy",M99="ya"),"PERIKSA: deterministic_policy tetapi LLM/ML ada dalam keputusan. ","")&IF(AND(U99="ya",V99=""),"PERIKSA: adaptif=ya wajib ada kutipan. ","")&IF(AND(R99="none",U99<>"n/a_tanpa_evaluasi",U99<>""),"PERIKSA: tanpa evaluasi, adaptif harus n/a. ","")&IF(AND(OR(R99="author_run",R99="author_run+independent",R99="independent_only"),Q99=""),"PERIKSA: isi kelas_dievaluasi. ","")&IF(AND(OR(R99="author_run",R99="author_run+independent",R99="independent_only"),W99=""),"PERIKSA: isi lokasi_bukti. ","")&IF(AND(H99="tidak",R99<>""),"PERIKSA: tanpa teks lengkap, kosongkan kolom evaluasi. ","")) | AC99: exclude | AD99: EC2 | AE99: dikeluarkan setelah audit reviewer kedua + rekonsiliasi
A100: aditi-2025-survey-model-context-protocol-mcp | B100: A Survey of the Model Context Protocol (MCP): Standardizing Context to Enhance Large Language Models (LLMs) | C100: 2025 | D100: E2 | E100: scan_cepat | F100: none | G100: https://doi.org/10.20944/preprints202504.0245.v1 | I100: survey_review | Z100: [AUDIT_v5_EXCLUDE: EC1] Dikeluarkan dari korpus MCP-spesifik oleh audit reviewer kedua v5. (audit lanjutan; diterima koordinator) | Catatan lama: Tinjauan survei arsitektur dasar, protokol, dan mekanisme keamanan MCP tanpa mitigasi baru. | AA100: =IF(I100="","",IF(OR(I100="attack",I100="survey_review",I100="benchmark_measurement",I100="position_other",I100="not_defense"),"n/a",IF(OR(X100="spec_normatif",X100="produksi_bukti_publik"),"L3",IF(ISNUMBER(SEARCH("independent",R100)),"L2",IF(R100="author_run","L1",IF(R100="none","L0","")))))) | AB100: =IF(I100="","",IF(AND(K100="deterministic_policy",M100="ya"),"PERIKSA: deterministic_policy tetapi LLM/ML ada dalam keputusan. ","")&IF(AND(U100="ya",V100=""),"PERIKSA: adaptif=ya wajib ada kutipan. ","")&IF(AND(R100="none",U100<>"n/a_tanpa_evaluasi",U100<>""),"PERIKSA: tanpa evaluasi, adaptif harus n/a. ","")&IF(AND(OR(R100="author_run",R100="author_run+independent",R100="independent_only"),Q100=""),"PERIKSA: isi kelas_dievaluasi. ","")&IF(AND(OR(R100="author_run",R100="author_run+independent",R100="independent_only"),W100=""),"PERIKSA: isi lokasi_bukti. ","")&IF(AND(H100="tidak",R100<>""),"PERIKSA: tanpa teks lengkap, kosongkan kolom evaluasi. ","")) | AC100: exclude | AD100: EC1 | AE100: audit lanjutan; diterima koordinator
...

Sheet Kamus_Kode
A1: KODE | B1: DEFINISI OPERASIONAL
A2: defense_primary | B2: Kontribusi utama paper adalah mekanisme pertahanan yang diimplementasikan atau dispesifikasikan.
A3: defense_secondary | B3: Kontribusi utama serangan, pengukuran, atau survei, tetapi paper mengimplementasikan DAN mengevaluasi minimal satu mitigasi.
A4: proposal_only | B4: Merekomendasikan atau menyketsa mitigasi tanpa implementasi atau evaluasi. Survei/SLR atas pertahanan BUKAN proposal_only: pakai survey_review.
A5: attack | B5: Kontribusi utama serangan atau eksploit, tanpa mitigasi yang dievaluasi.
A6: survey_review | B6: Survei, SLR, taksonomi, atau tinjauan.
A7: benchmark_measurement | B7: Benchmark, dataset, atau studi pengukuran tanpa mitigasi yang dievaluasi.
A8: position_other | B8: Makalah posisi, konseptual, indeks/kerangka penilaian tanpa mekanisme penegakan.
A9: not_defense | B9: Di luar cakupan pertahanan karena alasan lain (jelaskan di catatan).
A10: llm_dlm_keputusan = ya | B10: Keputusan izin/tolak/deteksi pada runtime bergantung pada keluaran LLM atau model ML (LLM-as-judge, klasifikator ML, LLM yang menormalisasi input dan hasilnya menentukan keputusan).
A11: llm_dlm_keputusan = tidak | B11: Keputusan murni dari aturan, kriptografi, atau mekanisme OS. Hanya kasus ini yang boleh berparadigma deterministic_policy.
A12: paradigma | B12: Pilih prinsip penegakan, bukan nama produk. Hibrida: pilih yang menentukan keputusan akhir dan jelaskan sisanya di ringkasan.
... A23: L3 | B23: Dilaporkan TERPISAH dari L0-L2 di Section 6 (rujuk Tabel 15). Jangan dihitung sebagai persentase literatur.

Sheet Daftar
A1: peran | B1: paradigma | C1: llm_dlm_keputusan | D1: titik_penegakan | E1: jenis_evaluasi | F1: asal_set_serangan | G1: adaptif | H1: deployment | I1: teks_lengkap | K1: Daftar ini dipakai dropdown di sheet Koding. Jangan ubah urutan atau ejaan.
A2: defense_primary | B2: content_inspection_static | C2: ya | D2: H | E2: none | F2: authors_own | G2: ya | H2: none | I2: ya
A3: defense_secondary | B3: content_inspection_runtime | C3: tidak | D3: C | E3: author_run | F3: third_party_public | G3: tidak | H3: prototype_open_source | I3: tidak
A4: proposal_only | B4: human_approval | C4: tidak_jelas | D4: S | E4: author_run+independent | F4: mixed | G4: tidak_jelas | H4: produksi_bukti_publik
A5: attack | B5: isolation_containment | D5: gateway_proxy | E5: independent_only | F5: none | G5: n/a_tanpa_evaluasi | H5: spec_normatif
A6: survey_review | B6: deterministic_policy | D6: registry | E6: deployment_measurement
A7: benchmark_measurement | B7: capability_or_token | D7: Theta
A8: position_other | B8: integrity_provenance | D8: X
A9: not_defense | B9: protocol_provision | D9: offline_analysis
B10: lainnya | D10: lainnya

Sheet Koding_Korpus148
A1: record_id | B1: judul | C1: tahun | D1: tier | E1: triase | F1: agent_role (referensi) | G1: tautan | H1: teks_lengkap_tersedia | I1: peran | J1: nama_pertahanan | K1: paradigma | L1: ringkasan_mekanisme (kata sendiri, maks 2 kalimat) | M1: llm_dlm_keputusan | N1: titik_penegakan | O1: crossings (R1-R7, pisah ;) | P1: kelas_diklaim (A1-D3, pisah ;) | Q1: kelas_dievaluasi (hanya yang ada eksperimen) | R1: jenis_evaluasi | S1: evaluator_independen (record_id) | T1: asal_set_serangan | U1: adaptif | V1: kutipan_adaptif (maks 25 kata) | W1: lokasi_bukti (bagian/tabel/hal.) | X1: deployment | Y1: biaya_utilitas | Z1: catatan | AA1: maturitas (otomatis) | AB1: cek_konsistensi (otomatis) | AC1: korpus_v5 | AD1: kode_eksklusi_v5 | AE1: catatan_audit_v5
A2: aditi-2025-model-context-protocol-vision-systems | B2: Model Context Protocol for Vision Systems: Audit, Security, and Protocol Extensions | C2: 2025 | D2: E2 | E2: kandidat_agent | F2: primary | G2: https://arxiv.org/abs/2509.22814 | H2: ya | I2: proposal_only | J2: unnamed:vision-protocol-extensions | K2: protocol_provision | L2: Usulan ekstensi skema semantik MCP dan validator prototipe untuk membatasi aksi visi di testbed terkontrol. | M2: tidak | N2: registry | O2: R2;R5 | P2: A3;B3;C5 | R2: none | T2: none | U2: n/a_tanpa_evaluasi | X2: none | Y2: not_reported | Z2: Proposal ekstensi protokol MCP dengan skema semantik dan validator prototipe tanpa evaluasi terhadap serangan. Catatan deployment: prototipe internal/eksperimental (belum dirilis secara publik). | AA2: =IF(I2="","",IF(OR(I2="attack",I2="survey_review",I2="benchmark_measurement",I2="position_other",I2="not_defense"),"n/a",IF(OR(X2="spec_normatif",X2="produksi_bukti_publik"),"L3",IF(ISNUMBER(SEARCH("independent",R2)),"L2",IF(R2="author_run","L1",IF(R2="none","L0","")))))) | AB2: =IF(I2="","",IF(AND(K2="deterministic_policy",M2="ya"),"PERIKSA: deterministic_policy tetapi LLM/ML ada dalam keputusan. ","")&IF(AND(U2="ya",V2=""),"PERIKSA: adaptif=ya wajib ada kutipan. ","")&IF(AND(R2="none",U2<>"n/a_tanpa_evaluasi",U2<>""),"PERIKSA: tanpa evaluasi, adaptif harus n/a. ","")&IF(AND(OR(R2="author_run",R2="author_run+independent",R2="independent_only"),Q2=""),"PERIKSA: isi kelas_dievaluasi. ","")&IF(AND(OR(R2="author_run",R2="author_run+independent",R2="independent_only"),W2=""),"PERIKSA: isi lokasi_bukti. ","")&IF(AND(H2="tidak",R2<>""),"PERIKSA: tanpa teks lengkap, kosongkan kolom evaluasi. ","")) | AC2: include
A3: alfonso-2026-mcp-seclint-open-source-static | B3: MCP-SecLint: An Open-Source Static Analyzer for Detecting Vulnerabilities in LLM Tool Integrations | C3: 2026 | D3: E1 | E3: kandidat_agent | F3: primary | G3: https://doi.org/10.1145/3806007.3810961 | H3: ya | I3: defense_primary | J3: MCP-SecLint | K3: content_inspection_static | L3: Penganalisis statis offline kode server MCP untuk mendeteksi eksekusi perintah berbahaya, token passthrough, dan endpoint tanpa autentikasi. | M3: tidak | N3: offline_analysis | O3: R4;R5 | P3: C5;C3 | Q3: C5;C3 | R3: author_run | T3: third_party_public | U3: tidak | W3: Abstract / hal. 1 | X3: none | Y3: not_reported | Z3: Penganalisis statis MCP-SecLint untuk mendeteksi dangerous sinks (C5) dan unauthenticated endpoints (C3) pada implementasi server MCP. Klaim C1 dicabut karena analisis statis kode server tidak menangani confused deputy planner. Catatan deployment: prototipe internal/eksperimental (belum dirilis secara publik). | AA3: =IF(I3="","",IF(OR(I3="attack",I3="survey_review",I3="benchmark_measurement",I3="position_other",I3="not_defense"),"n/a",IF(OR(X3="spec_normatif",X3="produksi_bukti_publik"),"L3",IF(ISNUMBER(SEARCH("independent",R3)),"L2",IF(R3="author_run","L1",IF(R3="none","L0","")))))) | AB3: =IF(I3="","",IF(AND(K3="deterministic_policy",M3="ya"),"PERIKSA: deterministic_policy tetapi LLM/ML ada dalam keputusan. ","")&IF(AND(U3="ya",V3=""),"PERIKSA: adaptif=ya wajib ada kutipan. ","")&IF(AND(R3="none",U3<>"n/a_tanpa_evaluasi",U3<>""),"PERIKSA: tanpa evaluasi, adaptif harus n/a. ","")&IF(AND(OR(R3="author_run",R3="author_run+independent",R3="independent_only"),Q3=""),"PERIKSA: isi kelas_dievaluasi. ","")&IF(AND(OR(R3="author_run",R3="author_run+independent",R3="independent_only"),W3=""),"PERIKSA: isi lokasi_bukti. ","")&IF(AND(H3="tidak",R3<>""),"PERIKSA: tanpa teks lengkap, kosongkan kolom evaluasi. ","")) | AC3: include
A4: alfredo-2026-attested-tool-server-admission-security | B4: Attested Tool-Server Admission: A Security Extension to the Model Context Protocol | C4: 2026 | D4: E2 | E4: kandidat_agent | F4: primary | G4: https://arxiv.org/abs/2605.24248 | H4: ya | I4: defense_primary | J4: mcp-attested | K4: integrity_provenance | L4: Mekanisme admisi server teratestasi kriptografis Ed25519 dengan validasi clearance assertion terhadap root trust pinned dan allowlist deny-by-default. | M4: tidak | N4: registry | O4: R7 | P4: B1;B2 | Q4: B1;B2 | R4: author_run | T4: authors_own | U4: tidak | W4: Sec 7.1; Sec 7.2; Tabel hal. 12 | X4: none | Y4: not_reported | Z4: Mekanisme admisi server teratestasi Ed25519 mcp-attested dengan allowlist deny-by-default, diuji pada 48 kasus tes hermetik & adversarial. Catatan deployment: prototipe internal/eksperimental (belum dirilis secara publik). | AA4: =IF(I4="","",IF(OR(I4="attack",I4="survey_review",I4="benchmark_measurement",I4="position_other",I4="not_defense"),"n/a",IF(OR(X4="spec_normatif",X4="produksi_bukti_publik"),"L3",IF(ISNUMBER(SEARCH("independent",R4)),"L2",IF(R4="author_run","L1",IF(R4="none","L0","")))))) | AB4: =IF(I4="","",IF(AND(K4="deterministic_policy",M4="ya"),"PERIKSA: deterministic_policy tetapi LLM/ML ada dalam keputusan. ","")&IF(AND(U4="ya",V4=""),"PERIKSA: adaptif=ya wajib ada kutipan. ","")&IF(AND(R4="none",U4<>"n/a_tanpa_evaluasi",U4<>""),"PERIKSA: tanpa evaluasi, adaptif harus n/a. ","")&IF(AND(OR(R4="author_run",R4="author_run+independent",R4="independent_only"),Q4=""),"PERIKSA: isi kelas_dievaluasi. ","")&IF(AND(OR(R4="author_run",R4="author_run+independent",R4="independent_only"),W4=""),"PERIKSA: isi lokasi_bukti. ","")&IF(AND(H4="tidak",R4<>""),"PERIKSA: tanpa teks lengkap, kosongkan kolom evaluasi. ","")) | AC4: include
A5: anthropic-2024-model-context-protocol-specification-architecture | B5: Model Context Protocol Specification (Architecture & Security) | C5: 2024 | D5: E3 | E5: kandidat_agent | F5: primary | H5: ya | I5: position_other | Z5: Spesifikasi arsitektural protokol MCP resmi Anthropic (revisi 2024-11-05). Ketentuan normatif dilaporkan di Section 5 (Tabel 14-15), bukan sebagai L3 pertahanan literatur. | AA5: =IF(I5="","",IF(OR(I5="attack",I5="survey_review",I5="benchmark_measurement",I5="position_other",I5="not_defense"),"n/a",IF(OR(X5="spec_normatif",X5="produksi_bukti_publik"),"L3",IF(ISNUMBER(SEARCH("independent",R5)),"L2",IF(R5="author_run","L1",IF(R5="none","L0","")))))) | AB5: =IF(I5="","",IF(AND(K5="deterministic_policy",M5="ya"),"PERIKSA: deterministic_policy tetapi LLM/ML ada dalam keputusan. ","")&IF(AND(U5="ya",V5=""),"PERIKSA: adaptif=ya wajib ada kutipan. ","")&IF(AND(R5="none",U5<>"n/a_tanpa_evaluasi",U5<>""),"PERIKSA: tanpa evaluasi, adaptif harus n/a. ","")&IF(AND(OR(R5="author_run",R5="author_run+independent",R5="independent_only"),Q5=""),"PERIKSA: isi kelas_dievaluasi. ","")&IF(AND(OR(R5="author_run",R5="author_run+independent",R5="independent_only"),W5=""),"PERIKSA: isi lokasi_bukti. ","")&IF(AND(H5="tidak",R5<>""),"PERIKSA: tanpa teks lengkap, kosongkan kolom evaluasi. ","")) | AC5: include
A6: baichao-2026-flowguard-signals-evidence-mcp-security | B6: FlowGuard: From Signals to Evidence for MCP Security Detection | C6: 2026 | D6: E2 | E6: kandidat_agent | F6: primary | G6: https://arxiv.org/abs/2607.14754 | H6: ya | I6: defense_primary | J6: FlowGuard | K6: content_inspection_runtime | L6: Sistem pemindai keamanan MCP aktif berbasis probing bertahap (recon & strike) yang memverifikasi bukti runtime pada pemanggilan tool dan menganalisis risiko semantik metadata menggunakan LLM bounded. | M6: ya | N6: H | O6: R2;R4;R5 | P6: A1;A2;C3;C5 | Q6: A1;A2;C3;C5 | R6: author_run | T6: authors_own | U6: tidak | W6: Sec V; Table II; Table IV; hal. 7-10 | X6: none | Y6: latensi dilaporkan (reduksi 2.23x, Tabel IV) | Z6: Pemindai keamanan MCP dua fase (reconnaissance & targeted strike) dengan adjudikasi bukti berbasis Qwen3-235B. Diuji pada 1.880 kasus benchmark buatan penulis dan 8.000 server MCPZoo; ancaman adaptif eksplisit di luar cakupan. Catatan deployment: prototipe internal/eksperimental (belum dirilis secara publik). | AA6: =IF(I6="","",IF(OR(I6="attack",I6="survey_review",I6="benchmark_measurement",I6="position_other",I6="not_defense"),"n/a",IF(OR(X6="spec_normatif",X6="produksi_bukti_publik"),"L3",IF(ISNUMBER(SEARCH("independent",R6)),"L2",IF(R6="author_run","L1",IF(R6="none","L0","")))))) | AB6: =IF(I6="","",IF(AND(K6="deterministic_policy",M6="ya"),"PERIKSA: deterministic_policy tetapi LLM/ML ada dalam keputusan. ","")&IF(AND(U6="ya",V6=""),"PERIKSA: adaptif=ya wajib ada kutipan. ","")&IF(AND(R6="none",U6<>"n/a_tanpa_evaluasi",U6<>""),"PERIKSA: tanpa evaluasi, adaptif harus n/a. ","")&IF(AND(OR(R6="author_run",R6="author_run+independent",R6="independent_only"),Q6=""),"PERIKSA: isi kelas_dievaluasi. ","")&IF(AND(OR(R6="author_run",R6="author_run+independent",R6="independent_only"),W6=""),"PERIKSA: isi lokasi_bukti. ","")&IF(AND(H6="tidak",R6<>""),"PERIKSA: tanpa teks lengkap, kosongkan kolom evaluasi. ","")) | AC6: include
A7: bin-2025-mcpguard-automatically-detecting-vulnerabilities-mcp | B7: MCPGuard : Automatically Detecting Vulnerabilities in MCP Servers | C7: 2025 | D7: E2 | E7: kandidat_agent | F7: primary | G7: https://arxiv.org/abs/2510.23673 | H7: ya | I7: survey_review | Z7: Makalah survei/lanskap keamanan MCP dan tinjauan taksonomis komprehensif atas pertahanan yang ada (server-side scanning & runtime monitoring) tanpa evaluasi atau implementasi mekanisme baru oleh penulis. KODER 1 keliru menganggap judul 'MCPGuard' sebagai defense_primary. | AA7: =IF(I7="","",IF(OR(I7="attack",I7="survey_review",I7="benchmark_measurement",I7="position_other",I7="not_defense"),"n/a",IF(OR(X7="spec_normatif",X7="produksi_bukti_publik"),"L3",IF(ISNUMBER(SEARCH("independent",R7)),"L2",IF(R7="author_run","L1",IF(R7="none","L0","")))))) | AB7: =IF(I7="","",IF(AND(K7="deterministic_policy",M7="ya"),"PERIKSA: deterministic_policy tetapi LLM/ML ada dalam keputusan. ","")&IF(AND(U7="ya",V7=""),"PERIKSA: adaptif=ya wajib ada kutipan. ","")&IF(AND(R7="none",U7<>"n/a_tanpa_evaluasi",U7<>""),"PERIKSA: tanpa evaluasi, adaptif harus n/a. ","")&IF(AND(OR(R7="author_run",R7="author_run+independent",R7="independent_only"),Q7=""),"PERIKSA: isi kelas_dievaluasi. ","")&IF(AND(OR(R7="author_run",R7="author_run+independent",R7="independent_only"),W7=""),"PERIKSA: isi lokasi_bukti. ","")&IF(AND(H7="tidak",R7<>""),"PERIKSA: tanpa teks lengkap, kosongkan kolom evaluasi. ","")) | AC7: include
A8: chenkai-2026-when-agentic-executions-fail-detecting | B8: When Agentic Executions Fail: Detecting and Localizing Runtime Faults from Telemetry | C8: 2026 | D8: E2 | E8: kandidat_agent | F8: primary | G8: https://arxiv.org/abs/2608.14680 | H8: ya | I8: benchmark_measurement | Z8: Makalah kontribusi utamanya adalah benchmark injeksi kesalahan runtime (AgentChaosBench) berisi 275 jejak telemetri Langfuse pada 5 aplikasi multi-agen (MCP & A2A) dengan evaluasi baseline LLM diagnostik (zero-shot LLM baselines); tidak mengusulkan mekanisme pertahanan baru. KODER 1 keliru menetapkannya sebagai defense_primary. | AA8: =IF(I8="","",IF(OR(I8="attack",I8="survey_review",I8="benchmark_measurement",I8="position_other",I8="not_defense"),"n/a",IF(OR(X8="spec_normatif",X8="produksi_bukti_publik"),"L3",IF(ISNUMBER(SEARCH("independent",R8)),"L2",IF(R8="author_run","L1",IF(R8="none","L0","")))))) | AB8: =IF(I8="","",IF(AND(K8="deterministic_policy",M8="ya"),"PERIKSA: deterministic_policy tetapi LLM/ML ada dalam keputusan. ","")&IF(AND(U8="ya",V8=""),"PERIKSA: adaptif=ya wajib ada kutipan. ","")&IF(AND(R8="none",U8<>"n/a_tanpa_evaluasi",U8<>""),"PERIKSA: tanpa evaluasi, adaptif harus n/a. ","")&IF(AND(OR(R8="author_run",R8="author_run+independent",R8="independent_only"),Q8=""),"PERIKSA: isi kelas_dievaluasi. ","")&IF(AND(OR(R8="author_run",R8="author_run+independent",R8="independent_only"),W8=""),"PERIKSA: isi lokasi_bukti. ","")&IF(AND(H8="tidak",R8<>""),"PERIKSA: tanpa teks lengkap, kosongkan kolom evaluasi. ","")) | AC8: include
